Workbook

Sheet Profit Loss-Combined
A1: Technocraft Fashions Limited
A3: Combined Profit & Loss for the Period ended Feb,2026
BD4: Amount in ₹
B5: Amount in ₹ | C5: For April,2025 | G5: Upto May,2025 | J5: Upto May,2025 | K5: For May,2025 | L5: Amravati | M5: Betul | N5: Interunit | O5: Upto June,2025 | P5: For June,2025 | Q5: Amravati | R5: Betul | S5: Interunit | T5: Upto July,2025 | U5: For July,2025 | V5: Amravati | W5: Betul | X5: Interunit | Y5: Upto Aug,2025 | Z5: For Aug,2025 | AA5: Amravati | AB5: Betul | AC5: Interunit | AD5: Upto Sept,2025 | AE5: For Sept,2025 | AF5: Amravati | AG5: Betul | AH5: Interunit | AI5: Upto Oct,2025 | AJ5: For Oct,2025 | AK5: Amravati | AL5: Betul | AM5: Interunit | AN5: Upto Nov ,2025 | AO5: For Nov,2025 | AP5: Amravati | AQ5: Betul | AR5: Interunit | AS5: Upto Dec ,2025 | AT5: For Dec,2025 | AU5: Amravati | AV5: Betul | AW5: Interunit | AX5: Upto Jan ,2026 | AY5: For Jan,2026 | AZ5: Amravati | BA5: Betul | BB5: Interunit | BC5: Upto Feb ,2026 | BD5: For Feb,2026
A6: PARTICULARS | B6: April,2025-Textile | C6: Amravati | D6: Betul | E6: Inter Unit | G6: Amravati | H6: Betul | I6: Inter Unit
A7: INCOME
A8: SALES
A9: SALE LOCAL - MISCELLANEOUS ITEMS | C9: =VLOOKUP(A9,'Profit Loss-Amravati-25-26'!$A$13:$B$190,2,0) -> 21860 | F9: =+B9+C9+D9 -> 21860 | G9: =VLOOKUP(A9,'Profit Loss-Amravati-25-26'!$A$9:$D$190,3,0) -> 21860 | J9: =SUM(G9:I9) -> 21860 | K9: =+H9+G9-F9 -> 0 | L9: =VLOOKUP(A9,'Profit Loss-Amravati-25-26'!$A$9:$F$190,5,0) -> 21860 | O9: =+L9+M9 -> 21860 | P9: =+O9-J9 -> 0 | Q9: =VLOOKUP(A9,'Profit Loss-Amravati-25-26'!$A$9:$H$190,7,0) -> 21860 | T9: =+Q9+R9 -> 21860 | U9: =+T9-O9 -> 0 | V9: =VLOOKUP(A9,'Profit Loss-Amravati-25-26'!$A$9:$J$190,9,0) -> 21860 | Y9: =+V9+W9 -> 21860 | Z9: =+Y9-T9 -> 0 | AA9: =VLOOKUP(A9,'Profit Loss-Amravati-25-26'!$A$9:$L$192,11,0) -> 21860 | AD9: =+AA9+AB9-AC9 -> 21860 | AE9: =+AD9-Y9 -> 0 | AF9: =VLOOKUP(A9,'Profit Loss-Amravati-25-26'!$A$9:$N$192,13,0) -> 21860 | AI9: =+AF9+AG9-AH9 -> 21860 | AJ9: =+AI9-AD9 -> 0 | AK9: =VLOOKUP(A9,'Profit Loss-Amravati-25-26'!$A$9:$P$192,15,0) -> 21860 | AN9: =+AK9+AL9-AM9 -> 21860 | AO9: =+AN9-AI9 -> 0 | AP9: =VLOOKUP(A9,'Profit Loss-Amravati-25-26'!$A$9:$R$192,17,0) -> 21860 | AS9: =+AP9+AQ9-AR9 -> 21860 | AT9: =+AS9-AN9 -> 0 | AU9: =VLOOKUP(A9,'Profit Loss-Amravati-25-26'!$A$9:$T$192,19,0) -> 21860 | AX9: =+AU9+AV9-AW9 -> 21860 | AY9: =+AX9-AS9 -> 0 | AZ9: =VLOOKUP(A9,'Profit Loss-Amravati-25-26'!$A$9:$V$192,21,0) -> 21860 | BC9: =+AZ9+BA9-BB9 -> 21860 | BD9: =+BC9-AX9 -> 0
A10: SALE LOCAL (GARMENT) | C10: =VLOOKUP(A10,'Profit Loss-Amravati-25-26'!$A$13:$B$190,2,0) -> 47838869 | F10: =+B10+C10+D10 -> 47838869 | G10: =VLOOKUP(A10,'Profit Loss-Amravati-25-26'!$A$9:$D$190,3,0) -> 93255699 | J10: =SUM(G10:I10) -> 93255699 | K10: =+H10+G10-F10 -> 45416830 | L10: =VLOOKUP(A10,'Profit Loss-Amravati-25-26'!$A$9:$F$190,5,0) -> 1.4859851e+08 | O10: =+L10+M10 -> 1.4859851e+08 | P10: =+O10-J10 -> 55342806 | Q10: =VLOOKUP(A10,'Profit Loss-Amravati-25-26'!$A$9:$H$190,7,0) -> 2.2662015e+08 | T10: =+Q10+R10 -> 2.2662015e+08 | U10: =+T10-O10 -> 78021644 | V10: =VLOOKUP(A10,'Profit Loss-Amravati-25-26'!$A$9:$J$190,9,0) -> 2.7676371e+08 | Y10: =+V10+W10 -> 2.7676371e+08 | Z10: =+Y10-T10 -> 50143556 | AA10: =VLOOKUP(A10,'Profit Loss-Amravati-25-26'!$A$9:$L$192,11,0) -> 3.6038358e+08 | AD10: =+AA10+AB10-AC10 -> 3.6038358e+08 | AE10: =+AD10-Y10 -> 83619871 | AF10: =VLOOKUP(A10,'Profit Loss-Amravati-25-26'!$A$9:$N$192,13,0) -> 3.919506e+08 | AI10: =+AF10+AG10-AH10 -> 3.919506e+08 | AJ10: =+AI10-AD10 -> 31567025 | AK10: =VLOOKUP(A10,'Profit Loss-Amravati-25-26'!$A$9:$P$192,15,0) -> 4.3805378e+08 | AN10: =+AK10+AL10-AM10 -> 4.3805378e+08 | AO10: =+AN10-AI10 -> 46103174 | AP10: =VLOOKUP(A10,'Profit Loss-Amravati-25-26'!$A$9:$R$192,17,0) -> 5.1824433e+08 | AS10: =+AP10+AQ10-AR10 -> 5.1824433e+08 | AT10: =+AS10-AN10 -> 80190553 | AU10: =VLOOKUP(A10,'Profit Loss-Amravati-25-26'!$A$9:$T$192,19,0) -> 5.9101041e+08 | AX10: =+AU10+AV10-AW10 -> 5.9101041e+08 | AY10: =+AX10-AS10 -> 72766078 | AZ10: =VLOOKUP(A10,'Profit Loss-Amravati-25-26'!$A$9:$V$192,21,0) -> 6.4868176e+08 | BC10: =+AZ10+BA10-BB10 -> 6.4868176e+08 | BD10: =+BC10-AX10 -> 57671352
A11: SALE EXPORT - FABRIC- (SAMPLE) | AU11: =VLOOKUP(A11,'Profit Loss-Amravati-25-26'!$A$9:$T$192,19,0) -> 0 | AX11: =+AU11+AV11-AW11 -> 0 | AY11: =+AX11-AS11 -> 0 | AZ11: =VLOOKUP(A11,'Profit Loss-Amravati-25-26'!$A$9:$V$192,21,0) -> 0 | BC11: =+AZ11+BA11-BB11 -> 0 | BD11: =+BC11-AX11 -> 0
A12: SAMPLE DEVELOPMENT SERVICES | AU12: =VLOOKUP(A12,'Profit Loss-Amravati-25-26'!$A$9:$T$192,19,0) -> 646961 | AX12: =+AU12+AV12-AW12 -> 646961 | AY12: =+AX12-AS12 -> 646961 | AZ12: =VLOOKUP(A12,'Profit Loss-Amravati-25-26'!$A$9:$V$192,21,0) -> 646961 | BC12: =+AZ12+BA12-BB12 -> 646961 | BD12: =+BC12-AX12 -> 0
A13: SALE LOCAL | C13: =VLOOKUP(A13,'Profit Loss-Amravati-25-26'!$A$13:$B$190,2,0) -> 26900 | F13: =+B13+C13+D13 -> 26900 | G13: =VLOOKUP(A13,'Profit Loss-Amravati-25-26'!$A$9:$D$190,3,0) -> 162790 | J13: =SUM(G13:I13) -> 162790 | K13: =+H13+G13-F13 -> 135890 | L13: =VLOOKUP(A13,'Profit Loss-Amravati-25-26'!$A$9:$F$190,5,0) -> 162790 | O13: =+L13+M13 -> 162790 | P13: =+O13-J13 -> 0 | Q13: =VLOOKUP(A13,'Profit Loss-Amravati-25-26'!$A$9:$H$190,7,0) -> 185950 | T13: =+Q13+R13 -> 185950 | U13: =+T13-O13 -> 23160 | V13: =VLOOKUP(A13,'Profit Loss-Amravati-25-26'!$A$9:$J$190,9,0) -> 205290 | Y13: =+V13+W13 -> 205290 | Z13: =+Y13-T13 -> 19340 | AA13: =VLOOKUP(A13,'Profit Loss-Amravati-25-26'!$A$9:$L$192,11,0) -> 439540 | AD13: =+AA13+AB13-AC13 -> 439540 | AE13: =+AD13-Y13 -> 234250 | AF13: =VLOOKUP(A13,'Profit Loss-Amravati-25-26'!$A$9:$N$192,13,0) -> 471500 | AI13: =+AF13+AG13-AH13 -> 471500 | AJ13: =+AI13-AD13 -> 31960 | AK13: =VLOOKUP(A13,'Profit Loss-Amravati-25-26'!$A$9:$P$192,15,0) -> 471500.01 | AN13: =+AK13+AL13-AM13 -> 471500.01 | AO13: =+AN13-AI13 -> 0.01 | AP13: =VLOOKUP(A13,'Profit Loss-Amravati-25-26'!$A$9:$R$192,17,0) -> 471500.01 | AS13: =+AP13+AQ13-AR13 -> 471500.01 | AT13: =+AS13-AN13 -> 0 | AU13: =VLOOKUP(A13,'Profit Loss-Amravati-25-26'!$A$9:$T$192,19,0) -> 471500.01 | AX13: =+AU13+AV13-AW13 -> 471500.01 | AY13: =+AX13-AS13 -> 0 | AZ13: =VLOOKUP(A13,'Profit Loss-Amravati-25-26'!$A$9:$V$192,21,0) -> 471500.01 | BC13: =+AZ13+BA13-BB13 -> 471500.01 | BD13: =+BC13-AX13 -> 0
A14: SALE EXPORT FABRIC | AK14: =VLOOKUP(A14,'Profit Loss-Amravati-25-26'!$A$9:$P$192,15,0) -> 72061522 | AN14: =+AK14+AL14-AM14 -> 72061522 | AO14: =+AN14-AI14 -> 72061522 | AP14: =VLOOKUP(A14,'Profit Loss-Amravati-25-26'!$A$9:$R$192,17,0) -> 150117512 | AS14: =+AP14+AQ14-AR14 -> 150117512 | AT14: =+AS14-AN14 -> 78055990 | AU14: =VLOOKUP(A14,'Profit Loss-Amravati-25-26'!$A$9:$T$192,19,0) -> 150117512 | AX14: =+AU14+AV14-AW14 -> 150117512 | AY14: =+AX14-AS14 -> 0 | AZ14: =VLOOKUP(A14,'Profit Loss-Amravati-25-26'!$A$9:$V$192,21,0) -> 158852699 | BC14: =+AZ14+BA14-BB14 -> 158852699 | BD14: =+BC14-AX14 -> 8735187
A15: SALE EXPORT (GARMENT)) | F15: 0 | G15: =VLOOKUP(A15,'Profit Loss-Amravati-25-26'!$A$9:$D$190,3,0) -> 17488529 | J15: =SUM(G15:I15) -> 17488529 | K15: =+H15+G15-F15 -> 17488529 | L15: =VLOOKUP(A15,'Profit Loss-Amravati-25-26'!$A$9:$F$190,5,0) -> 17488529 | O15: =+L15+M15 -> 17488529 | P15: =+O15-J15 -> 0 | Q15: =VLOOKUP(A15,'Profit Loss-Amravati-25-26'!$A$9:$H$190,7,0) -> 28044991 | T15: =+(Q15+R15)-352327 -> 27692664 | U15: =+T15-O15 -> 10204135 | V15: =VLOOKUP(A15,'Profit Loss-Amravati-25-26'!$A$9:$J$190,9,0) -> 38932993 | Y15: =+(V15+W15)-9215036-352327 -> 29365630 | Z15: =+Y15-T15 -> 1672966 | AA15: =VLOOKUP(A15,'Profit Loss-Amravati-25-26'!$A$9:$L$192,11,0) -> 31936237 | AD15: =+AA15+AB15-AC15 -> 31936237 | AE15: =+AD15-Y15 -> 2570607 | AF15: =VLOOKUP(A15,'Profit Loss-Amravati-25-26'!$A$9:$N$192,13,0) -> 58108673 | AI15: =+AF15+AG15-AH15 -> 58108673 | AJ15: =+AI15-AD15 -> 26172436 | AK15: =VLOOKUP(A15,'Profit Loss-Amravati-25-26'!$A$9:$P$192,15,0) -> 73649850 | AN15: =+AK15+AL15-AM15 -> 73649850 | AO15: =+AN15-AI15 -> 15541177 | AP15: =VLOOKUP(A15,'Profit Loss-Amravati-25-26'!$A$9:$R$192,17,0) -> 84681620 | AS15: =+AP15+AQ15-AR15 -> 84681620 | AT15: =+AS15-AN15 -> 11031770 | AU15: =VLOOKUP(A15,'Profit Loss-Amravati-25-26'!$A$9:$T$192,19,0) -> 84702821 | AX15: =+AU15+AV15-AW15 -> 84702821 | AY15: =+AX15-AS15 -> 21201 | AZ15: =VLOOKUP(A15,'Profit Loss-Amravati-25-26'!$A$9:$V$192,21,0) -> 105750522 | BC15: =+AZ15+BA15-BB15 -> 105750522 | BD15: =+BC15-AX15 -> 21047701
A16: SALE TRADING - LOCAL - GARMENT | Q16: =VLOOKUP(A16,'Profit Loss-Amravati-25-26'!$A$9:$H$190,7,0) -> 1961392 | T16: =+Q16+R16 -> 1961392 | U16: =+T16-O16 -> 1961392 | V16: =VLOOKUP(A16,'Profit Loss-Amravati-25-26'!$A$9:$J$190,9,0) -> 2001211 | Y16: =+V16+W16 -> 2001211 | Z16: =+Y16-T16 -> 39819 | AA16: =VLOOKUP(A16,'Profit Loss-Amravati-25-26'!$A$9:$L$192,11,0) -> 2001211 | AD16: =+AA16+AB16-AC16 -> 2001211 | AE16: =+AD16-Y16 -> 0 | AF16: =VLOOKUP(A16,'Profit Loss-Amravati-25-26'!$A$9:$N$192,13,0) -> 2419148 | AI16: =+AF16+AG16-AH16 -> 2419148 | AJ16: =+AI16-AD16 -> 417937 | AK16: =VLOOKUP(A16,'Profit Loss-Amravati-25-26'!$A$9:$P$192,15,0) -> 2419148 | AN16: =+AK16+AL16-AM16 -> 2419148 | AO16: =+AN16-AI16 -> 0 | AP16: =VLOOKUP(A16,'Profit Loss-Amravati-25-26'!$A$9:$R$192,17,0) -> 2821225 | AS16: =+AP16+AQ16-AR16 -> 2821225 | AT16: =+AS16-AN16 -> 402077 | AU16: =VLOOKUP(A16,'Profit Loss-Amravati-25-26'!$A$9:$T$192,19,0) -> 3094230 | AX16: =+AU16+AV16-AW16 -> 3094230 | AY16: =+AX16-AS16 -> 273005 | AZ16: =VLOOKUP(A16,'Profit Loss-Amravati-25-26'!$A$9:$V$192,21,0) -> 4971595 | BC16: =+AZ16+BA16-BB16 -> 4971595 | BD16: =+BC16-AX16 -> 1877365
A17: SALE TRADING - LOCAL - FABRIC | C17: =VLOOKUP(A17,'Profit Loss-Amravati-25-26'!$A$13:$B$190,2,0) -> 1704310 | F17: =+B17+C17+D17 -> 1704310 | G17: =VLOOKUP(A17,'Profit Loss-Amravati-25-26'!$A$9:$D$190,3,0) -> 1704310 | J17: =SUM(G17:I17) -> 1704310 | K17: =+H17+G17-F17 -> 0 | L17: =VLOOKUP(A17,'Profit Loss-Amravati-25-26'!$A$9:$F$190,5,0) -> 3480367 | O17: =+L17+M17 -> 3480367 | P17: =+O17-J17 -> 1776057 | Q17: =VLOOKUP(A17,'Profit Loss-Amravati-25-26'!$A$9:$H$190,7,0) -> 4008793 | T17: =+Q17+R17 -> 4008793 | U17: =+T17-O17 -> 528426 | V17: =VLOOKUP(A17,'Profit Loss-Amravati-25-26'!$A$9:$J$190,9,0) -> 4930093 | Y17: =+V17+W17 -> 4930093 | Z17: =+Y17-T17 -> 921300 | AA17: =VLOOKUP(A17,'Profit Loss-Amravati-25-26'!$A$9:$L$192,11,0) -> 5699323 | AD17: =+AA17+AB17-AC17 -> 5699323 | AE17: =+AD17-Y17 -> 769230 | AF17: =VLOOKUP(A17,'Profit Loss-Amravati-25-26'!$A$9:$N$192,13,0) -> 5699323 | AI17: =+AF17+AG17-AH17 -> 5699323 | AJ17: =+AI17-AD17 -> 0 | AK17: =VLOOKUP(A17,'Profit Loss-Amravati-25-26'!$A$9:$P$192,15,0) -> 6121968 | AN17: =+AK17+AL17-AM17 -> 6121968 | AO17: =+AN17-AI17 -> 422645 | AP17: =VLOOKUP(A17,'Profit Loss-Amravati-25-26'!$A$9:$R$192,17,0) -> 7995966 | AS17: =+AP17+AQ17-AR17 -> 7995966 | AT17: =+AS17-AN17 -> 1873998 | AU17: =VLOOKUP(A17,'Profit Loss-Amravati-25-26'!$A$9:$T$192,19,0) -> 9757463 | AX17: =+AU17+AV17-AW17 -> 9757463 | AY17: =+AX17-AS17 -> 1761497 | AZ17: =VLOOKUP(A17,'Profit Loss-Amravati-25-26'!$A$9:$V$192,21,0) -> 9760163 | BC17: =+AZ17+BA17-BB17 -> 9760163 | BD17: =+BC17-AX17 -> 2700
A18: SALES (LABOUR JOB) - INTER UNIT | D18: =VLOOKUP(A18,'Profit Loss-Betul-25-26'!$A$9:$B$140,2,0)*0+1501872 -> 1501872 | E18: 1501872 | F18: =+B18+C18+D18-E18 -> 0 | H18: =VLOOKUP(A18,'Profit Loss-Betul-25-26'!$A$9:$D$140,3,0) -> 2501098 | I18: =-H18 -> -2501098 | J18: =SUM(G18:I18) -> 0 | K18: =+H18+G18-F18+I18 -> 0 | M18: =VLOOKUP(A18,'Profit Loss-Betul-25-26'!$A$9:$F$141,5,0) -> 5286179 | N18: =-M18 -> -5286179 | O18: =SUM(L18:N18) -> 0 | P18: =+O18-J18 -> 0 | R18: =VLOOKUP(A18,'Profit Loss-Betul-25-26'!$A$9:$H$141,7,0) -> 9026583 | S18: =-R18 -> -9026583 | T18: =SUM(Q18:S18) -> 0 | U18: =+T18-O18 -> 0 | W18: =VLOOKUP(A18,'Profit Loss-Betul-25-26'!$A$9:$J$141,9,0) -> 12193532 | X18: =-W18 -> -12193532 | Y18: =SUM(V18:X18) -> 0 | Z18: =+Y18-T18 -> 0 | AB18: =VLOOKUP(A18,'Profit Loss-Betul-25-26'!$A$9:$L$141,11,0) -> 15382914 | AC18: =-AB18 -> -15382914 | AD18: =+AA18+AB18+AC18 -> 0 | AE18: =+AD18-Y18 -> 0 | AG18: =VLOOKUP(A18,'Profit Loss-Betul-25-26'!$A$9:$N$141,13,0) -> 16435708 | AH18: =+AG18 -> 16435708 | AI18: =+AF18+AG18-AH18 -> 0 | AJ18: =+AI18-AD18 -> 0 | AL18: =VLOOKUP(A18,'Profit Loss-Betul-25-26'!$A$9:$P$141,15,0) -> 18524580 | AM18: =+AL18 -> 18524580 | AN18: =+AK18+AL18-AM18 -> 0 | AO18: =+AN18-AI18 -> 0 | AQ18: =VLOOKUP(A18,'Profit Loss-Betul-25-26'!$A$9:$R$141,17,0) -> 21712831 | AR18: =+AQ18 -> 21712831 | AS18: =+AP18+AQ18-AR18 -> 0 | AT18: =+AS18-AN18 -> 0 | AV18: =VLOOKUP(A18,'Profit Loss-Betul-25-26'!$A$9:$T$141,19,0) -> 25000388 | AW18: =+AV18 -> 25000388 | AX18: =+AU18+AV18-AW18 -> 0 | AY18: =+AX18-AS18 -> 0 | BA18: =VLOOKUP(A18,'Profit Loss-Betul-25-26'!$A$9:$V$141,21,0) -> 27034065 | BB18: =+BA18 -> 27034065 | BC18: =+AZ18+BA18-BB18 -> 0 | BD18: =+BC18-AX18 -> 0
A19: GROSS SALES | B19: =SUM(B9:B18) -> 0 | C19: =SUM(C9:C18) -> 49591939 | D19: =SUM(D9:D18) -> 1501872 | F19: =SUM(F9:F18) -> 49591939 | G19: =SUM(G9:G18) -> 112633188 | H19: =SUM(H9:H18) -> 2501098 | I19: =SUM(I9:I18) -> -2501098 | J19: =SUM(J9:J18) -> 112633188 | K19: =SUM(K9:K18) -> 63041249 | L19: =SUM(L9:L18) -> 1.6975205e+08 | M19: =SUM(M9:M18) -> 5286179 | ... BD19: =SUM(BD9:BD18) -> 89334305 | BE19: =+BC19-AX19-BD19 -> 0
A20: EXPENSES RELATED TO SALES | L20: =VLOOKUP(A20,'Profit Loss-Amravati-25-26'!$A$9:$F$190,5,0) -> 0 | M20: =VLOOKUP(A20,'Profit Loss-Betul-25-26'!$A$9:$F$141,5,0) -> 0 | Q20: =VLOOKUP(A20,'Profit Loss-Amravati-25-26'!$A$9:$H$190,7,0) -> 0 | R20: =VLOOKUP(A20,'Profit Loss-Betul-25-26'!$A$9:$H$141,7,0) -> 0
A21: DELIVERY CHARGES ON SALE -GARMENT | C21: =VLOOKUP(A21,'Profit Loss-Amravati-25-26'!$A$13:$B$190,2,0) -> 212973.3 | F21: =+B21+C21+D21 -> 212973.3 | G21: =VLOOKUP(A21,'Profit Loss-Amravati-25-26'!$A$9:$D$190,3,0) -> 382533.84 | J21: =SUM(G21:I21) -> 382533.84 | K21: =+H21+G21-F21 -> 169560.54 | L21: =VLOOKUP(A21,'Profit Loss-Amravati-25-26'!$A$9:$F$190,5,0) -> 1381133.8 | O21: =SUM(L21:M21)-79796 -> 1301337.8 | P21: =+O21-J21 -> 918804 | Q21: =VLOOKUP(A21,'Profit Loss-Amravati-25-26'!$A$9:$H$190,7,0) -> 1717980.4 | T21: =+Q21+R21 -> 1717980.4 | U21: =+T21-O21 -> 416642.6 | V21: =VLOOKUP(A21,'Profit Loss-Amravati-25-26'!$A$9:$J$190,9,0) -> 1717980.4 | Y21: =+V21+W21+300000 -> 2017980.4 | Z21: =+Y21-T21 -> 300000 | AA21: =VLOOKUP(A21,'Profit Loss-Amravati-25-26'!$A$9:$L$192,11,0) -> 2180159.7 | AD21: =+AA21+AB21-AC21 -> 2180159.7 | AE21: =+AD21-Y21 -> 162179.23 | AF21: =VLOOKUP(A21,'Profit Loss-Amravati-25-26'!$A$9:$N$192,13,0) -> 2862982.8 | AG21: =VLOOKUP(A21,'Profit Loss-Betul-25-26'!$A$9:$N$141,13,0) -> 18000 | AI21: =+AF21+AG21-AH21 -> 2880982.8 | AJ21: =+AI21-AD21 -> 700823.14 | AK21: =VLOOKUP(A21,'Profit Loss-Amravati-25-26'!$A$9:$P$192,15,0) -> 3241559.8 | AL21: =VLOOKUP(A21,'Profit Loss-Betul-25-26'!$A$9:$P$141,15,0) -> 6000 | AN21: =+AK21+AL21-AM21 -> 3247559.8 | AO21: =+AN21-AI21 -> 366577.02 | AP21: =VLOOKUP(A21,'Profit Loss-Amravati-25-26'!$A$9:$R$192,17,0) -> 3456402.8 | AQ21: =VLOOKUP(A21,'Profit Loss-Betul-25-26'!$A$9:$R$141,17,0) -> 6000 | AS21: =+AP21+AQ21-AR21 -> 3462402.8 | AT21: =+AS21-AN21 -> 214843 | AU21: =VLOOKUP(A21,'Profit Loss-Amravati-25-26'!$A$9:$T$192,19,0) -> 3906763.1 | AV21: =VLOOKUP(A21,'Profit Loss-Betul-25-26'!$A$9:$T$141,19,0) -> 6000 | AX21: =+AU21+AV21-AW21 -> 3912763.1 | AY21: =+AX21-AS21 -> 450360.24 | AZ21: =VLOOKUP(A21,'Profit Loss-Amravati-25-26'!$A$9:$V$192,21,0) -> 4065545.8 | BA21: =VLOOKUP(A21,'Profit Loss-Betul-25-26'!$A$9:$V$141,21,0) -> 6000 | BC21: =+AZ21+BA21-BB21 -> 4071545.8 | BD21: =+BC21-AX21 -> 158782.69
A22: DELIVERY CHARGES ON SALES | C22: =VLOOKUP(A22,'Profit Loss-Amravati-25-26'!$A$13:$B$190,2,0) -> 15803 | F22: =+B22+C22+D22 -> 15803 | G22: =VLOOKUP(A22,'Profit Loss-Amravati-25-26'!$A$9:$D$190,3,0) -> 304524.24 | J22: =SUM(G22:I22) -> 304524.24 | K22: =+H22+G22-F22 -> 288721.24 | L22: =VLOOKUP(A22,'Profit Loss-Amravati-25-26'!$A$9:$F$190,5,0) -> 486121.24 | M22: =VLOOKUP(A22,'Profit Loss-Betul-25-26'!$A$9:$F$141,5,0) -> 12500 | O22: =SUM(L22:M22) -> 498621.24 | P22: =+O22-J22 -> 194097 | Q22: =VLOOKUP(A22,'Profit Loss-Amravati-25-26'!$A$9:$H$190,7,0)-31103 -> 2178427.2 | R22: =VLOOKUP(A22,'Profit Loss-Betul-25-26'!$A$9:$H$141,7,0) -> 12500 | T22: =+Q22+R22 -> 2190927.2 | U22: =+T22-O22 -> 1692306 | V22: =VLOOKUP(A22,'Profit Loss-Amravati-25-26'!$A$9:$J$190,9,0) -> 2668553.2 | W22: =VLOOKUP(A22,'Profit Loss-Betul-25-26'!$A$9:$J$141,9,0) -> 12500 | Y22: =+V22+W22 -> 2681053.2 | Z22: =+Y22-T22 -> 490125.98 | AA22: =VLOOKUP(A22,'Profit Loss-Amravati-25-26'!$A$9:$L$192,11,0) -> 3139356.7 | AB22: =VLOOKUP(A22,'Profit Loss-Betul-25-26'!$A$9:$L$141,11,0) -> 12500 | AD22: =+AA22+AB22-AC22 -> 3151856.7 | AE22: =+AD22-Y22 -> 470803.52 | AF22: =VLOOKUP(A22,'Profit Loss-Amravati-25-26'!$A$9:$N$192,13,0) -> 3321370.4 | AG22: =VLOOKUP(A22,'Profit Loss-Betul-25-26'!$A$9:$N$141,13,0) -> 12500 | AI22: =+AF22+AG22-AH22 -> 3333870.4 | AJ22: =+AI22-AD22 -> 182013.69 | AK22: =VLOOKUP(A22,'Profit Loss-Amravati-25-26'!$A$9:$P$192,15,0) -> 3628852.1 | AL22: =VLOOKUP(A22,'Profit Loss-Betul-25-26'!$A$9:$P$141,15,0) -> 12500 | AN22: =+AK22+AL22-AM22 -> 3641352.1 | AO22: =+AN22-AI22 -> 307481.71 | AP22: =VLOOKUP(A22,'Profit Loss-Amravati-25-26'!$A$9:$R$192,17,0) -> 4645461 | AQ22: =VLOOKUP(A22,'Profit Loss-Betul-25-26'!$A$9:$R$141,17,0) -> 12500 | AS22: =+AP22+AQ22-AR22 -> 4657961 | AT22: =+AS22-AN22 -> 1016608.9 | AU22: =VLOOKUP(A22,'Profit Loss-Amravati-25-26'!$A$9:$T$192,19,0) -> 5114840.2 | AV22: =VLOOKUP(A22,'Profit Loss-Betul-25-26'!$A$9:$T$141,19,0) -> 12500 | AX22: =+AU22+AV22-AW22 -> 5127340.2 | AY22: =+AX22-AS22 -> 469379.11 | AZ22: =VLOOKUP(A22,'Profit Loss-Amravati-25-26'!$A$9:$V$192,21,0) -> 5627752.2 | BA22: =VLOOKUP(A22,'Profit Loss-Betul-25-26'!$A$9:$V$141,21,0) -> 12500 | BC22: =+AZ22+BA22-BB22 -> 5640252.2 | BD22: =+BC22-AX22 -> 512912
A23: DOCUMENTATION CHARGES | F23: =+B23+C23+D23 -> 0 | J23: =SUM(G23:I23) -> 0 | K23: =+H23+G23-F23 -> 0 | L23: =VLOOKUP(A23,'Profit Loss-Amravati-25-26'!$A$9:$F$190,5,0) -> 0 | O23: =SUM(L23:M23) -> 0 | P23: =+O23-J23 -> 0 | Q23: =VLOOKUP(A23,'Profit Loss-Amravati-25-26'!$A$9:$H$190,7,0) -> 0 | T23: =SUM(Q23:R23) -> 0 | U23: =+T23-O23 -> 0 | V23: =VLOOKUP(A23,'Profit Loss-Amravati-25-26'!$A$9:$J$190,9,0) -> 0 | Y23: =SUM(V23:W23) -> 0 | Z23: =+Y23-T23 -> 0 | AA23: =VLOOKUP(A23,'Profit Loss-Amravati-25-26'!$A$9:$L$192,11,0) -> 0 | AD23: =+AA23+AB23-AC23 -> 0 | AE23: =+AD23-Y23 -> 0 | AF23: =VLOOKUP(A23,'Profit Loss-Amravati-25-26'!$A$9:$N$192,13,0) -> 0 | AI23: =+AF23+AG23-AH23 -> 0 | AJ23: =+AI23-AD23 -> 0 | AK23: =VLOOKUP(A23,'Profit Loss-Amravati-25-26'!$A$9:$P$192,15,0) -> 0 | AN23: =+AK23+AL23-AM23 -> 0 | AO23: =+AN23-AI23 -> 0 | AP23: =VLOOKUP(A23,'Profit Loss-Amravati-25-26'!$A$9:$R$192,17,0) -> 0 | AS23: =+AP23+AQ23-AR23 -> 0 | AT23: =+AS23-AN23 -> 0 | AU23: =VLOOKUP(A23,'Profit Loss-Amravati-25-26'!$A$9:$T$192,19,0) -> 0 | AX23: =+AU23+AV23-AW23 -> 0 | AY23: =+AX23-AS23 -> 0 | AZ23: =VLOOKUP(A23,'Profit Loss-Amravati-25-26'!$A$9:$V$192,21,0) -> 0 | BC23: =+AZ23+BA23-BB23 -> 0 | BD23: =+BC23-AX23 -> 0
A24: EXPORT EXPENSES | F24: =+B24+C24+D24 -> 0 | J24: =SUM(G24:I24) -> 0 | K24: =+H24+G24-F24 -> 0 | L24: =VLOOKUP(A24,'Profit Loss-Amravati-25-26'!$A$9:$F$190,5,0)*0 -> 0 | O24: =SUM(L24:M24) -> 0 | P24: =+O24-J24 -> 0 | Q24: =VLOOKUP(A24,'Profit Loss-Amravati-25-26'!$A$9:$H$190,7,0)-256403 -> 0.22 | T24: =SUM(Q24:R24) -> 0.22 | U24: =+T24-O24 -> 0.22 | V24: =VLOOKUP(A24,'Profit Loss-Amravati-25-26'!$A$9:$J$190,9,0)*0 -> 0 | Y24: =SUM(V24:W24) -> 0 | Z24: =+Y24-T24 -> -0.22 | AA24: =VLOOKUP(A24,'Profit Loss-Amravati-25-26'!$A$9:$L$192,11,0)-461456 -> 13498 | AD24: =+AA24+AB24-AC24-13498 -> 0 | AE24: =+AD24-Y24 -> 0 | AF24: =VLOOKUP(A24,'Profit Loss-Amravati-25-26'!$A$9:$N$192,13,0) -> 659088 | AJ24: =+AI24-AD24 -> 0 | AK24: =VLOOKUP(A24,'Profit Loss-Amravati-25-26'!$A$9:$P$192,15,0) -> 1150110.2 | AO24: =+AN24-AI24 -> 0 | AP24: =VLOOKUP(A24,'Profit Loss-Amravati-25-26'!$A$9:$R$192,17,0) -> 1796205.2 | AT24: =+AS24-AN24 -> 0 | AU24: =VLOOKUP(A24,'Profit Loss-Amravati-25-26'!$A$9:$T$192,19,0) -> 1808425 | AY24: =+AX24-AS24 -> 0 | AZ24: =VLOOKUP(A24,'Profit Loss-Amravati-25-26'!$A$9:$V$192,21,0)*0 -> 0 | BD24: =+BC24-AX24 -> 0
A25: TERMINAL HANDLING CHARGES | F25: =+B25+C25+D25 -> 0 | J25: =SUM(G25:I25) -> 0 | K25: =+H25+G25-F25 -> 0 | L25: =VLOOKUP(A25,'Profit Loss-Amravati-25-26'!$A$9:$F$190,5,0) -> 0 | O25: =SUM(L25:M25) -> 0 | P25: =+O25-J25 -> 0 | Q25: =VLOOKUP(A25,'Profit Loss-Amravati-25-26'!$A$9:$H$190,7,0) -> 0 | T25: =SUM(Q25:R25) -> 0 | U25: =+T25-O25 -> 0 | V25: =VLOOKUP(A25,'Profit Loss-Amravati-25-26'!$A$9:$J$190,9,0) -> 0 | Y25: =SUM(V25:W25) -> 0 | Z25: =+Y25-T25 -> 0 | AA25: =VLOOKUP(A25,'Profit Loss-Amravati-25-26'!$A$9:$L$192,11,0) -> 0 | AD25: =+AA25+AB25-AC25 -> 0 | AE25: =+AD25-Y25 -> 0 | AF25: =VLOOKUP(A25,'Profit Loss-Amravati-25-26'!$A$9:$N$192,13,0) -> 0 | AI25: =+AF25+AG25-AH25 -> 0 | AJ25: =+AI25-AD25 -> 0 | AK25: =VLOOKUP(A25,'Profit Loss-Amravati-25-26'!$A$9:$P$192,15,0) -> 0 | AN25: =+AK25+AL25-AM25 -> 0 | AO25: =+AN25-AI25 -> 0 | AS25: =+AP25+AQ25-AR25 -> 0 | AT25: =+AS25-AN25 -> 0 | AU25: =VLOOKUP(A25,'Profit Loss-Amravati-25-26'!$A$9:$T$192,19,0) -> 0 | AX25: =+AU25+AV25-AW25 -> 0 | AY25: =+AX25-AS25 -> 0 | AZ25: =VLOOKUP(A25,'Profit Loss-Amravati-25-26'!$A$9:$V$192,21,0) -> 0 | BC25: =+AZ25+BA25-BB25 -> 0 | BD25: =+BC25-AX25 -> 0
A26: FREIGHT ON EXPORT - (AIR) | V26: =VLOOKUP(A26,'Profit Loss-Amravati-25-26'!$A$9:$J$190,9,0) -> 0 | Y26: =SUM(V26:W26) -> 0 | Z26: =+Y26-T26 -> 0 | AA26: =VLOOKUP(A26,'Profit Loss-Amravati-25-26'!$A$9:$L$192,11,0) -> 0 | AD26: =+AA26+AB26-AC26 -> 0 | AE26: =+AD26-Y26 -> 0 | AF26: =VLOOKUP(A26,'Profit Loss-Amravati-25-26'!$A$9:$N$192,13,0) -> 0 | AI26: =+AF26+AG26-AH26 -> 0 | AJ26: =+AI26-AD26 -> 0 | AK26: =VLOOKUP(A26,'Profit Loss-Amravati-25-26'!$A$9:$P$192,15,0) -> 0 | AN26: =+AK26+AL26-AM26 -> 0 | AO26: =+AN26-AI26 -> 0 | AS26: =+AP26+AQ26-AR26 -> 0 | AT26: =+AS26-AN26 -> 0 | AU26: =VLOOKUP(A26,'Profit Loss-Amravati-25-26'!$A$9:$T$192,19,0) -> 0 | AX26: =+AU26+AV26-AW26 -> 0 | AY26: =+AX26-AS26 -> 0 | AZ26: =VLOOKUP(A26,'Profit Loss-Amravati-25-26'!$A$9:$V$192,21,0) -> 0 | BC26: =+AZ26+BA26-BB26 -> 0 | BD26: =+BC26-AX26 -> 0
A27: CLEARING CHARGES ON EXPORT | F27: =+B27+C27+D27 -> 0 | J27: =SUM(G27:I27) -> 0 | K27: =+H27+G27-F27 -> 0 | L27: =VLOOKUP(A27,'Profit Loss-Amravati-25-26'!$A$9:$F$190,5,0) -> 0 | O27: =SUM(L27:M27) -> 0 | P27: =+O27-J27 -> 0 | Q27: =VLOOKUP(A27,'Profit Loss-Amravati-25-26'!$A$9:$H$190,7,0) -> 0 | T27: =SUM(Q27:R27) -> 0 | U27: =+T27-O27 -> 0 | V27: =VLOOKUP(A27,'Profit Loss-Amravati-25-26'!$A$9:$J$190,9,0) -> 0 | Y27: =SUM(V27:W27) -> 0 | Z27: =+Y27-T27 -> 0 | AA27: =VLOOKUP(A27,'Profit Loss-Amravati-25-26'!$A$9:$L$192,11,0) -> 0 | AD27: =+AA27+AB27-AC27 -> 0 | AE27: =+AD27-Y27 -> 0 | AF27: =VLOOKUP(A27,'Profit Loss-Amravati-25-26'!$A$9:$N$192,13,0) -> 0 | AI27: =+AF27+AG27-AH27 -> 0 | AJ27: =+AI27-AD27 -> 0 | AK27: =VLOOKUP(A27,'Profit Loss-Amravati-25-26'!$A$9:$P$192,15,0) -> 0 | AN27: =+AK27+AL27-AM27 -> 0 | AO27: =+AN27-AI27 -> 0 | AS27: =+AP27+AQ27-AR27 -> 0 | AT27: =+AS27-AN27 -> 0 | AU27: =VLOOKUP(A27,'Profit Loss-Amravati-25-26'!$A$9:$T$192,19,0) -> 0 | AX27: =+AU27+AV27-AW27 -> 0 | AY27: =+AX27-AS27 -> 0 | AZ27: =VLOOKUP(A27,'Profit Loss-Amravati-25-26'!$A$9:$V$192,21,0) -> 0 | BC27: =+AZ27+BA27-BB27 -> 0 | BD27: =+BC27-AX27 -> 0
A28: DETENTION CHARGES ON EXPORT | F28: =+B28+C28+D28 -> 0 | J28: =SUM(G28:I28) -> 0 | K28: =+H28+G28-F28 -> 0 | L28: =VLOOKUP(A28,'Profit Loss-Amravati-25-26'!$A$9:$F$190,5,0) -> 0 | O28: =SUM(L28:M28) -> 0 | P28: =+O28-J28 -> 0 | Q28: =VLOOKUP(A28,'Profit Loss-Amravati-25-26'!$A$9:$H$190,7,0) -> 0 | T28: =SUM(Q28:R28) -> 0 | U28: =+T28-O28 -> 0 | V28: =VLOOKUP(A28,'Profit Loss-Amravati-25-26'!$A$9:$J$190,9,0) -> 0 | Y28: =SUM(V28:W28) -> 0 | Z28: =+Y28-T28 -> 0 | AA28: =VLOOKUP(A28,'Profit Loss-Amravati-25-26'!$A$9:$L$192,11,0) -> 0 | AD28: =+AA28+AB28-AC28 -> 0 | AE28: =+AD28-Y28 -> 0 | AF28: =VLOOKUP(A28,'Profit Loss-Amravati-25-26'!$A$9:$N$192,13,0) -> 0 | AI28: =+AF28+AG28-AH28 -> 0 | AJ28: =+AI28-AD28 -> 0 | AK28: =VLOOKUP(A28,'Profit Loss-Amravati-25-26'!$A$9:$P$192,15,0) -> 0 | AN28: =+AK28+AL28-AM28 -> 0 | AO28: =+AN28-AI28 -> 0 | AS28: =+AP28+AQ28-AR28 -> 0 | AT28: =+AS28-AN28 -> 0 | AU28: =VLOOKUP(A28,'Profit Loss-Amravati-25-26'!$A$9:$T$192,19,0) -> 0 | AX28: =+AU28+AV28-AW28 -> 0 | AY28: =+AX28-AS28 -> 0 | AZ28: =VLOOKUP(A28,'Profit Loss-Amravati-25-26'!$A$9:$V$192,21,0) -> 0 | BC28: =+AZ28+BA28-BB28 -> 0 | BD28: =+BC28-AX28 -> 0
A29: INSURANCE FOR EXPORT | F29: =+B29+C29+D29 -> 0 | J29: =SUM(G29:I29) -> 0 | K29: =+H29+G29-F29 -> 0 | O29: =SUM(L29:M29) -> 0 | P29: =+O29-J29 -> 0 | T29: =SUM(Q29:R29) -> 0 | U29: =+T29-O29 -> 0 | Y29: =SUM(V29:W29) -> 0 | Z29: =+Y29-T29 -> 0 | AD29: =+AA29+AB29-AC29 -> 0 | AE29: =+AD29-Y29 -> 0 | AI29: =+AF29+AG29-AH29 -> 0 | AJ29: =+AI29-AD29 -> 0 | AN29: =+AK29+AL29-AM29 -> 0 | AO29: =+AN29-AI29 -> 0 | AS29: =+AP29+AQ29-AR29 -> 0 | AT29: =+AS29-AN29 -> 0 | AU29: =VLOOKUP(A29,'Profit Loss-Amravati-25-26'!$A$9:$T$192,19,0) -> 0 | AX29: =+AU29+AV29-AW29 -> 0 | AY29: =+AX29-AS29 -> 0 | AZ29: =VLOOKUP(A29,'Profit Loss-Amravati-25-26'!$A$9:$V$192,21,0) -> 0 | BC29: =+AZ29+BA29-BB29 -> 0 | BD29: =+BC29-AX29 -> 0
A30: DETENTION CHARGES ON TRANSPORT | F30: =+B30+C30+D30 -> 0 | J30: =SUM(G30:I30) -> 0 | K30: =+H30+G30-F30 -> 0 | O30: =SUM(L30:M30) -> 0 | P30: =+O30-J30 -> 0 | T30: =SUM(Q30:R30) -> 0 | U30: =+T30-O30 -> 0 | Y30: =SUM(V30:W30) -> 0 | Z30: =+Y30-T30 -> 0 | AD30: =+AA30+AB30-AC30 -> 0 | AE30: =+AD30-Y30 -> 0 | AI30: =+AF30+AG30-AH30 -> 0 | AJ30: =+AI30-AD30 -> 0 | AN30: =+AK30+AL30-AM30 -> 0 | AO30: =+AN30-AI30 -> 0 | AS30: =+AP30+AQ30-AR30 -> 0 | AT30: =+AS30-AN30 -> 0 | AX30: =+AU30+AV30-AW30 -> 0 | AY30: =+AX30-AS30 -> 0 | BC30: =+AZ30+BA30-BB30 -> 0 | BD30: =+BC30-AX30 -> 0
A31: COOLIE & CARTAGE ON SALES | Y31: =SUM(V31:W31) -> 0 | Z31: =+Y31-T31 -> 0 | AA31: =VLOOKUP(A31,'Profit Loss-Amravati-25-26'!$A$9:$L$192,11,0) -> 0 | AD31: =+AA31+AB31-AC31 -> 0 | AE31: =+AD31-Y31 -> 0 | AF31: =VLOOKUP(A31,'Profit Loss-Amravati-25-26'!$A$9:$N$192,13,0) -> 0 | AI31: =+AF31+AG31-AH31 -> 0 | AJ31: =+AI31-AD31 -> 0 | AK31: =VLOOKUP(A31,'Profit Loss-Amravati-25-26'!$A$9:$P$192,15,0) -> 0 | AN31: =+AK31+AL31-AM31 -> 0 | AO31: =+AN31-AI31 -> 0 | AS31: =+AP31+AQ31-AR31 -> 0 | AT31: =+AS31-AN31 -> 0 | AU31: =VLOOKUP(A31,'Profit Loss-Amravati-25-26'!$A$9:$T$192,19,0) -> 0 | AX31: =+AU31+AV31-AW31 -> 0 | AY31: =+AX31-AS31 -> 0 | AZ31: =VLOOKUP(A31,'Profit Loss-Amravati-25-26'!$A$9:$V$192,21,0) -> 0 | BC31: =+AZ31+BA31-BB31 -> 0 | BD31: =+BC31-AX31 -> 0
A32: FREIGHT & OTHER CAHRGES ON EXPORT | F32: 0 | G32: =278950.22+8556 -> 287506.22 | J32: =278950.22+8556 -> 287506.22 | K32: =278950.22+8556 -> 287506.22 | L32: 207710 | O32: =SUM(L32:M32)+79796 -> 287506 | P32: =+O32-J32 -> -0.22 | Q32: =256403+31103 -> 287506 | T32: =SUM(Q32:R32) -> 287506 | U32: =+T32-O32 -> 0 | V32: 413637 | Y32: =SUM(V32:W32) -> 413637 | Z32: =+Y32-T32 -> 126131 | AA32: 461456 | AD32: =+AA32+AB32-AC32+13498 -> 474954 | AE32: =+AD32-Y32 -> 61317 | AI32: =+AF32+AG32-AH32+AF24 -> 659088 | AJ32: =+AI32-AD32 -> 184134 | AN32: =+AK32+AL32-AM32+AK24 -> 1150110.2 | AO32: =+AN32-AI32 -> 491022.22 | AS32: =+AP32+AQ32-AR32+AP24 -> 1796205.2 | AT32: =+AS32-AN32 -> 646095 | AX32: =+AU32+AV32-AW32+AU24 -> 1808425 | AY32: =+AX32-AS32 -> 12219.8 | AZ32: 1974917 | BC32: =+AZ32+BA32-BB32+AZ24 -> 1974917 | BD32: =+BC32-AX32 -> 166491.98
A33: PACKING EXPENSES | C33: =VLOOKUP(A33,'Profit Loss-Amravati-25-26'!$A$13:$B$190,2,0) -> 370 | F33: =+B33+C33+D33 -> 370 | G33: =VLOOKUP(A33,'Profit Loss-Amravati-25-26'!$A$9:$D$190,3,0) -> 370 | J33: =SUM(G33:I33) -> 370 | K33: =+H33+G33-F33 -> 0 | L33: =VLOOKUP(A33,'Profit Loss-Amravati-25-26'!$A$9:$F$190,5,0) -> 1170 | O33: =SUM(L33:M33) -> 1170 | P33: =+O33-J33 -> 800 | Q33: =VLOOKUP(A33,'Profit Loss-Amravati-25-26'!$A$9:$H$190,7,0) -> 1170 | T33: =+Q33+R33 -> 1170 | U33: =+T33-O33 -> 0 | V33: =VLOOKUP(A33,'Profit Loss-Amravati-25-26'!$A$9:$J$190,9,0) -> 1170 | Y33: =+V33+W33 -> 1170 | Z33: =+Y33-T33 -> 0 | AA33: =VLOOKUP(A33,'Profit Loss-Amravati-25-26'!$A$9:$L$192,11,0) -> 1170 | AD33: =+AA33+AB33-AC33 -> 1170 | AE33: =+AD33-Y33 -> 0 | AF33: =VLOOKUP(A33,'Profit Loss-Amravati-25-26'!$A$9:$N$192,13,0) -> 2270 | AI33: =+AF33+AG33-AH33 -> 2270 | AJ33: =+AI33-AD33 -> 1100 | AK33: =VLOOKUP(A33,'Profit Loss-Amravati-25-26'!$A$9:$P$192,15,0) -> 2470 | AN33: =+AK33+AL33-AM33 -> 2470 | AO33: =+AN33-AI33 -> 200 | AP33: =VLOOKUP(A33,'Profit Loss-Amravati-25-26'!$A$9:$R$192,17,0) -> 3275 | AS33: =+AP33+AQ33-AR33 -> 3275 | AT33: =+AS33-AN33 -> 805 | AU33: =VLOOKUP(A33,'Profit Loss-Amravati-25-26'!$A$9:$T$192,19,0) -> 3275 | AX33: =+AU33+AV33-AW33 -> 3275 | AY33: =+AX33-AS33 -> 0 | AZ33: =VLOOKUP(A33,'Profit Loss-Amravati-25-26'!$A$9:$V$192,21,0) -> 3275 | BC33: =+AZ33+BA33-BB33 -> 3275 | BD33: =+BC33-AX33 -> 0
A34: MARKETING DEVELOPMENT ASSISTANCE | AA34: =VLOOKUP(A34,'Profit Loss-Amravati-25-26'!$A$9:$L$192,11,0) -> 88549 | AD34: =+AA34+AB34-AC34 -> 88549 | AE34: =+AD34-Y34 -> 88549 | AF34: =VLOOKUP(A34,'Profit Loss-Amravati-25-26'!$A$9:$N$192,13,0) -> 88549 | AI34: =+AF34+AG34-AH34 -> 88549 | AJ34: =+AI34-AD34 -> 0 | AK34: =VLOOKUP(A34,'Profit Loss-Amravati-25-26'!$A$9:$P$192,15,0) -> 88549 | AN34: =+AK34+AL34-AM34 -> 88549 | AO34: =+AN34-AI34 -> 0 | AP34: =VLOOKUP(A34,'Profit Loss-Amravati-25-26'!$A$9:$R$192,17,0) -> 88549 | AS34: =+AP34+AQ34-AR34 -> 88549 | AT34: =+AS34-AN34 -> 0 | AU34: =VLOOKUP(A34,'Profit Loss-Amravati-25-26'!$A$9:$T$192,19,0) -> 88549 | AX34: =+AU34+AV34-AW34 -> 88549 | AY34: =+AX34-AS34 -> 0 | AZ34: =VLOOKUP(A34,'Profit Loss-Amravati-25-26'!$A$9:$V$192,21,0) -> 88549 | BC34: =+AZ34+BA34-BB34 -> 88549 | BD34: =+BC34-AX34 -> 0
A35: BUSINESS SUPPORT SERVICES | F35: =+B35+C35+D35 -> 0 | G35: =VLOOKUP(A35,'Profit Loss-Amravati-25-26'!$A$9:$D$190,3,0) -> 184166 | J35: =SUM(G35:I35) -> 184166 | K35: =+H35+G35-F35 -> 184166 | L35: =VLOOKUP(A35,'Profit Loss-Amravati-25-26'!$A$9:$F$190,5,0) -> 183672 | O35: =SUM(L35:M35) -> 183672 | P35: =+O35-J35 -> -494 | Q35: =VLOOKUP(A35,'Profit Loss-Amravati-25-26'!$A$9:$H$190,7,0) -> 183672 | T35: =+Q35+R35 -> 183672 | U35: =+T35-O35 -> 0 | V35: =VLOOKUP(A35,'Profit Loss-Amravati-25-26'!$A$9:$J$190,9,0) -> 183672 | Y35: =+V35+W35 -> 183672 | Z35: =+Y35-T35 -> 0 | AA35: =VLOOKUP(A35,'Profit Loss-Amravati-25-26'!$A$9:$L$192,11,0) -> 190161 | AD35: =+AA35+AB35-AC35 -> 190161 | AE35: =+AD35-Y35 -> 6489 | AF35: =VLOOKUP(A35,'Profit Loss-Amravati-25-26'!$A$9:$N$192,13,0) -> 190161 | AI35: =+AF35+AG35-AH35 -> 190161 | AJ35: =+AI35-AD35 -> 0 | AK35: =VLOOKUP(A35,'Profit Loss-Amravati-25-26'!$A$9:$P$192,15,0) -> 3927287.8 | AN35: =+AK35+AL35-AM35 -> 3927287.8 | AO35: =+AN35-AI35 -> 3737126.8 | AP35: =VLOOKUP(A35,'Profit Loss-Amravati-25-26'!$A$9:$R$192,17,0) -> 7846069 | AS35: =+AP35+AQ35-AR35 -> 7846069 | AT35: =+AS35-AN35 -> 3918781.2 | AU35: =VLOOKUP(A35,'Profit Loss-Amravati-25-26'!$A$9:$T$192,19,0) -> 7846069 | AX35: =+AU35+AV35-AW35 -> 7846069 | AY35: =+AX35-AS35 -> 0 | AZ35: =VLOOKUP(A35,'Profit Loss-Amravati-25-26'!$A$9:$V$192,21,0) -> 8387918.4 | BC35: =+AZ35+BA35-BB35 -> 8387918.4 | BD35: =+BC35-AX35 -> 541849.43
A36: COMMISSION/BROKERAGE | F36: =+B36+C36+D36 -> 0 | J36: =SUM(G36:I36) -> 0 | K36: =+H36+G36-F36 -> 0 | O36: =SUM(L36:M36) -> 0 | P36: =+O36-J36 -> 0 | T36: =SUM(Q36:R36) -> 0 | U36: =+T36-O36 -> 0 | Y36: =SUM(V36:W36) -> 0 | Z36: =+Y36-T36 -> 0 | AD36: =+AA36+AB36-AC36 -> 0 | AE36: =+AD36-Y36 -> 0 | AI36: =+AF36+AG36-AH36 -> 0 | AJ36: =+AI36-AD36 -> 0 | AK36: =VLOOKUP(A36,'Profit Loss-Amravati-25-26'!$A$9:$P$192,15,0) -> 70000 | AN36: =+AK36+AL36-AM36 -> 70000 | AO36: =+AN36-AI36 -> 70000 | AP36: =VLOOKUP(A36,'Profit Loss-Amravati-25-26'!$A$9:$R$192,17,0) -> 70000 | AS36: =+AP36+AQ36-AR36 -> 70000 | AT36: =+AS36-AN36 -> 0 | AU36: =VLOOKUP(A36,'Profit Loss-Amravati-25-26'!$A$9:$T$192,19,0) -> 70000 | AX36: =+AU36+AV36-AW36 -> 70000 | AY36: =+AX36-AS36 -> 0 | AZ36: =VLOOKUP(A36,'Profit Loss-Amravati-25-26'!$A$9:$V$192,21,0) -> 70000 | BC36: =+AZ36+BA36-BB36 -> 70000 | BD36: =+BC36-AX36 -> 0
A37: TOTAL EXPENSES RELATED TO SALES | B37: =SUM(B21:B36) -> 0 | C37: =SUM(C21:C36) -> 229146.3 | D37: =SUM(D21:D36) -> 0 | F37: =SUM(F21:F36) -> 229146.3 | G37: =SUM(G21:G36) -> 1159100.3 | H37: =SUM(H21:H36) -> 0 | J37: =SUM(J21:J36) -> 1159100.3 | K37: =SUM(K21:K36) -> 929954 | L37: =SUM(L21:L36) -> 2259807.1 | M37: =SUM(M21:M36) -> 12500 | O37: =SUM(O21:O36) -> 2272307.1 | P37: =SUM(P21:P36) -> 1113206.8 | Q37: =SUM(Q21:Q36) -> 4368755.9 | R37: =SUM(R21:R36) -> 12500 | T37: =SUM(T21:T36) -> 4381255.9 | U37: =SUM(U21:U36) -> 2108948.8 | V37: =SUM(V21:V36) -> 4985012.7 | W37: =SUM(W21:W36) -> 12500 | Y37: =SUM(Y21:Y36) -> 5297512.7 | Z37: =SUM(Z21:Z36) -> 916256.76 | AA37: =SUM(AA21:AA36) -> 6074350.4 | AB37: =SUM(AB21:AB36) -> 12500 | AD37: =SUM(AD21:AD36) -> 6086850.4 | AE37: =SUM(AE21:AE36) -> 789337.75 | AF37: =SUM(AF21:AF36) -> 7124421.2 | AG37: =SUM(AG21:AG36) -> 30500 | AI37: =SUM(AI21:AI36) -> 7154921.2 | AJ37: =SUM(AJ21:AJ36) -> 1068070.8 | AK37: =SUM(AK21:AK36) -> 12108829 | AL37: =SUM(AL21:AL36) -> 18500 | AN37: =SUM(AN21:AN36) -> 12127329 | AO37: =SUM(AO21:AO36) -> 4972407.7 | AP37: =SUM(AP21:AP36) -> 17905962 | AQ37: =SUM(AQ21:AQ36) -> 18500 | AS37: =SUM(AS21:AS36) -> 17924462 | AT37: =SUM(AT21:AT36) -> 5797133.1 | AU37: =SUM(AU21:AU36) -> 18837921 | AV37: =SUM(AV21:AV36) -> 18500 | AX37: =SUM(AX21:AX36) -> 18856421 | AY37: =SUM(AY21:AY36) -> 931959.15 | AZ37: =SUM(AZ21:AZ36) -> 20217957 | BA37: =SUM(BA21:BA36) -> 18500 | BC37: =SUM(BC21:BC36) -> 20236457 | BD37: =SUM(BD21:BD36) -> 1380036.1 | BE37: =+BC37-AX37-BD37 -> -1.8626451e-09
A38: NET SALES | B38: =B19-B37 -> 0 | C38: =C19-C37 -> 49362792 | D38: =D19-D37 -> 1501872 | F38: =F19-F37 -> 49362792 | G38: =G19-G37 -> 1.1147409e+08 | H38: =H19-H37 -> 2501098 | I38: =I19-I37 -> -2501098 | J38: =J19-J37 -> 1.1147409e+08 | K38: =K19-K37 -> 62111295 | L38: =L19-L37 -> 1.6749224e+08 | M38: =M19-M37 -> 5273679 | ... BD38: =BD19-BD37 -> 87954269 | BE38: =+BC38-AX38-BD38 -> 0
A39: OTHER OPERATING INCOME | L39: =VLOOKUP(A39,'Profit Loss-Amravati-25-26'!$A$9:$F$190,5,0) -> 0 | M39: =VLOOKUP(A39,'Profit Loss-Betul-25-26'!$A$9:$F$141,5,0) -> 0
A40: DEPB LICENCE SALE | G40: =VLOOKUP(A40,'Profit Loss-Amravati-25-26'!$A$9:$D$190,3,0) -> 316074 | J40: =SUM(G40:I40) -> 316074 | K40: =+H40+G40-F40 -> 316074 | L40: =VLOOKUP(A40,'Profit Loss-Amravati-25-26'!$A$9:$F$190,5,0) -> 316074 | O40: =SUM(L40:M40) -> 316074 | P40: =+O40-J40 -> 0 | Q40: =VLOOKUP(A40,'Profit Loss-Amravati-25-26'!$A$9:$H$190,7,0) -> 316074 | T40: =SUM(Q40:R40) -> 316074 | U40: =+T40-O40 -> 0 | V40: =VLOOKUP(A40,'Profit Loss-Amravati-25-26'!$A$9:$J$190,9,0) -> 316074 | Y40: =SUM(V40:W40) -> 316074 | Z40: =+Y40-T40 -> 0 | AA40: =VLOOKUP(A40,'Profit Loss-Amravati-25-26'!$A$9:$L$192,11,0) -> 6259301 | AD40: =+AA40+AB40-AC40 -> 6259301 | AE40: =+AD40-Y40 -> 5943227 | AF40: =VLOOKUP(A40,'Profit Loss-Amravati-25-26'!$A$9:$N$192,13,0) -> 6259301 | AI40: =+AF40+AG40-AH40 -> 6259301 | AJ40: =+AI40-AD40 -> 0 | AK40: =VLOOKUP(A40,'Profit Loss-Amravati-25-26'!$A$9:$P$192,15,0) -> 6259301 | AN40: =+AK40+AL40-AM40 -> 6259301 | AO40: =+AN40-AI40 -> 0 | AP40: =VLOOKUP(A40,'Profit Loss-Amravati-25-26'!$A$9:$R$192,17,0) -> 6259301 | AS40: =+AP40+AQ40-AR40 -> 6259301 | AT40: =+AS40-AN40 -> 0 | AU40: =VLOOKUP(A40,'Profit Loss-Amravati-25-26'!$A$9:$T$192,19,0) -> 7320935 | AX40: =+AU40+AV40-AW40 -> 7320935 | AY40: =+AX40-AS40 -> 1061634 | AZ40: =VLOOKUP(A40,'Profit Loss-Amravati-25-26'!$A$9:$V$192,21,0) -> 7320935 | BC40: =+AZ40+BA40-BB40 -> 7320935 | BD40: =+BC40-AX40 -> 0
A41: Rodtep Licence as per Receipt basis | G41: =VLOOKUP(A41,'Profit Loss-Amravati-25-26'!$A$9:$D$190,3,0) -> -316074 | J41: =SUM(G41:I41) -> -316074 | K41: =+H41+G41-F41 -> -316074 | L41: =VLOOKUP(A41,'Profit Loss-Amravati-25-26'!$A$9:$F$190,5,0) -> -316074 | O41: =SUM(L41:M41) -> -316074 | P41: =+O41-J41 -> 0 | Q41: =VLOOKUP(A41,'Profit Loss-Amravati-25-26'!$A$9:$H$190,7,0) -> -316074 | T41: =SUM(Q41:R41) -> -316074 | U41: =+T41-O41 -> 0 | V41: =VLOOKUP(A41,'Profit Loss-Amravati-25-26'!$A$9:$J$190,9,0) -> -316074 | Y41: =SUM(V41:W41) -> -316074 | Z41: =+Y41-T41 -> 0 | AA41: =VLOOKUP(A41,'Profit Loss-Amravati-25-26'!$A$9:$L$192,11,0) -> -6259301 | AD41: =+AA41+AB41-AC41 -> -6259301 | AE41: =+AD41-Y41 -> -5943227 | AF41: =VLOOKUP(A41,'Profit Loss-Amravati-25-26'!$A$9:$N$192,13,0) -> -6259301 | AI41: =+AF41+AG41-AH41 -> -6259301 | AJ41: =+AI41-AD41 -> 0 | AK41: =VLOOKUP(A41,'Profit Loss-Amravati-25-26'!$A$9:$P$192,15,0) -> -6259301 | AN41: =+AK41+AL41-AM41 -> -6259301 | AO41: =+AN41-AI41 -> 0 | AP41: =VLOOKUP(A41,'Profit Loss-Amravati-25-26'!$A$9:$R$192,17,0) -> -6259301 | AS41: =+AP41+AQ41-AR41 -> -6259301 | AT41: =+AS41-AN41 -> 0 | AU41: =VLOOKUP(A41,'Profit Loss-Amravati-25-26'!$A$9:$T$192,19,0) -> -7320935 | AX41: =+AU41+AV41-AW41 -> -7320935 | AY41: =+AX41-AS41 -> -1061634 | AZ41: =VLOOKUP(A41,'Profit Loss-Amravati-25-26'!$A$9:$V$192,21,0) -> -7320935 | BC41: =+AZ41+BA41-BB41 -> -7320935 | BD41: =+BC41-AX41 -> 0
A42: Rodtep Licence as per Accrual basis | G42: =VLOOKUP(A42,'Profit Loss-Amravati-25-26'!$A$9:$D$190,3,0) -> 859887 | J42: =SUM(G42:I42) -> 859887 | K42: =+H42+G42-F42 -> 859887 | L42: =VLOOKUP(A42,'Profit Loss-Amravati-25-26'!$A$9:$F$190,5,0) -> 859887 | M42: =VLOOKUP(A42,'Profit Loss-Betul-25-26'!$A$9:$F$141,5,0) -> 0 | O42: =SUM(L42:M42) -> 859887 | P42: =+O42-J42 -> 0 | Q42: =VLOOKUP(A42,'Profit Loss-Amravati-25-26'!$A$9:$H$190,7,0) -> 1347177 | T42: =SUM(Q42:R42) -> 1347177 | U42: =+T42-O42 -> 487290 | V42: =VLOOKUP(A42,'Profit Loss-Amravati-25-26'!$A$9:$J$190,9,0) -> 1755145 | W42: =VLOOKUP(A42,'Profit Loss-Betul-25-26'!$A$9:$J$141,9,0) -> 0 | Y42: =SUM(V42:W42) -> 1755145 | Z42: =+Y42-T42 -> 407968 | AA42: =VLOOKUP(A42,'Profit Loss-Amravati-25-26'!$A$9:$L$192,11,0) -> 1849897 | AB42: =VLOOKUP(A42,'Profit Loss-Betul-25-26'!$A$9:$L$141,11,0) -> 0 | AD42: =+AA42+AB42-AC42 -> 1849897 | AE42: =+AD42-Y42 -> 94752 | AF42: =VLOOKUP(A42,'Profit Loss-Amravati-25-26'!$A$9:$N$192,13,0) -> 2694207 | AI42: =+AF42+AG42-AH42 -> 2694207 | AJ42: =+AI42-AD42 -> 844310 | AK42: =VLOOKUP(A42,'Profit Loss-Amravati-25-26'!$A$9:$P$192,15,0) -> 5431594 | AN42: =+AK42+AL42-AM42 -> 5431594 | AO42: =+AN42-AI42 -> 2737387 | AP42: =VLOOKUP(A42,'Profit Loss-Amravati-25-26'!$A$9:$R$192,17,0) -> 8136195 | AQ42: =VLOOKUP(A42,'Profit Loss-Betul-25-26'!$A$9:$R$141,17,0) -> 0 | AS42: =+AP42+AQ42-AR42 -> 8136195 | AT42: =+AS42-AN42 -> 2704601 | AU42: =VLOOKUP(A42,'Profit Loss-Amravati-25-26'!$A$9:$T$192,19,0) -> 8137208 | AX42: =+AU42+AV42-AW42 -> 8137208 | AY42: =+AX42-AS42 -> 1013 | AZ42: =VLOOKUP(A42,'Profit Loss-Amravati-25-26'!$A$9:$V$192,21,0) -> 8978541 | BC42: =+AZ42+BA42-BB42 -> 8978541 | BD42: =+BC42-AX42 -> 841333
A43: DUTY DRAWBACK RECEIVED | F43: =+B43+C43+D43 -> 0 | G43: =VLOOKUP(A43,'Profit Loss-Amravati-25-26'!$A$9:$D$190,3,0) -> 517983 | J43: =SUM(G43:I43) -> 517983 | K43: =+H43+G43-F43 -> 517983 | L43: =VLOOKUP(A43,'Profit Loss-Amravati-25-26'!$A$9:$F$190,5,0) -> 517983 | O43: =SUM(L43:M43) -> 517983 | P43: =+O43-J43 -> 0 | Q43: =VLOOKUP(A43,'Profit Loss-Amravati-25-26'!$A$9:$H$190,7,0) -> 836371 | T43: =SUM(Q43:R43) -> 836371 | U43: =+T43-O43 -> 318388 | V43: =VLOOKUP(A43,'Profit Loss-Amravati-25-26'!$A$9:$J$190,9,0) -> 1163782 | Y43: =SUM(V43:W43) -> 1163782 | Z43: =+Y43-T43 -> 327411 | AA43: =VLOOKUP(A43,'Profit Loss-Amravati-25-26'!$A$9:$L$192,11,0) -> 1248612 | AD43: =+AA43+AB43-AC43 -> 1248612 | AE43: =+AD43-Y43 -> 84830 | AF43: =VLOOKUP(A43,'Profit Loss-Amravati-25-26'!$A$9:$N$192,13,0) -> 1751367 | AI43: =+AF43+AG43-AH43 -> 1751367 | AJ43: =+AI43-AD43 -> 502755 | AK43: =VLOOKUP(A43,'Profit Loss-Amravati-25-26'!$A$9:$P$192,15,0) -> 3861478 | AN43: =+AK43+AL43-AM43 -> 3861478 | AO43: =+AN43-AI43 -> 2110111 | AP43: =VLOOKUP(A43,'Profit Loss-Amravati-25-26'!$A$9:$R$192,17,0) -> 6018309 | AS43: =+AP43+AQ43-AR43 -> 6018309 | AT43: =+AS43-AN43 -> 2156831 | AU43: =VLOOKUP(A43,'Profit Loss-Amravati-25-26'!$A$9:$T$192,19,0) -> 6018905 | AX43: =+AU43+AV43-AW43 -> 6018905 | AY43: =+AX43-AS43 -> 596 | AZ43: =VLOOKUP(A43,'Profit Loss-Amravati-25-26'!$A$9:$V$192,21,0) -> 6655556 | BC43: =+AZ43+BA43-BB43 -> 6655556 | BD43: =+BC43-AX43 -> 636651
A44: SALE SCRAP | C44: =VLOOKUP(A44,'Profit Loss-Amravati-25-26'!$A$13:$B$190,2,0) -> 21100 | F44: =+B44+C44+D44 -> 21100 | G44: =VLOOKUP(A44,'Profit Loss-Amravati-25-26'!$A$9:$D$190,3,0) -> 75856 | J44: =SUM(G44:I44) -> 75856 | K44: =+H44+G44-F44 -> 54756 | L44: =VLOOKUP(A44,'Profit Loss-Amravati-25-26'!$A$9:$F$190,5,0) -> 122094 | O44: =SUM(L44:M44) -> 122094 | P44: =+O44-J44 -> 46238 | Q44: =VLOOKUP(A44,'Profit Loss-Amravati-25-26'!$A$9:$H$190,7,0) -> 155784 | T44: =SUM(Q44:R44) -> 155784 | U44: =+T44-O44 -> 33690 | V44: =VLOOKUP(A44,'Profit Loss-Amravati-25-26'!$A$9:$J$190,9,0) -> 510434 | Y44: =SUM(V44:W44) -> 510434 | Z44: =+Y44-T44 -> 354650 | AA44: =VLOOKUP(A44,'Profit Loss-Amravati-25-26'!$A$9:$L$192,11,0) -> 533514 | AD44: =+AA44+AB44-AC44 -> 533514 | AE44: =+AD44-Y44 -> 23080 | AF44: =VLOOKUP(A44,'Profit Loss-Amravati-25-26'!$A$9:$N$192,13,0) -> 533514 | AI44: =+AF44+AG44-AH44 -> 533514 | AJ44: =+AI44-AD44 -> 0 | AK44: =VLOOKUP(A44,'Profit Loss-Amravati-25-26'!$A$9:$P$192,15,0) -> 575364 | AN44: =+AK44+AL44-AM44 -> 575364 | AO44: =+AN44-AI44 -> 41850 | AP44: =VLOOKUP(A44,'Profit Loss-Amravati-25-26'!$A$9:$R$192,17,0) -> 627514 | AS44: =+AP44+AQ44-AR44 -> 627514 | AT44: =+AS44-AN44 -> 52150 | AU44: =VLOOKUP(A44,'Profit Loss-Amravati-25-26'!$A$9:$T$192,19,0) -> 644564 | AX44: =+AU44+AV44-AW44 -> 644564 | AY44: =+AX44-AS44 -> 17050 | AZ44: =VLOOKUP(A44,'Profit Loss-Amravati-25-26'!$A$9:$V$192,21,0) -> 682214 | BC44: =+AZ44+BA44-BB44 -> 682214 | BD44: =+BC44-AX44 -> 37650
A45: SALE FABRIC WASTE | C45: =VLOOKUP(A45,'Profit Loss-Amravati-25-26'!$A$13:$B$190,2,0) -> 235670 | F45: =+B45+C45+D45 -> 235670 | G45: =VLOOKUP(A45,'Profit Loss-Amravati-25-26'!$A$9:$D$190,3,0) -> 864560 | J45: =SUM(G45:I45) -> 864560 | K45: =+H45+G45-F45 -> 628890 | L45: =VLOOKUP(A45,'Profit Loss-Amravati-25-26'!$A$9:$F$190,5,0) -> 1524524 | O45: =SUM(L45:M45) -> 1524524 | P45: =+O45-J45 -> 659964 | Q45: =VLOOKUP(A45,'Profit Loss-Amravati-25-26'!$A$9:$H$190,7,0) -> 2117005 | T45: =SUM(Q45:R45) -> 2117005 | U45: =+T45-O45 -> 592481 | V45: =VLOOKUP(A45,'Profit Loss-Amravati-25-26'!$A$9:$J$190,9,0) -> 2839665 | Y45: =SUM(V45:W45) -> 2839665 | Z45: =+Y45-T45 -> 722660 | AA45: =VLOOKUP(A45,'Profit Loss-Amravati-25-26'!$A$9:$L$192,11,0) -> 3196865 | AD45: =+AA45+AB45-AC45 -> 3196865 | AE45: =+AD45-Y45 -> 357200 | AF45: =VLOOKUP(A45,'Profit Loss-Amravati-25-26'!$A$9:$N$192,13,0) -> 3839855 | AI45: =+AF45+AG45-AH45 -> 3839855 | AJ45: =+AI45-AD45 -> 642990 | AK45: =VLOOKUP(A45,'Profit Loss-Amravati-25-26'!$A$9:$P$192,15,0) -> 4155695 | AN45: =+AK45+AL45-AM45 -> 4155695 | AO45: =+AN45-AI45 -> 315840 | AP45: =VLOOKUP(A45,'Profit Loss-Amravati-25-26'!$A$9:$R$192,17,0) -> 5026115 | AS45: =+AP45+AQ45-AR45 -> 5026115 | AT45: =+AS45-AN45 -> 870420 | AU45: =VLOOKUP(A45,'Profit Loss-Amravati-25-26'!$A$9:$T$192,19,0) -> 5800745 | AX45: =+AU45+AV45-AW45 -> 5800745 | AY45: =+AX45-AS45 -> 774630 | AZ45: =VLOOKUP(A45,'Profit Loss-Amravati-25-26'!$A$9:$V$192,21,0) -> 6318995 | BC45: =+AZ45+BA45-BB45 -> 6318995 | BD45: =+BC45-AX45 -> 518250
A46: TOTAL OTHER OPERATING INCOME | B46: =SUM(B40:B45) -> 0 | C46: =SUM(C40:C45) -> 256770 | D46: =SUM(D40:D45) -> 0 | F46: =SUM(F40:F45) -> 256770 | G46: =SUM(G40:G45) -> 2318286 | H46: =SUM(H40:H45) -> 0 | J46: =SUM(J40:J45) -> 2318286 | K46: =SUM(K40:K45) -> 2061516 | L46: =SUM(L40:L45) -> 3024488 | M46: =SUM(M40:M45) -> 0 | O46: =SUM(O40:O45) -> 3024488 | P46: =SUM(P40:P45) -> 706202 | Q46: =SUM(Q40:Q45) -> 4456337 | R46: =SUM(R40:R45) -> 0 | T46: =SUM(T40:T45) -> 4456337 | U46: =SUM(U40:U45) -> 1431849 | V46: =SUM(V40:V45) -> 6269026 | W46: =SUM(W40:W45) -> 0 | Y46: =SUM(Y40:Y45) -> 6269026 | Z46: =SUM(Z40:Z45) -> 1812689 | AA46: =SUM(AA40:AA45) -> 6828888 | AB46: =SUM(AB40:AB45) -> 0 | AD46: =SUM(AD40:AD45) -> 6828888 | AE46: =SUM(AE40:AE45) -> 559862 | AF46: =SUM(AF40:AF45) -> 8818943 | AG46: =SUM(AG40:AG45) -> 0 | AI46: =SUM(AI40:AI45) -> 8818943 | AJ46: =SUM(AJ40:AJ45) -> 1990055 | AK46: =SUM(AK40:AK45) -> 14024131 | AL46: =SUM(AL40:AL45) -> 0 | AN46: =SUM(AN40:AN45) -> 14024131 | AO46: =SUM(AO40:AO45) -> 5205188 | AP46: =SUM(AP40:AP45) -> 19808133 | AQ46: =SUM(AQ40:AQ45) -> 0 | AS46: =SUM(AS40:AS45) -> 19808133 | AT46: =SUM(AT40:AT45) -> 5784002 | AU46: =SUM(AU40:AU45) -> 20601422 | AV46: =SUM(AV40:AV45) -> 0 | AX46: =SUM(AX40:AX45) -> 20601422 | AY46: =SUM(AY40:AY45) -> 793289 | AZ46: =SUM(AZ40:AZ45) -> 22635306 | BA46: =SUM(BA40:BA45) -> 0 | BC46: =SUM(BC40:BC45) -> 22635306 | BD46: =SUM(BD40:BD45) -> 2033884 | BE46: =+BC46-AX46-BD46 -> 0
A47: REVENUE FROM OPERATION | B47: =B38+B46 -> 0 | C47: =C38+C46 -> 49619562 | D47: =D38+D46 -> 1501872 | F47: =F38+F46 -> 49619562 | G47: =G38+G46 -> 1.1379237e+08 | H47: =H38+H46 -> 2501098 | I47: =I38+I46 -> -2501098 | J47: =J38+J46 -> 1.1379237e+08 | K47: =K38+K46 -> 64172811 | L47: =L38+L46 -> 1.7051673e+08 | M47: =M38+M46 -> 5273679 | O47: =O38+O46 -> 1.7050423e+08 | P47: =P38+P46 -> 56711859 | Q47: =Q38+Q46 -> 2.6093072e+08 | R47: =R38+R46 -> 9014083 | T47: =T38+T46 -> 2.6056589e+08 | U47: =U38+U46 -> 90061657 | V47: =V38+V46 -> 3.2413917e+08 | W47: =W38+W46 -> 12181032 | Y47: =Y38+Y46 -> 3.142593e+08 | Z47: =Z38+Z46 -> 53693413 | AA47: =AA38+AA46 -> 4.0123628e+08 | AB47: =AB38+AB46 -> 15370414 | AD47: =AD38+AD46 -> 4.0122378e+08 | AE47: =AE38+AE46 -> 86964482 | AF47: =AF38+AF46 -> 4.6036563e+08 | AG47: =AG38+AG46 -> 16405208 | AI47: =AI38+AI46 -> 4.6033513e+08 | AJ47: =AJ38+AJ46 -> 59111342 | AK47: =AK38+AK46 -> 5.9471493e+08 | AL47: =AL38+AL46 -> 18506080 | AM47: =AM38+AM46 -> 18524580 | AN47: =AN38+AN46 -> 5.9469643e+08 | AO47: =AO38+AO46 -> 1.343613e+08 | AP47: =AP38+AP46 -> 7.6625618e+08 | ... BD47: =BD38+BD46 -> 89988153 | BE47: =+BC47-AX47-BD47 -> 0
A49: EXPENSES | L49: =VLOOKUP(A49,'Profit Loss-Amravati-25-26'!$A$9:$F$190,5,0) -> 0 | M49: =VLOOKUP(A49,'Profit Loss-Betul-25-26'!$A$9:$F$141,5,0) -> 0
A50: COST OF GOODS SOLD | L50: =VLOOKUP(A50,'Profit Loss-Amravati-25-26'!$A$9:$F$190,5,0) -> 0 | M50: =VLOOKUP(A50,'Profit Loss-Betul-25-26'!$A$9:$F$141,5,0) -> 0
A51: OPENING STOCK | C51: =VLOOKUP(A51,'Profit Loss-Amravati-25-26'!$A$13:$B$190,2,0) -> 161491723 | F51: =+B51+C51+D51 -> 161491723 | G51: =VLOOKUP(A51,'Profit Loss-Amravati-25-26'!$A$9:$D$190,3,0) -> 161491723 | J51: =SUM(G51:I51) -> 161491723 | K51: =+H51+G51-F51 -> 0 | L51: =VLOOKUP(A51,'Profit Loss-Amravati-25-26'!$A$9:$F$190,5,0) -> 161491723 | M51: =VLOOKUP(A51,'Profit Loss-Betul-25-26'!$A$9:$F$141,5,0) -> 0 | O51: =SUM(L51:M51) -> 161491723 | P51: =+O51-J51 -> 0 | Q51: =VLOOKUP(A51,'Profit Loss-Amravati-25-26'!$A$9:$H$190,7,0) -> 161491723 | T51: =SUM(Q51:R51) -> 161491723 | U51: =+T51-O51 -> 0 | V51: =VLOOKUP(A51,'Profit Loss-Amravati-25-26'!$A$9:$J$190,9,0) -> 161491723 | W51: =VLOOKUP(A51,'Profit Loss-Betul-25-26'!$A$9:$J$141,9,0) -> 0 | Y51: =SUM(V51:W51) -> 161491723 | Z51: =+Y51-T51 -> 0 | AA51: =VLOOKUP(A51,'Profit Loss-Amravati-25-26'!$A$9:$L$192,11,0) -> 161491723 | AD51: =+AA51+AB51 -> 161491723 | AE51: =+AD51-Y51 -> 0 | AF51: =VLOOKUP(A51,'Profit Loss-Amravati-25-26'!$A$9:$N$192,13,0) -> 161491723 | AG51: =VLOOKUP(A51,'Profit Loss-Betul-25-26'!$A$9:$N$141,13,0) -> 0 | AI51: =+AF51+AG51 -> 161491723 | AJ51: =+AI51-AD51 -> 0 | AK51: =VLOOKUP(A51,'Profit Loss-Amravati-25-26'!$A$9:$P$192,15,0) -> 161491723 | AL51: =VLOOKUP(A51,'Profit Loss-Betul-25-26'!$A$9:$P$141,15,0) -> 0 | AN51: =+AK51+AL51 -> 161491723 | AO51: =+AN51-AI51 -> 0 | AP51: =VLOOKUP(A51,'Profit Loss-Amravati-25-26'!$A$9:$R$192,17,0) -> 161491723 | AQ51: =VLOOKUP(A51,'Profit Loss-Betul-25-26'!$A$9:$R$141,17,0) -> 0 | AS51: =+AP51+AQ51 -> 161491723 | AT51: =+AS51-AN51 -> 0 | AU51: =VLOOKUP(A51,'Profit Loss-Amravati-25-26'!$A$9:$T$192,19,0) -> 161491723 | AV51: =VLOOKUP(A51,'Profit Loss-Betul-25-26'!$A$9:$T$141,19,0) -> 0 | AX51: =+AU51+AV51 -> 161491723 | AY51: =+AX51-AS51 -> 0 | AZ51: =VLOOKUP(A51,'Profit Loss-Amravati-25-26'!$A$9:$V$192,21,0) -> 161491723 | BA51: =VLOOKUP(A51,'Profit Loss-Betul-25-26'!$A$9:$V$141,21,0) -> 0 | BC51: =+AZ51+BA51 -> 161491723 | BD51: =+BC51-AX51 -> 0
A52: PURCHASE YARN - LOCAL | B52: =VLOOKUP(A52,'Profit Loss-Textile'!$A$8:$B$135,2,0) -> 0 | C52: =VLOOKUP(A52,'Profit Loss-Amravati-25-26'!$A$13:$B$190,2,0) -> 0 | F52: =+B52+C52+D52 -> 0 | G52: =VLOOKUP(A52,'Profit Loss-Amravati-25-26'!$A$9:$D$190,3,0) -> 4363200 | J52: =SUM(G52:I52) -> 4363200 | K52: =+H52+G52-F52 -> 4363200 | L52: =VLOOKUP(A52,'Profit Loss-Amravati-25-26'!$A$9:$F$190,5,0) -> 15711171 | O52: =SUM(L52:M52) -> 15711171 | P52: =+O52-J52 -> 11347971 | Q52: =VLOOKUP(A52,'Profit Loss-Amravati-25-26'!$A$9:$H$190,7,0) -> 16255569 | T52: =SUM(Q52:R52) -> 16255569 | U52: =+T52-O52 -> 544398.18 | V52: =VLOOKUP(A52,'Profit Loss-Amravati-25-26'!$A$9:$J$190,9,0) -> 16255569 | Y52: =SUM(V52:W52) -> 16255569 | Z52: =+Y52-T52 -> 0 | AA52: =VLOOKUP(A52,'Profit Loss-Amravati-25-26'!$A$9:$L$192,11,0) -> 21505900 | AD52: =+AA52+AB52 -> 21505900 | AE52: =+AD52-Y52 -> 5250331 | AF52: =VLOOKUP(A52,'Profit Loss-Amravati-25-26'!$A$9:$N$192,13,0) -> 21505900 | AI52: =+AF52+AG52-AH52 -> 21505900 | AJ52: =+AI52-AD52 -> 0 | AK52: =VLOOKUP(A52,'Profit Loss-Amravati-25-26'!$A$9:$P$192,15,0) -> 21505900 | AN52: =+AK52+AL52-AM52 -> 21505900 | AO52: =+AN52-AI52 -> 0 | AP52: =VLOOKUP(A52,'Profit Loss-Amravati-25-26'!$A$9:$R$192,17,0) -> 21505900 | AS52: =+AP52+AQ52-AR52 -> 21505900 | AT52: =+AS52-AN52 -> 0 | AU52: =VLOOKUP(A52,'Profit Loss-Amravati-25-26'!$A$9:$T$192,19,0) -> 21505900 | AX52: =+AU52+AV52-AW52 -> 21505900 | AY52: =+AX52-AS52 -> 0 | AZ52: =VLOOKUP(A52,'Profit Loss-Amravati-25-26'!$A$9:$V$192,21,0) -> 21505900 | BC52: =+AZ52+BA52-BB52 -> 21505900 | BD52: =+BC52-AX52 -> 0
A53: PURCHASE (JOB WORK) - INTER UNIT | C53: 1501872 | E53: 1501872 | F53: =+C53+D53-E53 -> 0 | G53: =VLOOKUP(A53,'Profit Loss-Amravati-25-26'!$A$9:$D$190,3,0) -> 2501098 | I53: =-G53 -> -2501098 | J53: =SUM(G53:I53) -> 0 | K53: =+H53+G53-F53+I53 -> 0 | L53: =VLOOKUP(A53,'Profit Loss-Amravati-25-26'!$A$9:$F$190,5,0) -> 5286179 | N53: =-L53 -> -5286179 | O53: =SUM(L53:N53) -> 0 | P53: =+O53-J53 -> 0 | Q53: =VLOOKUP(A53,'Profit Loss-Amravati-25-26'!$A$9:$H$190,7,0) -> 9026583 | S53: =-Q53 -> -9026583 | T53: =SUM(Q53:S53) -> 0 | U53: =+T53-O53 -> 0 | V53: =VLOOKUP(A53,'Profit Loss-Amravati-25-26'!$A$9:$J$190,9,0) -> 12193532 | X53: =-V53 -> -12193532 | Y53: =SUM(V53:X53) -> 0 | Z53: =+Y53-T53 -> 0 | AA53: =VLOOKUP(A53,'Profit Loss-Amravati-25-26'!$A$9:$L$192,11,0) -> 15382914 | AC53: =-AA53 -> -15382914 | AD53: =+AA53+AB53+AC53 -> 0 | AE53: =+AD53-Y53 -> 0 | AF53: =VLOOKUP(A53,'Profit Loss-Amravati-25-26'!$A$9:$N$192,13,0) -> 16435708 | AH53: =+AF53 -> 16435708 | AJ53: =+AI53-AD53 -> 0 | AK53: =VLOOKUP(A53,'Profit Loss-Amravati-25-26'!$A$9:$P$192,15,0) -> 18524580 | AM53: =+AK53 -> 18524580 | AO53: =+AN53-AI53 -> 0 | AP53: =VLOOKUP(A53,'Profit Loss-Amravati-25-26'!$A$9:$R$192,17,0) -> 21712831 | AR53: =+AP53 -> 21712831 | AT53: =+AS53-AN53 -> 0 | AU53: =VLOOKUP(A53,'Profit Loss-Amravati-25-26'!$A$9:$T$192,19,0) -> 25000388 | AW53: =+AU53 -> 25000388 | AY53: =+AX53-AS53 -> 0 | AZ53: =VLOOKUP(A53,'Profit Loss-Amravati-25-26'!$A$9:$V$192,21,0) -> 27034065 | BB53: =+AZ53 -> 27034065 | BD53: =+BC53-AX53 -> 0
A54: DELIVERY CHARGES ON PURCHASES | B54: =VLOOKUP(A54,'Profit Loss-Textile'!$A$8:$B$135,2,0) -> 0 | C54: =VLOOKUP(A54,'Profit Loss-Amravati-25-26'!$A$13:$B$190,2,0) -> 49560 | F54: =+B54+C54+D54 -> 49560 | G54: =VLOOKUP(A54,'Profit Loss-Amravati-25-26'!$A$9:$D$190,3,0) -> 130704 | J54: =SUM(G54:I54) -> 130704 | K54: =+H54+G54-F54 -> 81144 | L54: =VLOOKUP(A54,'Profit Loss-Amravati-25-26'!$A$9:$F$190,5,0) -> 151414 | O54: =SUM(L54:M54) -> 151414 | P54: =+O54-J54 -> 20710 | Q54: =VLOOKUP(A54,'Profit Loss-Amravati-25-26'!$A$9:$H$190,7,0) -> 246584 | R54: =VLOOKUP(A54,'Profit Loss-Betul-25-26'!$A$9:$H$141,7,0) -> 400 | T54: =SUM(Q54:R54) -> 246984 | U54: =+T54-O54 -> 95570 | V54: =VLOOKUP(A54,'Profit Loss-Amravati-25-26'!$A$9:$J$190,9,0) -> 279664 | W54: =VLOOKUP(A54,'Profit Loss-Betul-25-26'!$A$9:$J$141,9,0) -> 400 | Y54: =SUM(V54:W54) -> 280064 | Z54: =+Y54-T54 -> 33080 | AA54: =VLOOKUP(A54,'Profit Loss-Amravati-25-26'!$A$9:$L$192,11,0) -> 333003 | AB54: =VLOOKUP(A54,'Profit Loss-Betul-25-26'!$A$9:$L$141,11,0) -> 400 | AD54: =+AA54+AB54 -> 333403 | AE54: =+AD54-Y54 -> 53339 | AF54: =VLOOKUP(A54,'Profit Loss-Amravati-25-26'!$A$9:$N$192,13,0) -> 359828 | AG54: =VLOOKUP(A54,'Profit Loss-Betul-25-26'!$A$9:$N$141,13,0) -> 1470 | AI54: =+AF54+AG54-AH54 -> 361298 | AJ54: =+AI54-AD54 -> 27895 | AK54: =VLOOKUP(A54,'Profit Loss-Amravati-25-26'!$A$9:$P$192,15,0) -> 525972 | AL54: =VLOOKUP(A54,'Profit Loss-Betul-25-26'!$A$9:$P$141,15,0) -> 13190 | AN54: =+AK54+AL54-AM54 -> 539162 | AO54: =+AN54-AI54 -> 177864 | AP54: =VLOOKUP(A54,'Profit Loss-Amravati-25-26'!$A$9:$R$192,17,0) -> 805876 | AQ54: =VLOOKUP(A54,'Profit Loss-Betul-25-26'!$A$9:$R$141,17,0) -> 2370 | AS54: =+AP54+AQ54-AR54 -> 808246 | AT54: =+AS54-AN54 -> 269084 | AU54: =VLOOKUP(A54,'Profit Loss-Amravati-25-26'!$A$9:$T$192,19,0) -> 1474114 | AV54: =VLOOKUP(A54,'Profit Loss-Betul-25-26'!$A$9:$T$141,19,0) -> 2370 | AX54: =+AU54+AV54-AW54 -> 1476484 | AY54: =+AX54-AS54 -> 668238 | AZ54: =VLOOKUP(A54,'Profit Loss-Amravati-25-26'!$A$9:$V$192,21,0) -> 1577814 | BA54: =VLOOKUP(A54,'Profit Loss-Betul-25-26'!$A$9:$V$141,21,0) -> 2370 | BC54: =+AZ54+BA54-BB54 -> 1580184 | BD54: =+BC54-AX54 -> 103700
A55: DELIVERY CHARGES - PURCHASE- FABRIC | G55: =VLOOKUP(A55,'Profit Loss-Amravati-25-26'!$A$9:$D$190,3,0) -> 422014 | J55: =SUM(G55:I55) -> 422014 | K55: =+H55+G55-F55 -> 422014 | L55: =VLOOKUP(A55,'Profit Loss-Amravati-25-26'!$A$9:$F$190,5,0) -> 472710 | O55: =SUM(L55:M55) -> 472710 | P55: =+O55-J55 -> 50696 | Q55: =VLOOKUP(A55,'Profit Loss-Amravati-25-26'!$A$9:$H$190,7,0) -> 1060184.4 | T55: =SUM(Q55:R55) -> 1060184.4 | U55: =+T55-O55 -> 587474.41 | V55: =VLOOKUP(A55,'Profit Loss-Amravati-25-26'!$A$9:$J$190,9,0) -> 1784563.4 | Y55: =SUM(V55:W55) -> 1784563.4 | Z55: =+Y55-T55 -> 724379.02 | AA55: =VLOOKUP(A55,'Profit Loss-Amravati-25-26'!$A$9:$L$192,11,0) -> 2217544.7 | AD55: =+AA55+AB55 -> 2217544.7 | AE55: =+AD55-Y55 -> 432981.25 | AF55: =VLOOKUP(A55,'Profit Loss-Amravati-25-26'!$A$9:$N$192,13,0) -> 2561544.7 | AI55: =+AF55+AG55-AH55 -> 2561544.7 | AJ55: =+AI55-AD55 -> 344000 | AK55: =VLOOKUP(A55,'Profit Loss-Amravati-25-26'!$A$9:$P$192,15,0) -> 2786461.1 | AN55: =+AK55+AL55-AM55 -> 2786461.1 | AO55: =+AN55-AI55 -> 224916.46 | AP55: =VLOOKUP(A55,'Profit Loss-Amravati-25-26'!$A$9:$R$192,17,0) -> 2949461.1 | AS55: =+AP55+AQ55-AR55 -> 2949461.1 | AT55: =+AS55-AN55 -> 163000 | AU55: =VLOOKUP(A55,'Profit Loss-Amravati-25-26'!$A$9:$T$192,19,0) -> 2949461.1 | AX55: =+AU55+AV55-AW55 -> 2949461.1 | AY55: =+AX55-AS55 -> 0 | AZ55: =VLOOKUP(A55,'Profit Loss-Amravati-25-26'!$A$9:$V$192,21,0) -> 3127405.8 | BC55: =+AZ55+BA55-BB55 -> 3127405.8 | BD55: =+BC55-AX55 -> 177944.63
A56: DELIVERY CHARGES - PURCHASE-GARMENT | AS56: =+AP56+AQ56-AR56 -> 0 | AT56: =+AS56-AN56 -> 0 | AX56: =+AU56+AV56-AW56 -> 0 | AY56: =+AX56-AS56 -> 0 | BC56: =+AZ56+BA56-BB56 -> 0 | BD56: =+BC56-AX56 -> 0
A57: PURCHASE FOR TRADING - GARMENT | G57: =VLOOKUP(A57,'Profit Loss-Amravati-25-26'!$A$9:$D$190,3,0) -> 8460079 | J57: =SUM(G57:I57) -> 8460079 | K57: =+H57+G57-F57 -> 8460079 | L57: =VLOOKUP(A57,'Profit Loss-Amravati-25-26'!$A$9:$F$190,5,0) -> 8460079 | O57: =SUM(L57:M57) -> 8460079 | P57: =+O57-J57 -> 0 | Q57: =VLOOKUP(A57,'Profit Loss-Amravati-25-26'!$A$9:$H$190,7,0) -> 8460079 | T57: =SUM(Q57:R57) -> 8460079 | U57: =+T57-O57 -> 0 | V57: =VLOOKUP(A57,'Profit Loss-Amravati-25-26'!$A$9:$J$190,9,0) -> 8460079 | Y57: =SUM(V57:W57) -> 8460079 | Z57: =+Y57-T57 -> 0 | AA57: =VLOOKUP(A57,'Profit Loss-Amravati-25-26'!$A$9:$L$192,11,0) -> 8460079 | AD57: =+AA57+AB57 -> 8460079 | AE57: =+AD57-Y57 -> 0 | AF57: =VLOOKUP(A57,'Profit Loss-Amravati-25-26'!$A$9:$N$192,13,0) -> 8460079 | AI57: =+AF57+AG57-AH57 -> 8460079 | AJ57: =+AI57-AD57 -> 0 | AK57: =VLOOKUP(A57,'Profit Loss-Amravati-25-26'!$A$9:$P$192,15,0) -> 8460079 | AN57: =+AK57+AL57-AM57 -> 8460079 | AO57: =+AN57-AI57 -> 0 | AP57: =VLOOKUP(A57,'Profit Loss-Amravati-25-26'!$A$9:$R$192,17,0) -> 8460079 | AS57: =+AP57+AQ57-AR57 -> 8460079 | AT57: =+AS57-AN57 -> 0 | AU57: =VLOOKUP(A57,'Profit Loss-Amravati-25-26'!$A$9:$T$192,19,0) -> 8460079 | AX57: =+AU57+AV57-AW57 -> 8460079 | AY57: =+AX57-AS57 -> 0 | AZ57: =VLOOKUP(A57,'Profit Loss-Amravati-25-26'!$A$9:$V$192,21,0) -> 8460079 | BC57: =+AZ57+BA57-BB57 -> 8460079 | BD57: =+BC57-AX57 -> 0
A58: PURCHASE FOR TRADING - (SCRAP) | Q58: =VLOOKUP(A58,'Profit Loss-Amravati-25-26'!$A$9:$H$190,7,0) -> 0 | T58: =SUM(Q58:R58) -> 0 | U58: =+T58-O58 -> 0 | V58: =VLOOKUP(A58,'Profit Loss-Amravati-25-26'!$A$9:$J$190,9,0) -> 0 | Y58: =SUM(V58:W58) -> 0 | Z58: =+Y58-T58 -> 0 | AA58: =VLOOKUP(A58,'Profit Loss-Amravati-25-26'!$A$9:$L$192,11,0) -> 0 | AD58: =+AA58+AB58 -> 0 | AE58: =+AD58-Y58 -> 0 | AF58: =VLOOKUP(A58,'Profit Loss-Amravati-25-26'!$A$9:$N$192,13,0) -> 0 | AI58: =+AF58+AG58-AH58 -> 0 | AJ58: =+AI58-AD58 -> 0 | AK58: =VLOOKUP(A58,'Profit Loss-Amravati-25-26'!$A$9:$P$192,15,0) -> 0 | AN58: =+AK58+AL58-AM58 -> 0 | AO58: =+AN58-AI58 -> 0 | AP58: =VLOOKUP(A58,'Profit Loss-Amravati-25-26'!$A$9:$R$192,17,0) -> 0 | AS58: =+AP58+AQ58-AR58 -> 0 | AT58: =+AS58-AN58 -> 0 | AU58: =VLOOKUP(A58,'Profit Loss-Amravati-25-26'!$A$9:$T$192,19,0) -> 0 | AX58: =+AU58+AV58-AW58 -> 0 | AY58: =+AX58-AS58 -> 0 | AZ58: =VLOOKUP(A58,'Profit Loss-Amravati-25-26'!$A$9:$V$192,21,0) -> 0 | BC58: =+AZ58+BA58-BB58 -> 0 | BD58: =+BC58-AX58 -> 0
A59: PURCHASE PACKING MATERIAL (GARMENT) | C59: =VLOOKUP(A59,'Profit Loss-Amravati-25-26'!$A$13:$B$190,2,0) -> 3621747.6 | F59: =+B59+C59+D59 -> 3621747.6 | G59: =VLOOKUP(A59,'Profit Loss-Amravati-25-26'!$A$9:$D$190,3,0) -> 9323779.6 | J59: =SUM(G59:I59) -> 9323779.6 | K59: =+H59+G59-F59 -> 5702032 | L59: =VLOOKUP(A59,'Profit Loss-Amravati-25-26'!$A$9:$F$190,5,0) -> 12981156 | O59: =SUM(L59:M59) -> 12981156 | P59: =+O59-J59 -> 3657376.6 | Q59: =VLOOKUP(A59,'Profit Loss-Amravati-25-26'!$A$9:$H$190,7,0) -> 18489486 | T59: =SUM(Q59:R59) -> 18489486 | U59: =+T59-O59 -> 5508330 | V59: =VLOOKUP(A59,'Profit Loss-Amravati-25-26'!$A$9:$J$190,9,0) -> 24958004 | Y59: =SUM(V59:W59) -> 24958004 | Z59: =+Y59-T59 -> 6468518.1 | AA59: =VLOOKUP(A59,'Profit Loss-Amravati-25-26'!$A$9:$L$192,11,0) -> 30061663 | AD59: =+AA59+AB59 -> 30061663 | AE59: =+AD59-Y59 -> 5103658.4 | AF59: =VLOOKUP(A59,'Profit Loss-Amravati-25-26'!$A$9:$N$192,13,0) -> 35530936 | AI59: =+AF59+AG59-AH59 -> 35530936 | AJ59: =+AI59-AD59 -> 5469273.6 | AK59: =VLOOKUP(A59,'Profit Loss-Amravati-25-26'!$A$9:$P$192,15,0) -> 38947941 | AN59: =+AK59+AL59-AM59 -> 38947941 | AO59: =+AN59-AI59 -> 3417005 | AP59: =VLOOKUP(A59,'Profit Loss-Amravati-25-26'!$A$9:$R$192,17,0) -> 42673335 | AS59: =+AP59+AQ59-AR59 -> 42673335 | AT59: =+AS59-AN59 -> 3725393.5 | AU59: =VLOOKUP(A59,'Profit Loss-Amravati-25-26'!$A$9:$T$192,19,0) -> 47951382 | AX59: =+AU59+AV59-AW59 -> 47951382 | AY59: =+AX59-AS59 -> 5278046.6 | AZ59: =VLOOKUP(A59,'Profit Loss-Amravati-25-26'!$A$9:$V$192,21,0) -> 51707465 | BC59: =+AZ59+BA59-BB59 -> 51707465 | BD59: =+BC59-AX59 -> 3756083.6
A60: PURCHASE PACKING MATERIAL | AA60: =VLOOKUP(A60,'Profit Loss-Amravati-25-26'!$A$9:$L$192,11,0) -> 40306.78 | AD60: =+AA60+AB60 -> 40306.78 | AE60: =+AD60-Y60 -> 40306.78 | AF60: =VLOOKUP(A60,'Profit Loss-Amravati-25-26'!$A$9:$N$192,13,0) -> 254494.78 | AI60: =+AF60+AG60-AH60 -> 254494.78 | AJ60: =+AI60-AD60 -> 214188 | AK60: =VLOOKUP(A60,'Profit Loss-Amravati-25-26'!$A$9:$P$192,15,0) -> 479841.78 | AN60: =+AK60+AL60-AM60 -> 479841.78 | AO60: =+AN60-AI60 -> 225347 | AP60: =VLOOKUP(A60,'Profit Loss-Amravati-25-26'!$A$9:$R$192,17,0) -> 867193.78 | AS60: =+AP60+AQ60-AR60 -> 867193.78 | AT60: =+AS60-AN60 -> 387352 | AU60: =VLOOKUP(A60,'Profit Loss-Amravati-25-26'!$A$9:$T$192,19,0) -> 867193.78 | AX60: =+AU60+AV60-AW60 -> 867193.78 | AY60: =+AX60-AS60 -> 0 | AZ60: =VLOOKUP(A60,'Profit Loss-Amravati-25-26'!$A$9:$V$192,21,0) -> 2022689.8 | BC60: =+AZ60+BA60-BB60 -> 2022689.8 | BD60: =+BC60-AX60 -> 1155496
A61: CUSTOM DUTY ON IMPORT | C61: =VLOOKUP(A61,'Profit Loss-Amravati-25-26'!$A$13:$B$190,2,0) -> 1857 | F61: =+B61+C61+D61 -> 1857 | G61: =VLOOKUP(A61,'Profit Loss-Amravati-25-26'!$A$9:$D$190,3,0) -> 6454 | J61: =SUM(G61:I61) -> 6454 | K61: =+H61+G61-F61 -> 4597 | L61: =VLOOKUP(A61,'Profit Loss-Amravati-25-26'!$A$9:$F$190,5,0) -> 7937 | O61: =SUM(L61:M61) -> 7937 | P61: =+O61-J61 -> 1483 | Q61: =VLOOKUP(A61,'Profit Loss-Amravati-25-26'!$A$9:$H$190,7,0) -> 28237 | T61: =SUM(Q61:R61) -> 28237 | U61: =+T61-O61 -> 20300 | V61: =VLOOKUP(A61,'Profit Loss-Amravati-25-26'!$A$9:$J$190,9,0) -> 110359 | Y61: =SUM(V61:W61) -> 110359 | Z61: =+Y61-T61 -> 82122 | AA61: =VLOOKUP(A61,'Profit Loss-Amravati-25-26'!$A$9:$L$192,11,0) -> 112239 | AD61: =+AA61+AB61 -> 112239 | AE61: =+AD61-Y61 -> 1880 | AF61: =VLOOKUP(A61,'Profit Loss-Amravati-25-26'!$A$9:$N$192,13,0) -> 118941 | AI61: =+AF61+AG61-AH61 -> 118941 | AJ61: =+AI61-AD61 -> 6702 | AK61: =VLOOKUP(A61,'Profit Loss-Amravati-25-26'!$A$9:$P$192,15,0) -> 152321 | AN61: =+AK61+AL61-AM61 -> 152321 | AO61: =+AN61-AI61 -> 33380 | AP61: =VLOOKUP(A61,'Profit Loss-Amravati-25-26'!$A$9:$R$192,17,0) -> 209507 | AS61: =+AP61+AQ61-AR61 -> 209507 | AT61: =+AS61-AN61 -> 57186 | AU61: =VLOOKUP(A61,'Profit Loss-Amravati-25-26'!$A$9:$T$192,19,0) -> 459679.5 | AX61: =+AU61+AV61-AW61 -> 459679.5 | AY61: =+AX61-AS61 -> 250172.5 | AZ61: =VLOOKUP(A61,'Profit Loss-Amravati-25-26'!$A$9:$V$192,21,0) -> 472048.5 | BC61: =+AZ61+BA61-BB61 -> 472048.5 | BD61: =+BC61-AX61 -> 12369
A62: PURCHASE FABRICS & HOSIERY LOCAL | C62: =VLOOKUP(A62,'Profit Loss-Amravati-25-26'!$A$13:$B$190,2,0) -> 21624068 | F62: =+B62+C62+D62 -> 21624068 | G62: =VLOOKUP(A62,'Profit Loss-Amravati-25-26'!$A$9:$D$190,3,0) -> 56514483 | J62: =SUM(G62:I62) -> 56514483 | K62: =+H62+G62-F62 -> 34890415 | L62: =VLOOKUP(A62,'Profit Loss-Amravati-25-26'!$A$9:$F$190,5,0) -> 92339270 | O62: =SUM(L62:M62) -> 92339270 | P62: =+O62-J62 -> 35824787 | Q62: =VLOOKUP(A62,'Profit Loss-Amravati-25-26'!$A$9:$H$190,7,0) -> 1.340444e+08 | T62: =SUM(Q62:R62) -> 1.340444e+08 | U62: =+T62-O62 -> 41705125 | V62: =VLOOKUP(A62,'Profit Loss-Amravati-25-26'!$A$9:$J$190,9,0) -> 1.731658e+08 | Y62: =SUM(V62:W62) -> 1.731658e+08 | Z62: =+Y62-T62 -> 39121406 | AA62: =VLOOKUP(A62,'Profit Loss-Amravati-25-26'!$A$9:$L$192,11,0) -> 2.2478117e+08 | AD62: =+AA62+AB62 -> 2.2478117e+08 | AE62: =+AD62-Y62 -> 51615372 | AF62: =VLOOKUP(A62,'Profit Loss-Amravati-25-26'!$A$9:$N$192,13,0) -> 2.6947259e+08 | AI62: =+AF62+AG62-AH62 -> 2.6947259e+08 | AJ62: =+AI62-AD62 -> 44691418 | AK62: =VLOOKUP(A62,'Profit Loss-Amravati-25-26'!$A$9:$P$192,15,0) -> 3.7264743e+08 | AN62: =+AK62+AL62-AM62 -> 3.7264743e+08 | AO62: =+AN62-AI62 -> 1.0317484e+08 | AP62: =VLOOKUP(A62,'Profit Loss-Amravati-25-26'!$A$9:$R$192,17,0) -> 4.869369e+08 | AS62: =+AP62+AQ62-AR62 -> 4.869369e+08 | AT62: =+AS62-AN62 -> 1.1428947e+08 | AU62: =VLOOKUP(A62,'Profit Loss-Amravati-25-26'!$A$9:$T$192,19,0) -> 5.5895829e+08 | AX62: =+AU62+AV62-AW62 -> 5.5895829e+08 | AY62: =+AX62-AS62 -> 72021391 | AZ62: =VLOOKUP(A62,'Profit Loss-Amravati-25-26'!$A$9:$V$192,21,0) -> 6.1342312e+08 | BC62: =+AZ62+BA62-BB62 -> 6.1342312e+08 | BD62: =+BC62-AX62 -> 54464837
A63: PURCHASE (JOB WORK) - INTER UNIT
A64: DELIVERY CHARGES - PURCHASE-GARMENT | C64: =VLOOKUP(A64,'Profit Loss-Amravati-25-26'!$A$13:$B$190,2,0) -> 136918.62 | F64: =+B64+C64+D64 -> 136918.62 | G64: =VLOOKUP(A64,'Profit Loss-Amravati-25-26'!$A$9:$D$190,3,0) -> 258906.48 | J64: =SUM(G64:I64) -> 258906.48 | K64: =+H64+G64-F64 -> 121987.86 | L64: =VLOOKUP(A64,'Profit Loss-Amravati-25-26'!$A$9:$F$190,5,0) -> 1048958.5 | O64: =SUM(L64:M64) -> 1048958.5 | P64: =+O64-J64 -> 790052 | Q64: =VLOOKUP(A64,'Profit Loss-Amravati-25-26'!$A$9:$H$190,7,0) -> 1291929.1 | T64: =SUM(Q64:R64) -> 1291929.1 | U64: =+T64-O64 -> 242970.59 | V64: =VLOOKUP(A64,'Profit Loss-Amravati-25-26'!$A$9:$J$190,9,0) -> 1951692 | Y64: =SUM(V64:W64) -> 1951692 | Z64: =+Y64-T64 -> 659762.92 | AA64: =VLOOKUP(A64,'Profit Loss-Amravati-25-26'!$A$9:$L$192,11,0) -> 2294085.4 | AD64: =+AA64+AB64 -> 2294085.4 | AE64: =+AD64-Y64 -> 342393.41 | AF64: =VLOOKUP(A64,'Profit Loss-Amravati-25-26'!$A$9:$N$192,13,0) -> 3099076.1 | AI64: =+AF64+AG64-AH64 -> 3099076.1 | AJ64: =+AI64-AD64 -> 804990.72 | AK64: =VLOOKUP(A64,'Profit Loss-Amravati-25-26'!$A$9:$P$192,15,0) -> 3182557.7 | AN64: =+AK64+AL64-AM64 -> 3182557.7 | AO64: =+AN64-AI64 -> 83481.6 | AP64: =VLOOKUP(A64,'Profit Loss-Amravati-25-26'!$A$9:$R$192,17,0) -> 3492809.1 | AQ64: =VLOOKUP(A56,'Profit Loss-Betul-25-26'!$A$9:$R$141,17,0) -> 45070 | AS64: =+AP64+AQ64-AR64 -> 3537879.1 | AT64: =+AS64-AN64 -> 355321.34 | AU64: =VLOOKUP(A56,'Profit Loss-Amravati-25-26'!$A$9:$T$192,19,0) -> 3768745.3 | AV64: =VLOOKUP(A64,'Profit Loss-Betul-25-26'!$A$9:$T$141,19,0) -> 45070 | AX64: =+AU64+AV64-AW64 -> 3813815.3 | AY64: =+AX64-AS64 -> 275936.24 | AZ64: =VLOOKUP(A64,'Profit Loss-Amravati-25-26'!$A$9:$V$192,21,0) -> 4211205.7 | BA64: =VLOOKUP(A64,'Profit Loss-Betul-25-26'!$A$9:$V$141,21,0) -> 45070 | BC64: =+AZ64+BA64-BB64 -> 4256275.7 | BD64: =+BC64-AX64 -> 442460.41
A65: PUR. THREAD & TRIM ITEMS | C65: =VLOOKUP(A65,'Profit Loss-Amravati-25-26'!$A$13:$B$190,2,0) -> 6052378.4 | F65: =+B65+C65+D65 -> 6052378.4 | G65: =VLOOKUP(A65,'Profit Loss-Amravati-25-26'!$A$9:$D$190,3,0) -> 10960901 | J65: =SUM(G65:I65) -> 10960901 | K65: =+H65+G65-F65 -> 4908522.1 | L65: =VLOOKUP(A65,'Profit Loss-Amravati-25-26'!$A$9:$F$190,5,0) -> 14613110 | O65: =SUM(L65:M65) -> 14613110 | P65: =+O65-J65 -> 3652209.1 | Q65: =VLOOKUP(A65,'Profit Loss-Amravati-25-26'!$A$9:$H$190,7,0) -> 23264220 | T65: =SUM(Q65:R65) -> 23264220 | U65: =+T65-O65 -> 8651109.9 | V65: =VLOOKUP(A65,'Profit Loss-Amravati-25-26'!$A$9:$J$190,9,0) -> 26880068 | Y65: =SUM(V65:W65) -> 26880068 | Z65: =+Y65-T65 -> 3615848.9 | AA65: =VLOOKUP(A65,'Profit Loss-Amravati-25-26'!$A$9:$L$192,11,0) -> 33028070 | AD65: =+AA65+AB65 -> 33028070 | AE65: =+AD65-Y65 -> 6148002 | AF65: =VLOOKUP(A65,'Profit Loss-Amravati-25-26'!$A$9:$N$192,13,0) -> 36987494 | AI65: =+AF65+AG65-AH65 -> 36987494 | AJ65: =+AI65-AD65 -> 3959423.7 | AK65: =VLOOKUP(A65,'Profit Loss-Amravati-25-26'!$A$9:$P$192,15,0) -> 41174309 | AN65: =+AK65+AL65-AM65 -> 41174309 | AO65: =+AN65-AI65 -> 4186814.7 | AP65: =VLOOKUP(A65,'Profit Loss-Amravati-25-26'!$A$9:$R$192,17,0) -> 45966285 | AS65: =+AP65+AQ65-AR65 -> 45966285 | AT65: =+AS65-AN65 -> 4791976.5 | AU65: =VLOOKUP(A65,'Profit Loss-Amravati-25-26'!$A$9:$T$192,19,0) -> 50431955 | AX65: =+AU65+AV65-AW65 -> 50431955 | AY65: =+AX65-AS65 -> 4465669.9 | AZ65: =VLOOKUP(A65,'Profit Loss-Amravati-25-26'!$A$9:$V$192,21,0) -> 55409554 | BC65: =+AZ65+BA65-BB65 -> 55409554 | BD65: =+BC65-AX65 -> 4977598.8
A66: PUR. THREAD & TRIM ITEMS- IMPORT | C66: =VLOOKUP(A66,'Profit Loss-Amravati-25-26'!$A$13:$B$190,2,0) -> 211799.78 | F66: =+B66+C66+D66 -> 211799.78 | G66: =VLOOKUP(A66,'Profit Loss-Amravati-25-26'!$A$9:$D$190,3,0) -> 211799.78 | J66: =SUM(G66:I66) -> 211799.78 | K66: =+H66+G66-F66 -> 0 | L66: =VLOOKUP(A66,'Profit Loss-Amravati-25-26'!$A$9:$F$190,5,0) -> 601203.68 | O66: =SUM(L66:M66) -> 601203.68 | P66: =+O66-J66 -> 389403.9 | Q66: =VLOOKUP(A66,'Profit Loss-Amravati-25-26'!$A$9:$H$190,7,0) -> 601204.02 | T66: =SUM(Q66:R66) -> 601204.02 | U66: =+T66-O66 -> 0.34 | V66: =VLOOKUP(A66,'Profit Loss-Amravati-25-26'!$A$9:$J$190,9,0) -> 601204.02 | Y66: =SUM(V66:W66) -> 601204.02 | Z66: =+Y66-T66 -> 0 | AA66: =VLOOKUP(A66,'Profit Loss-Amravati-25-26'!$A$9:$L$192,11,0) -> 865612.81 | AD66: =+AA66+AB66 -> 865612.81 | AE66: =+AD66-Y66 -> 264408.79 | AF66: =VLOOKUP(A66,'Profit Loss-Amravati-25-26'!$A$9:$N$192,13,0) -> 1564521.1 | AI66: =+AF66+AG66-AH66 -> 1564521.1 | AJ66: =+AI66-AD66 -> 698908.33 | AK66: =VLOOKUP(A66,'Profit Loss-Amravati-25-26'!$A$9:$P$192,15,0) -> 1664942.1 | AN66: =+AK66+AL66-AM66 -> 1664942.1 | AO66: =+AN66-AI66 -> 100421 | AP66: =VLOOKUP(A66,'Profit Loss-Amravati-25-26'!$A$9:$R$192,17,0) -> 2020313.7 | AS66: =+AP66+AQ66-AR66 -> 2020313.7 | AT66: =+AS66-AN66 -> 355371.56 | AU66: =VLOOKUP(A66,'Profit Loss-Amravati-25-26'!$A$9:$T$192,19,0) -> 2686911.7 | AX66: =+AU66+AV66-AW66 -> 2686911.7 | AY66: =+AX66-AS66 -> 666598 | AZ66: =VLOOKUP(A66,'Profit Loss-Amravati-25-26'!$A$9:$V$192,21,0) -> 2728363.2 | BC66: =+AZ66+BA66-BB66 -> 2728363.2 | BD66: =+BC66-AX66 -> 41451.48
A67: PURCHASE PACKING MATERIAL-(IMPORT) | C67: =VLOOKUP(A67,'Profit Loss-Amravati-25-26'!$A$13:$B$190,2,0) -> 149392.31 | F67: =+B67+C67+D67 -> 149392.31 | G67: =VLOOKUP(A67,'Profit Loss-Amravati-25-26'!$A$9:$D$190,3,0) -> 149392.18 | J67: =SUM(G67:I67) -> 149392.18 | K67: 0 | L67: =VLOOKUP(A67,'Profit Loss-Amravati-25-26'!$A$9:$F$190,5,0) -> 261205.55 | O67: =SUM(L67:M67) -> 261205.55 | P67: =+O67-J67 -> 111813.37 | Q67: =VLOOKUP(A67,'Profit Loss-Amravati-25-26'!$A$9:$H$190,7,0) -> 261205.55 | T67: =SUM(Q67:R67) -> 261205.55 | U67: =+T67-O67 -> 0 | V67: =VLOOKUP(A67,'Profit Loss-Amravati-25-26'!$A$9:$J$190,9,0) -> 1140723.6 | Y67: =SUM(V67:W67) -> 1140723.6 | Z67: =+Y67-T67 -> 879518 | AA67: =VLOOKUP(A67,'Profit Loss-Amravati-25-26'!$A$9:$L$192,11,0) -> 1183834.9 | AD67: =+AA67+AB67 -> 1183834.9 | AE67: =+AD67-Y67 -> 43111.32 | AF67: =VLOOKUP(A67,'Profit Loss-Amravati-25-26'!$A$9:$N$192,13,0) -> 1316638.7 | AI67: =+AF67+AG67-AH67 -> 1316638.7 | AJ67: =+AI67-AD67 -> 132803.85 | AK67: =VLOOKUP(A67,'Profit Loss-Amravati-25-26'!$A$9:$P$192,15,0) -> 2087500.6 | AN67: =+AK67+AL67-AM67 -> 2087500.6 | AO67: =+AN67-AI67 -> 770861.86 | AP67: =VLOOKUP(A67,'Profit Loss-Amravati-25-26'!$A$9:$R$192,17,0) -> 2744904.7 | AS67: =+AP67+AQ67-AR67 -> 2744904.7 | AT67: =+AS67-AN67 -> 657404.16 | AU67: =VLOOKUP(A67,'Profit Loss-Amravati-25-26'!$A$9:$T$192,19,0) -> 2744904.7 | AX67: =+AU67+AV67-AW67 -> 2744904.7 | AY67: =+AX67-AS67 -> 0 | AZ67: =VLOOKUP(A67,'Profit Loss-Amravati-25-26'!$A$9:$V$192,21,0) -> 2744904.7 | BC67: =+AZ67+BA67-BB67 -> 2744904.7 | BD67: =+BC67-AX67 -> 0
A68: COOLIE & CARTAGE ON PURCHASE | B68: =VLOOKUP(A68,'Profit Loss-Textile'!$A$8:$B$135,2,0) -> 0 | C68: =VLOOKUP(A68,'Profit Loss-Amravati-25-26'!$A$13:$B$190,2,0) -> 2740 | F68: =+B68+C68+D68 -> 2740 | G68: =VLOOKUP(A68,'Profit Loss-Amravati-25-26'!$A$9:$D$190,3,0) -> 11610 | J68: =SUM(G68:I68) -> 11610 | K68: =+H68+G68-F68 -> 8870 | L68: =VLOOKUP(A68,'Profit Loss-Amravati-25-26'!$A$9:$F$190,5,0) -> 100160 | O68: =SUM(L68:M68) -> 100160 | P68: =+O68-J68 -> 88550 | Q68: =VLOOKUP(A68,'Profit Loss-Amravati-25-26'!$A$9:$H$190,7,0) -> 109690 | T68: =SUM(Q68:R68) -> 109690 | U68: =+T68-O68 -> 9530 | V68: =VLOOKUP(A68,'Profit Loss-Amravati-25-26'!$A$9:$J$190,9,0) -> 139690 | Y68: =SUM(V68:W68) -> 139690 | Z68: =+Y68-T68 -> 30000 | AA68: =VLOOKUP(A68,'Profit Loss-Amravati-25-26'!$A$9:$L$192,11,0) -> 141130 | AD68: =+AA68+AB68 -> 141130 | AE68: =+AD68-Y68 -> 1440 | AF68: =VLOOKUP(A68,'Profit Loss-Amravati-25-26'!$A$9:$N$192,13,0) -> 145330 | AI68: =+AF68+AG68-AH68 -> 145330 | AJ68: =+AI68-AD68 -> 4200 | AK68: =VLOOKUP(A68,'Profit Loss-Amravati-25-26'!$A$9:$P$192,15,0) -> 145330 | AN68: =+AK68+AL68-AM68 -> 145330 | AO68: =+AN68-AI68 -> 0 | AP68: =VLOOKUP(A68,'Profit Loss-Amravati-25-26'!$A$9:$R$192,17,0) -> 152770 | AS68: =+AP68+AQ68-AR68 -> 152770 | AT68: =+AS68-AN68 -> 7440 | AU68: =VLOOKUP(A68,'Profit Loss-Amravati-25-26'!$A$9:$T$192,19,0) -> 152770 | AX68: =+AU68+AV68-AW68 -> 152770 | AY68: =+AX68-AS68 -> 0 | AZ68: =VLOOKUP(A68,'Profit Loss-Amravati-25-26'!$A$9:$V$192,21,0) -> 152770 | BC68: =+AZ68+BA68-BB68 -> 152770 | BD68: =+BC68-AX68 -> 0
A69: CLEARING CHARGES ON IMPORT | C69: =VLOOKUP(A69,'Profit Loss-Amravati-25-26'!$A$13:$B$190,2,0) -> 31619 | F69: =+B69+C69+D69 -> 31619 | G69: =VLOOKUP(A69,'Profit Loss-Amravati-25-26'!$A$9:$D$190,3,0) -> 34440 | J69: =SUM(G69:I69) -> 34440 | K69: =+H69+G69-F69 -> 2821 | L69: =VLOOKUP(A69,'Profit Loss-Amravati-25-26'!$A$9:$F$190,5,0) -> 314381.98 | O69: =SUM(L69:M69) -> 314381.98 | P69: =+O69-J69 -> 279941.98 | Q69: =VLOOKUP(A69,'Profit Loss-Amravati-25-26'!$A$9:$H$190,7,0) -> 324058.98 | T69: =SUM(Q69:R69) -> 324058.98 | U69: =+T69-O69 -> 9677 | V69: =VLOOKUP(A69,'Profit Loss-Amravati-25-26'!$A$9:$J$190,9,0) -> 432611.98 | Y69: =SUM(V69:W69) -> 432611.98 | Z69: =+Y69-T69 -> 108553 | AA69: =VLOOKUP(A69,'Profit Loss-Amravati-25-26'!$A$9:$L$192,11,0) -> 445689.98 | AD69: =+AA69+AB69 -> 445689.98 | AE69: =+AD69-Y69 -> 13078 | AF69: =VLOOKUP(A69,'Profit Loss-Amravati-25-26'!$A$9:$N$192,13,0) -> 559064.98 | AI69: =+AF69+AG69-AH69 -> 559064.98 | AJ69: =+AI69-AD69 -> 113375 | AK69: =VLOOKUP(A69,'Profit Loss-Amravati-25-26'!$A$9:$P$192,15,0) -> 581312.84 | AN69: =+AK69+AL69-AM69 -> 581312.84 | AO69: =+AN69-AI69 -> 22247.86 | AP69: =VLOOKUP(A69,'Profit Loss-Amravati-25-26'!$A$9:$R$192,17,0) -> 603849.48 | AS69: =+AP69+AQ69-AR69 -> 603849.48 | AT69: =+AS69-AN69 -> 22536.64 | AU69: =VLOOKUP(A69,'Profit Loss-Amravati-25-26'!$A$9:$T$192,19,0) -> 639212.44 | AX69: =+AU69+AV69-AW69 -> 639212.44 | AY69: =+AX69-AS69 -> 35362.96 | AZ69: =VLOOKUP(A69,'Profit Loss-Amravati-25-26'!$A$9:$V$192,21,0) -> 701107.44 | BC69: =+AZ69+BA69-BB69 -> 701107.44 | BD69: =+BC69-AX69 -> 61895
A70: JOB WORK | C70: =VLOOKUP(A70,'Profit Loss-Amravati-25-26'!$A$13:$B$190,2,0) -> 2021221.8 | F70: =+B70+C70+D70 -> 2021221.8 | G70: =VLOOKUP(A70,'Profit Loss-Amravati-25-26'!$A$9:$D$190,3,0) -> 2841923.8 | J70: =SUM(G70:I70) -> 2841923.8 | K70: =+H70+G70-F70 -> 820702 | L70: =VLOOKUP(A70,'Profit Loss-Amravati-25-26'!$A$9:$F$190,5,0) -> 3962292.2 | O70: =SUM(L70:M70) -> 3962292.2 | P70: =+O70-J70 -> 1120368.4 | Q70: =VLOOKUP(A70,'Profit Loss-Amravati-25-26'!$A$9:$H$190,7,0) -> 7942144.6 | T70: =SUM(Q70:R70) -> 7942144.6 | U70: =+T70-O70 -> 3979852.4 | V70: =VLOOKUP(A70,'Profit Loss-Amravati-25-26'!$A$9:$J$190,9,0) -> 10354344 | Y70: =SUM(V70:W70) -> 10354344 | Z70: =+Y70-T70 -> 2412198.9 | AA70: =VLOOKUP(A70,'Profit Loss-Amravati-25-26'!$A$9:$L$192,11,0) -> 13260813 | AD70: =+AA70+AB70 -> 13260813 | AE70: =+AD70-Y70 -> 2906469.5 | AF70: =VLOOKUP(A70,'Profit Loss-Amravati-25-26'!$A$9:$N$192,13,0) -> 19834441 | AI70: =+AF70+AG70-AH70 -> 19834441 | AJ70: =+AI70-AD70 -> 6573628 | AK70: =VLOOKUP(A70,'Profit Loss-Amravati-25-26'!$A$9:$P$192,15,0) -> 21276764 | AN70: =+AK70+AL70-AM70 -> 21276764 | AO70: =+AN70-AI70 -> 1442323.1 | AP70: =VLOOKUP(A70,'Profit Loss-Amravati-25-26'!$A$9:$R$192,17,0) -> 22496109 | AS70: =+AP70+AQ70-AR70 -> 22496109 | AT70: =+AS70-AN70 -> 1219344.7 | AU70: =VLOOKUP(A70,'Profit Loss-Amravati-25-26'!$A$9:$T$192,19,0) -> 23705684 | AV70: =VLOOKUP(A70,'Profit Loss-Betul-25-26'!$A$9:$T$141,19,0) -> 50381.2 | AX70: =+AU70+AV70-AW70 -> 23756065 | AY70: =+AX70-AS70 -> 1259956.6 | AZ70: =VLOOKUP(A70,'Profit Loss-Amravati-25-26'!$A$9:$V$192,21,0) -> 25013475 | BA70: =VLOOKUP(A70,'Profit Loss-Betul-25-26'!$A$9:$V$141,21,0) -> 142097.9 | BC70: =+AZ70+BA70-BB70 -> 25155573 | BD70: =+BC70-AX70 -> 1399507.7
A71: CLOSING STOCK | C71: =VLOOKUP(A71,'Profit Loss-Amravati-25-26'!$A$13:$B$190,2,0) -> 155824387 | F71: =+B71+C71+D71 -> 155824387 | G71: =VLOOKUP(A71,'Profit Loss-Amravati-25-26'!$A$9:$D$190,3,0) -> 160389511 | J71: =SUM(G71:I71) -> 160389511 | K71: =+H71+G71-F71 -> 4565124 | L71: =VLOOKUP(A71,'Profit Loss-Amravati-25-26'!$A$9:$F$190,5,0) -> 163256804 | M71: =VLOOKUP(A71,'Profit Loss-Betul-25-26'!$A$9:$F$141,5,0) -> 0 | O71: =SUM(L71:M71) -> 163256804 | P71: =+O71-J71 -> 2867293 | Q71: =VLOOKUP(A71,'Profit Loss-Amravati-25-26'!$A$9:$H$190,7,0) -> 1.5846681e+08 | T71: =SUM(Q71:R71) -> 1.5846681e+08 | U71: =+T71-O71 -> -4789995.9 | V71: =VLOOKUP(A71,'Profit Loss-Amravati-25-26'!$A$9:$J$190,9,0)+8299564 -> 1.6057742e+08 | W71: =VLOOKUP(A71,'Profit Loss-Betul-25-26'!$A$9:$J$141,9,0) -> 0 | Y71: =SUM(V71:W71) -> 1.6057742e+08 | Z71: =+Y71-T71 -> 2110610 | AA71: =VLOOKUP(A71,'Profit Loss-Amravati-25-26'!$A$9:$L$192,11,0) -> 161430162 | AD71: =+AA71+AB71 -> 161430162 | AE71: =+AD71-Y71 -> 852743.86 | AF71: =VLOOKUP(A71,'Profit Loss-Amravati-25-26'!$A$9:$N$192,13,0) -> 167843857 | AG71: =VLOOKUP(A71,'Profit Loss-Betul-25-26'!$A$9:$N$141,13,0) -> 0 | AI71: =+AF71+AG71-AH71 -> 167843857 | AJ71: =+AI71-AD71 -> 6413695 | AK71: =VLOOKUP(A71,'Profit Loss-Amravati-25-26'!$A$9:$P$192,15,0) -> 182285500 | AL71: =VLOOKUP(A71,'Profit Loss-Betul-25-26'!$A$9:$P$141,15,0) -> 0 | AN71: =+AK71+AL71-AM71 -> 182285500 | AO71: =+AN71-AI71 -> 14441643 | AP71: =VLOOKUP(A71,'Profit Loss-Amravati-25-26'!$A$9:$R$192,17,0) -> 170675054 | AQ71: =VLOOKUP(A71,'Profit Loss-Betul-25-26'!$A$9:$R$141,17,0) -> 0 | AS71: =+AP71+AQ71-AR71 -> 170675054 | AT71: =+AS71-AN71 -> -11610446 | AU71: =VLOOKUP(A71,'Profit Loss-Amravati-25-26'!$A$9:$T$192,19,0) -> 1.8851891e+08 | AV71: =VLOOKUP(A71,'Profit Loss-Betul-25-26'!$A$9:$T$141,19,0) -> 0 | AX71: =+AU71+AV71-AW71 -> 1.8851891e+08 | AY71: =+AX71-AS71 -> 17843851 | AZ71: =VLOOKUP(A71,'Profit Loss-Amravati-25-26'!$A$9:$V$192,21,0) -> 169525758 | BA71: =VLOOKUP(A71,'Profit Loss-Betul-25-26'!$A$9:$V$141,21,0) -> 0 | BC71: =+AZ71+BA71-BB71 -> 169525758 | BD71: =+BC71-AX71 -> -18993147
A72: TOTAL COST OF GOODS SOLD | B72: =SUM(B51:B71)-B71 -> 0 | C72: =SUM(C51:C70)-C71 -> 41072511 | D72: =SUM(D51:D70)-D71 -> 0 | F72: =SUM(F51:F70)-F71 -> 39570639 | G72: =SUM(G51:G70)-G71 -> 97292996 | H72: =SUM(H51:H70)-H71 -> 0 | I72: =SUM(I51:I70)-I71 -> -2501098 | J72: =SUM(J51:J70)-J71 -> 94791898 | K72: =SUM(K51:K70)-K71 -> 55221260 | L72: =SUM(L51:L70)-L71 -> 1.5454615e+08 | M72: =SUM(M51:M70)-M71 -> 0 | ... BD72: =SUM(BD51:BD70)-BD71 -> 85586491 | BE72: =+BC72-AX72-BD72 -> 1.7881393e-07
A73: THROUGHPUT | C73: =C47-C72 -> 8547051.8 | D73: =D47-D72 -> 1501872 | F73: =F47-F72 -> 10048924 | G73: =G47-G72 -> 16499377 | H73: =H47-H72 -> 2501098 | J73: =J47-J72 -> 19000475 | K73: =K47-K72 -> 8951551.5 | L73: =L47-L72 -> 15970585 | M73: =M47-M72 -> 5273679 | O73: =O47-O72 -> 21244264 | P73: =P47-P72 -> 2243788.5 | Q73: =Q47-Q72 -> 36500231 | R73: =R47-R72 -> 9013683 | T73: =T47-T72 -> 45161587 | U73: =U47-U72 -> 23917323 | V73: =V47-V72 -> 44516955 | W73: =W47-W72 -> 12180632 | Y73: =Y47-Y72 -> 46830224 | Z73: =Z47-Z72 -> 1668636.5 | AA73: =AA47-AA72 -> 47060664 | AB73: =AB47-AB72 -> 15370014 | AD73: =AD47-AD72 -> 62430678 | AE73: =AE47-AE72 -> 15600454 | AF73: =AF47-AF72 -> 48511172 | AG73: =AG47-AG72 -> 16403738 | AI73: =AI47-AI72 -> 64914910 | AJ73: =AJ47-AJ72 -> 2484231.5 | AK73: =AK47-AK72 -> 81365461 | AL73: =AL47-AL72 -> 18492890 | AN73: =AN47-AN72 -> 99858351 | AO73: =AO47-AO72 -> 34943442 | AP73: =AP47-AP72 -> 1.1184139e+08 | AQ73: =AQ47-AQ72 -> 21646891 | AS73: =AS47-AS72 -> 1.3348828e+08 | AT73: =AT47-AT72 -> 33629933 | AU73: =AU47-AU72 -> 1.1685677e+08 | AV73: =AV47-AV72 -> 24884067 | AX73: =AX47-AX72 -> 1.4174084e+08 | AY73: =AY47-AY72 -> 8252551.3 | AZ73: =AZ47-AZ72 -> 1.1931647e+08 | BA73: =BA47-BA72 -> 26826027 | BC73: =BC47-BC72 -> 1.461425e+08 | BD73: =BD47-BD72 -> 4401661.5 | BE73: =+BC73-AX73-BD73 -> -2.0861626e-07
A74: Throughput as % of Revenue from operations | C74: =+C73/C47*100 -> 17.225166 | D74: 0 | F74: =+F73/F47*100 -> 20.25194 | G74: =+G73/G47*100 -> 14.499546 | H74: 0 | J74: =+J73/J47*100 -> 16.697495 | K74: =+K73/K47*100 -> 13.949134 | L74: =+L73/L47*100 -> 9.3659929 | M74: =+M73/M47*100 -> 100 | O74: =+O73/O47*100 -> 12.45967 | P74: =+P73/P47*100 -> 3.9564715 | Q74: =+Q73/Q47*100 -> 13.988476 | R74: =+R73/R47*100 -> 99.995562 | T74: =+T73/T47*100 -> 17.332118 | U74: =+U73/U47*100 -> 26.55661 | V74: =+V73/V47*100 -> 13.733902 | W74: =+W73/W47*100 -> 99.996716 | Y74: =+Y73/Y47*100 -> 14.901778 | Z74: =+Z73/Z47*100 -> 3.1077118 | AA74: =+AA73/AA47*100 -> 11.728915 | AB74: =+AB73/AB47*100 -> 99.997398 | AD74: =+AD73/AD47*100 -> 15.560064 | AE74: =+AE73/AE47*100 -> 17.93888 | AF74: =+AF73/AF47*100 -> 10.537531 | AG74: =+AG73/AG47*100 -> 99.991039 | AI74: =+AI73/AI47*100 -> 14.101663 | AJ74: =+AJ73/AJ47*100 -> 4.2026308 | AK74: =+AK73/AK47*100 -> 13.681422 | AL74: =+AL73/AL47*100 -> 99.928726 | AN74: =+AN73/AN47*100 -> 16.791483 | AO74: =+AO73/AO47*100 -> 26.007073 | AP74: =+AP73/AP47*100 -> 14.595823 | AQ74: =+AQ73/AQ47*100 -> 99.781325 | AS74: =+AS73/AS47*100 -> 17.421263 | AT74: =+AT73/AT47*100 -> 19.604574 | AU74: =+AU73/AU47*100 -> 13.885299 | AV74: =+AV73/AV47*100 -> 99.608432 | AX74: =+AX73/AX47*100 -> 16.842475 | AY74: =+AY73/AY47*100 -> 10.955188 | AZ74: =+AZ73/AZ47*100 -> 12.808045 | BA74: =+BA73/BA47*100 -> 99.298412 | BC74: =+BC73/BC47*100 -> 15.688001 | BD74: =+BD73/BD47*100 -> 4.8913789
A76: FIXED EXPENSES | M76: =VLOOKUP(A76,'Profit Loss-Betul-25-26'!$A$9:$F$141,5,0) -> 0
A77: MAN POWER SUPPLY CHARGES | B77: =VLOOKUP(A77,'Profit Loss-Textile'!$A$8:$B$135,2,0) -> 0 | F77: =+B77+C77+D77 -> 0 | K77: =+H77+G77-F77 -> 0 | P77: =+L77+K77-J77 -> 0 | U77: =+Q77+P77-O77 -> 0 | Z77: =+V77+U77-T77 -> 0 | AE77: =+AA77+Z77-Y77 -> 0 | AJ77: =+AF77+AE77-AD77 -> 0 | AO77: =+AK77+AJ77-AI77 -> 0 | AT77: =+AP77+AO77-AN77 -> 0 | AY77: =+AU77+AT77-AS77 -> 0 | BD77: =+AZ77+AY77-AX77 -> 0
A78: PURCHASE STORES & SPARES | B78: =VLOOKUP(A78,'Profit Loss-Textile'!$A$8:$B$135,2,0) -> 0 | C78: =VLOOKUP(A78,'Profit Loss-Amravati-25-26'!$A$13:$B$190,2,0) -> 0 | D78: =VLOOKUP(A78,'Profit Loss-Betul-25-26'!$A$9:$B$140,2,0) -> 2730 | F78: =+B78+C78+D78 -> 2730 | G78: =VLOOKUP(A78,'Profit Loss-Amravati-25-26'!$A$9:$D$190,3,0) -> 44156 | H78: =VLOOKUP(A78,'Profit Loss-Betul-25-26'!$A$9:$D$140,3,0) -> 5340 | J78: =SUM(G78:I78) -> 49496 | K78: =+H78+G78-F78 -> 46766 | L78: =VLOOKUP(A78,'Profit Loss-Amravati-25-26'!$A$9:$F$190,5,0) -> 51481 | M78: =VLOOKUP(A78,'Profit Loss-Betul-25-26'!$A$9:$F$141,5,0) -> 5340 | O78: =SUM(L78:M78) -> 56821 | P78: =+O78-J78 -> 7325 | Q78: =VLOOKUP(A78,'Profit Loss-Amravati-25-26'!$A$9:$H$190,7,0) -> 67930 | R78: =VLOOKUP(A78,'Profit Loss-Betul-25-26'!$A$9:$H$141,7,0) -> 6497 | T78: =SUM(Q78:S78) -> 74427 | U78: =+T78-O78 -> 17606 | V78: =VLOOKUP(A78,'Profit Loss-Amravati-25-26'!$A$9:$J$190,9,0) -> 91530 | W78: =VLOOKUP(A78,'Profit Loss-Betul-25-26'!$A$9:$J$141,9,0) -> 11917 | Y78: =SUM(V78:X78) -> 103447 | Z78: =+Y78-T78 -> 29020 | AA78: =VLOOKUP(A78,'Profit Loss-Amravati-25-26'!$A$9:$L$192,11,0) -> 112236.22 | AB78: =VLOOKUP(A78,'Profit Loss-Betul-25-26'!$A$9:$L$141,11,0) -> 11917 | AD78: =+AA78+AB78 -> 124153.22 | AE78: =+AD78-Y78 -> 20706.22 | AF78: =VLOOKUP(A78,'Profit Loss-Amravati-25-26'!$A$9:$N$192,13,0) -> 282891.22 | AG78: =VLOOKUP(A78,'Profit Loss-Betul-25-26'!$A$9:$N$141,13,0) -> 34338 | AI78: =+AF78+AG78-AH78 -> 317229.22 | AJ78: =+AI78-AD78 -> 193076 | AK78: =VLOOKUP(A78,'Profit Loss-Amravati-25-26'!$A$9:$P$192,15,0) -> 352598.22 | AL78: =VLOOKUP(A78,'Profit Loss-Betul-25-26'!$A$9:$P$141,15,0) -> 46563 | AN78: =+AK78+AL78-AM78 -> 399161.22 | AO78: =+AN78-AI78 -> 81932 | AP78: =VLOOKUP(A78,'Profit Loss-Amravati-25-26'!$A$9:$R$192,17,0) -> 529427.22 | AQ78: =VLOOKUP(A78,'Profit Loss-Betul-25-26'!$A$9:$R$141,17,0) -> 51152 | AS78: =+AP78+AQ78-AR78 -> 580579.22 | AT78: =+AS78-AN78 -> 181418 | AU78: =VLOOKUP(A78,'Profit Loss-Amravati-25-26'!$A$9:$T$192,19,0) -> 529427.22 | AV78: =VLOOKUP(A78,'Profit Loss-Betul-25-26'!$A$9:$T$141,19,0) -> 51152 | AX78: =+AU78+AV78-AW78 -> 580579.22 | AY78: =+AX78-AS78 -> 0 | AZ78: =VLOOKUP(A78,'Profit Loss-Amravati-25-26'!$A$9:$V$192,21,0) -> 685459.22 | BA78: =VLOOKUP(A78,'Profit Loss-Betul-25-26'!$A$9:$V$141,21,0) -> 51152 | BC78: =+AZ78+BA78-BB78 -> 736611.22 | BD78: =+BC78-AX78 -> 156032
A79: PURCHASE STORE & SPARES (FABRIC) | K79: =+H79+G79-F79 -> 0 | O79: =SUM(L79:M79) -> 0 | P79: =+O79-J79 -> 0 | Q79: =VLOOKUP(A79,'Profit Loss-Amravati-25-26'!$A$9:$H$190,7,0) -> 8825 | T79: =SUM(Q79:S79) -> 8825 | U79: =+T79-O79 -> 8825 | V79: =VLOOKUP(A79,'Profit Loss-Amravati-25-26'!$A$9:$J$190,9,0) -> 8825 | Y79: =SUM(V79:X79) -> 8825 | Z79: =+Y79-T79 -> 0 | AA79: =VLOOKUP(A79,'Profit Loss-Amravati-25-26'!$A$9:$L$192,11,0) -> 21784.8 | AD79: =+AA79+AB79 -> 21784.8 | AE79: =+AD79-Y79 -> 12959.8 | AF79: =VLOOKUP(A79,'Profit Loss-Amravati-25-26'!$A$9:$N$192,13,0) -> 21784.8 | AI79: =+AF79+AG79-AH79 -> 21784.8 | AJ79: =+AI79-AD79 -> 0 | AK79: =VLOOKUP(A79,'Profit Loss-Amravati-25-26'!$A$9:$P$192,15,0) -> 21784.8 | AN79: =+AK79+AL79-AM79 -> 21784.8 | AO79: =+AN79-AI79 -> 0 | AP79: =VLOOKUP(A79,'Profit Loss-Amravati-25-26'!$A$9:$R$192,17,0) -> 21784.8 | AS79: =+AP79+AQ79-AR79 -> 21784.8 | AT79: =+AS79-AN79 -> 0 | AU79: =VLOOKUP(A79,'Profit Loss-Amravati-25-26'!$A$9:$T$192,19,0) -> 21784.8 | AX79: =+AU79+AV79-AW79 -> 21784.8 | AY79: =+AX79-AS79 -> 0 | AZ79: =VLOOKUP(A79,'Profit Loss-Amravati-25-26'!$A$9:$V$192,21,0) -> 21784.8 | BC79: =+AZ79+BA79-BB79 -> 21784.8 | BD79: =+BC79-AX79 -> 0
A80: DETENTION CHARGES ON IMPORT | AU80: =VLOOKUP(A80,'Profit Loss-Amravati-25-26'!$A$9:$T$192,19,0) -> 1817 | AX80: =+AU80+AV80-AW80 -> 1817 | AY80: =+AX80-AS80 -> 1817 | AZ80: =VLOOKUP(A80,'Profit Loss-Amravati-25-26'!$A$9:$V$192,21,0) -> 1817 | BC80: =+AZ80+BA80-BB80 -> 1817 | BD80: =+BC80-AX80 -> 0
A81: WATER CHARGES | C81: =VLOOKUP(A81,'Profit Loss-Amravati-25-26'!$A$13:$B$190,2,0) -> 510 | D81: =VLOOKUP(A81,'Profit Loss-Betul-25-26'!$A$9:$B$140,2,0) -> 0 | F81: =+B81+C81+D81 -> 510 | G81: =VLOOKUP(A81,'Profit Loss-Amravati-25-26'!$A$9:$D$190,3,0) -> 1198 | H81: =VLOOKUP(A81,'Profit Loss-Betul-25-26'!$A$9:$D$140,3,0) -> 0 | J81: =SUM(G81:I81) -> 1198 | K81: =+H81+G81-F81 -> 688 | L81: =VLOOKUP(A81,'Profit Loss-Amravati-25-26'!$A$9:$F$190,5,0) -> 1198 | M81: =VLOOKUP(A81,'Profit Loss-Betul-25-26'!$A$9:$F$141,5,0) -> 0 | O81: =SUM(L81:M81) -> 1198 | P81: =+O81-J81 -> 0 | Q81: =VLOOKUP(A81,'Profit Loss-Amravati-25-26'!$A$9:$H$190,7,0) -> 1198 | R81: =VLOOKUP(A81,'Profit Loss-Betul-25-26'!$A$9:$H$141,7,0) -> 0 | T81: =SUM(Q81:S81) -> 1198 | U81: =+T81-O81 -> 0 | V81: =VLOOKUP(A81,'Profit Loss-Amravati-25-26'!$A$9:$J$190,9,0) -> 1198 | W81: =VLOOKUP(A81,'Profit Loss-Betul-25-26'!$A$9:$J$141,9,0) -> 0 | Y81: =SUM(V81:X81) -> 1198 | Z81: =+Y81-T81 -> 0 | AA81: =VLOOKUP(A81,'Profit Loss-Amravati-25-26'!$A$9:$L$192,11,0) -> 1198 | AB81: =VLOOKUP(A81,'Profit Loss-Betul-25-26'!$A$9:$L$141,11,0) -> 0 | AD81: =+AA81+AB81 -> 1198 | AE81: =+AD81-Y81 -> 0 | AF81: =VLOOKUP(A81,'Profit Loss-Amravati-25-26'!$A$9:$N$192,13,0) -> 1198 | AG81: =VLOOKUP(A81,'Profit Loss-Betul-25-26'!$A$9:$N$141,13,0) -> 0 | AI81: =+AF81+AG81-AH81 -> 1198 | AJ81: =+AI81-AD81 -> 0 | AK81: =VLOOKUP(A81,'Profit Loss-Amravati-25-26'!$A$9:$P$192,15,0) -> 1198 | AL81: =VLOOKUP(A81,'Profit Loss-Betul-25-26'!$A$9:$P$141,15,0) -> 0 | AN81: =+AK81+AL81-AM81 -> 1198 | AO81: =+AN81-AI81 -> 0 | AP81: =VLOOKUP(A81,'Profit Loss-Amravati-25-26'!$A$9:$R$192,17,0) -> 1198 | AQ81: =VLOOKUP(A81,'Profit Loss-Betul-25-26'!$A$9:$R$141,17,0) -> 0 | AS81: =+AP81+AQ81-AR81 -> 1198 | AT81: =+AS81-AN81 -> 0 | AU81: =VLOOKUP(A81,'Profit Loss-Amravati-25-26'!$A$9:$T$192,19,0) -> 2198 | AV81: =VLOOKUP(A81,'Profit Loss-Betul-25-26'!$A$9:$T$141,19,0) -> 0 | AX81: =+AU81+AV81-AW81 -> 2198 | AY81: =+AX81-AS81 -> 1000 | AZ81: =VLOOKUP(A81,'Profit Loss-Amravati-25-26'!$A$9:$V$192,21,0) -> 2698 | BA81: =VLOOKUP(A81,'Profit Loss-Betul-25-26'!$A$9:$V$141,21,0) -> 0 | BC81: =+AZ81+BA81-BB81 -> 2698 | BD81: =+BC81-AX81 -> 500
A82: POWER | C82: =VLOOKUP(A82,'Profit Loss-Amravati-25-26'!$A$13:$B$190,2,0) -> -1100 | D82: =VLOOKUP(A82,'Profit Loss-Betul-25-26'!$A$9:$B$140,2,0) -> 146247 | F82: =+B82+C82+D82 -> 145147 | G82: =VLOOKUP(A82,'Profit Loss-Amravati-25-26'!$A$9:$D$190,3,0) -> -1670 | H82: =VLOOKUP(A82,'Profit Loss-Betul-25-26'!$A$9:$D$140,3,0) -> 300528 | J82: =SUM(G82:I82) -> 298858 | K82: =+H82+G82-F82 -> 153711 | L82: =VLOOKUP(A82,'Profit Loss-Amravati-25-26'!$A$9:$F$190,5,0) -> -2260 | M82: =VLOOKUP(A82,'Profit Loss-Betul-25-26'!$A$9:$F$141,5,0) -> 450528 | O82: =SUM(L82:M82) -> 448268 | P82: =+O82-J82 -> 149410 | Q82: =VLOOKUP(A82,'Profit Loss-Amravati-25-26'!$A$9:$H$190,7,0) -> -3110 | R82: =VLOOKUP(A82,'Profit Loss-Betul-25-26'!$A$9:$H$141,7,0) -> 668010 | T82: =SUM(Q82:S82) -> 664900 | U82: =+T82-O82 -> 216632 | V82: =VLOOKUP(A82,'Profit Loss-Amravati-25-26'!$A$9:$J$190,9,0) -> -4140 | W82: =VLOOKUP(A82,'Profit Loss-Betul-25-26'!$A$9:$J$141,9,0) -> 853010 | Y82: =SUM(V82:X82) -> 848870 | Z82: =+Y82-T82 -> 183970 | AA82: =VLOOKUP(A82,'Profit Loss-Amravati-25-26'!$A$9:$L$192,11,0) -> -5020 | AB82: =VLOOKUP(A82,'Profit Loss-Betul-25-26'!$A$9:$L$141,11,0) -> 985942 | AD82: =+AA82+AB82 -> 980922 | AE82: =+AD82-Y82 -> 132052 | AF82: =VLOOKUP(A82,'Profit Loss-Amravati-25-26'!$A$9:$N$192,13,0) -> -6020 | AG82: =VLOOKUP(A82,'Profit Loss-Betul-25-26'!$A$9:$N$141,13,0) -> 1135660 | AI82: =+AF82+AG82-AH82 -> 1129640 | AJ82: =+AI82-AD82 -> 148718 | AK82: =VLOOKUP(A82,'Profit Loss-Amravati-25-26'!$A$9:$P$192,15,0) -> -6020 | AL82: =VLOOKUP(A82,'Profit Loss-Betul-25-26'!$A$9:$P$141,15,0) -> 1333357 | AN82: =+AK82+AL82-AM82 -> 1327337 | AO82: =+AN82-AI82 -> 197697 | AP82: =VLOOKUP(A82,'Profit Loss-Amravati-25-26'!$A$9:$R$192,17,0) -> 231120 | AQ82: =VLOOKUP(A82,'Profit Loss-Betul-25-26'!$A$9:$R$141,17,0) -> 1480619 | AS82: =+AP82+AQ82-AR82 -> 1711739 | AT82: =+AS82-AN82 -> 384402 | AU82: =VLOOKUP(A82,'Profit Loss-Amravati-25-26'!$A$9:$T$192,19,0) -> 351120 | AV82: =VLOOKUP(A82,'Profit Loss-Betul-25-26'!$A$9:$T$141,19,0) -> 1672586 | AX82: =+AU82+AV82-AW82 -> 2023706 | AY82: =+AX82-AS82 -> 311967 | AZ82: =VLOOKUP(A82,'Profit Loss-Amravati-25-26'!$A$9:$V$192,21,0) -> 444490 | BA82: =VLOOKUP(A82,'Profit Loss-Betul-25-26'!$A$9:$V$141,21,0) -> 1852183 | BC82: =+AZ82+BA82-BB82 -> 2296673 | BD82: =+BC82-AX82 -> 272967
A83: ELECTRICAL ITEMS | B83: =VLOOKUP(A83,'Profit Loss-Textile'!$A$8:$B$135,2,0) -> 0 | C83: =VLOOKUP(A83,'Profit Loss-Amravati-25-26'!$A$13:$B$190,2,0) -> 5020.4 | F83: =+B83+C83+D83 -> 5020.4 | G83: =VLOOKUP(A83,'Profit Loss-Amravati-25-26'!$A$9:$D$190,3,0) -> 5020.4 | J83: =SUM(G83:I83) -> 5020.4 | K83: =+H83+G83-F83 -> 0 | L83: =VLOOKUP(A83,'Profit Loss-Amravati-25-26'!$A$9:$F$190,5,0) -> 10511.88 | O83: =SUM(L83:M83) -> 10511.88 | P83: =+O83-J83 -> 5491.48 | Q83: =VLOOKUP(A83,'Profit Loss-Amravati-25-26'!$A$9:$H$190,7,0) -> 36893.88 | T83: =SUM(Q83:S83) -> 36893.88 | U83: =+T83-O83 -> 26382 | V83: =VLOOKUP(A83,'Profit Loss-Amravati-25-26'!$A$9:$J$190,9,0) -> 10511.88 | Y83: =SUM(V83:X83) -> 10511.88 | Z83: =+Y83-T83 -> -26382 | AA83: =VLOOKUP(A83,'Profit Loss-Amravati-25-26'!$A$9:$L$192,11,0) -> 13011.88 | AD83: =+AA83+AB83 -> 13011.88 | AE83: =+AD83-Y83 -> 2500 | AF83: =VLOOKUP(A83,'Profit Loss-Amravati-25-26'!$A$9:$N$192,13,0) -> 13011.88 | AI83: =+AF83+AG83-AH83 -> 13011.88 | AJ83: =+AI83-AD83 -> 0 | AK83: =VLOOKUP(A83,'Profit Loss-Amravati-25-26'!$A$9:$P$192,15,0) -> 13011.88 | AN83: =+AK83+AL83-AM83 -> 13011.88 | AO83: =+AN83-AI83 -> 0 | AP83: =VLOOKUP(A83,'Profit Loss-Amravati-25-26'!$A$9:$R$192,17,0) -> 39393.88 | AS83: =+AP83+AQ83-AR83 -> 39393.88 | AT83: =+AS83-AN83 -> 26382 | AU83: =VLOOKUP(A83,'Profit Loss-Amravati-25-26'!$A$9:$T$192,19,0) -> 39393.88 | AX83: =+AU83+AV83-AW83 -> 39393.88 | AY83: =+AX83-AS83 -> 0 | AZ83: =VLOOKUP(A83,'Profit Loss-Amravati-25-26'!$A$9:$V$192,21,0) -> 39393.88 | BC83: =+AZ83+BA83-BB83 -> 39393.88 | BD83: =+BC83-AX83 -> 0
A84: INSPECTION/TESTING | C84: =VLOOKUP(A84,'Profit Loss-Amravati-25-26'!$A$13:$B$190,2,0) -> 154906.9 | F84: =+B84+C84+D84 -> 154906.9 | G84: =VLOOKUP(A84,'Profit Loss-Amravati-25-26'!$A$9:$D$190,3,0) -> 448759.9 | J84: =SUM(G84:I84) -> 448759.9 | K84: =+H84+G84-F84 -> 293853 | L84: =VLOOKUP(A84,'Profit Loss-Amravati-25-26'!$A$9:$F$190,5,0) -> 559200.9 | O84: =SUM(L84:M84) -> 559200.9 | P84: =+O84-J84 -> 110441 | Q84: =VLOOKUP(A84,'Profit Loss-Amravati-25-26'!$A$9:$H$190,7,0) -> 789858.5 | T84: =SUM(Q84:S84) -> 789858.5 | U84: =+T84-O84 -> 230657.6 | V84: =VLOOKUP(A84,'Profit Loss-Amravati-25-26'!$A$9:$J$190,9,0) -> 954250.7 | Y84: =SUM(V84:X84) -> 954250.7 | Z84: =+Y84-T84 -> 164392.2 | AA84: =VLOOKUP(A84,'Profit Loss-Amravati-25-26'!$A$9:$L$192,11,0) -> 1251679.7 | AD84: =+AA84+AB84 -> 1251679.7 | AE84: =+AD84-Y84 -> 297429.03 | AF84: =VLOOKUP(A84,'Profit Loss-Amravati-25-26'!$A$9:$N$192,13,0) -> 1683085.6 | AI84: =+AF84+AG84-AH84 -> 1683085.6 | AJ84: =+AI84-AD84 -> 431405.85 | AK84: =VLOOKUP(A84,'Profit Loss-Amravati-25-26'!$A$9:$P$192,15,0) -> 1939596.4 | AN84: =+AK84+AL84-AM84 -> 1939596.4 | AO84: =+AN84-AI84 -> 256510.87 | AP84: =VLOOKUP(A84,'Profit Loss-Amravati-25-26'!$A$9:$R$192,17,0) -> 2017706.4 | AS84: =+AP84+AQ84-AR84 -> 2017706.4 | AT84: =+AS84-AN84 -> 78110 | AU84: =VLOOKUP(A84,'Profit Loss-Amravati-25-26'!$A$9:$T$192,19,0) -> 2282203.2 | AX84: =+AU84+AV84-AW84 -> 2282203.2 | AY84: =+AX84-AS84 -> 264496.8 | AZ84: =VLOOKUP(A84,'Profit Loss-Amravati-25-26'!$A$9:$V$192,21,0) -> 2398712.2 | BC84: =+AZ84+BA84-BB84 -> 2398712.2 | BD84: =+BC84-AX84 -> 116509
A85: Opening Stock of Electrical Item | C85: =VLOOKUP(A85,'Profit Loss-Amravati-25-26'!$A$13:$B$190,2,0) -> 564066 | F85: =+B85+C85+D85 -> 564066 | G85: =+F85 -> 564066 | J85: =SUM(G85:I85) -> 564066 | K85: =+H85+G85-F85 -> 0 | L85: =VLOOKUP(A85,'Profit Loss-Amravati-25-26'!$A$9:$F$190,5,0) -> 564066 | O85: =SUM(L85:M85) -> 564066 | P85: =+O85-J85 -> 0 | Q85: =VLOOKUP(A85,'Profit Loss-Amravati-25-26'!$A$9:$H$190,7,0) -> 564066 | T85: =SUM(Q85:S85) -> 564066 | U85: =+T85-O85 -> 0 | V85: =VLOOKUP(A85,'Profit Loss-Amravati-25-26'!$A$9:$J$190,9,0) -> 564066 | Y85: =SUM(V85:X85) -> 564066 | Z85: =+Y85-T85 -> 0 | AA85: =VLOOKUP(A85,'Profit Loss-Amravati-25-26'!$A$9:$L$192,11,0) -> 564066 | AD85: =+AA85+AB85 -> 564066 | AE85: =+AD85-Y85 -> 0 | AF85: =VLOOKUP(A85,'Profit Loss-Amravati-25-26'!$A$9:$N$192,13,0) -> 564066 | AI85: =+AF85+AG85-AH85 -> 564066 | AJ85: =+AI85-AD85 -> 0 | AK85: =VLOOKUP(A85,'Profit Loss-Amravati-25-26'!$A$9:$P$192,15,0) -> 564066 | AN85: =+AK85+AL85-AM85 -> 564066 | AO85: =+AN85-AI85 -> 0 | AP85: =VLOOKUP(A85,'Profit Loss-Amravati-25-26'!$A$9:$R$192,17,0) -> 564066 | AS85: =+AP85+AQ85-AR85 -> 564066 | AT85: =+AS85-AN85 -> 0 | AU85: =VLOOKUP(A85,'Profit Loss-Amravati-25-26'!$A$9:$T$192,19,0) -> 564066 | AX85: =+AU85+AV85-AW85 -> 564066 | AY85: =+AX85-AS85 -> 0 | AZ85: =VLOOKUP(A85,'Profit Loss-Amravati-25-26'!$A$9:$V$192,21,0) -> 564066 | BC85: =+AZ85+BA85-BB85 -> 564066 | BD85: =+BC85-AX85 -> 0
A86: Closing Stock of Electrical Item | C86: =VLOOKUP(A86,'Profit Loss-Amravati-25-26'!$A$13:$B$190,2,0) -> -583066 | F86: =+B86+C86+D86 -> -583066 | G86: =+'Profit Loss-Amravati-25-26'!C85 -> 0 | J86: =SUM(G86:I86) -> 0 | K86: =+H86+G86-F86 -> 583066 | L86: =VLOOKUP(A86,'Profit Loss-Amravati-25-26'!$A$9:$F$190,5,0) -> -671047 | O86: =SUM(L86:M86) -> -671047 | P86: =+O86-J86 -> -671047 | Q86: =VLOOKUP(A86,'Profit Loss-Amravati-25-26'!$A$9:$H$190,7,0) -> -841953.5 | T86: =SUM(Q86:S86) -> -841953.5 | U86: =+T86-O86 -> -170906.5 | V86: =VLOOKUP(A86,'Profit Loss-Amravati-25-26'!$A$9:$J$190,9,0) -> -1480923.7 | Y86: =SUM(V86:X86) -> -1480923.7 | Z86: =+Y86-T86 -> -638970.2 | AA86: =VLOOKUP(A86,'Profit Loss-Amravati-25-26'!$A$9:$L$192,11,0) -> -826333 | AD86: =+AA86+AB86 -> -826333 | AE86: =+AD86-Y86 -> 654590.7 | AF86: =VLOOKUP(A86,'Profit Loss-Amravati-25-26'!$A$9:$N$192,13,0) -> -1094236 | AI86: =+AF86+AG86-AH86 -> -1094236 | AJ86: =+AI86-AD86 -> -267903 | AK86: =VLOOKUP(A86,'Profit Loss-Amravati-25-26'!$A$9:$P$192,15,0) -> -1133460 | AN86: =+AK86+AL86-AM86 -> -1133460 | AO86: =+AN86-AI86 -> -39224 | AP86: =VLOOKUP(A86,'Profit Loss-Amravati-25-26'!$A$9:$R$192,17,0) -> -1196226 | AS86: =+AP86+AQ86-AR86 -> -1196226 | AT86: =+AS86-AN86 -> -62766 | AU86: =VLOOKUP(A86,'Profit Loss-Amravati-25-26'!$A$9:$T$192,19,0) -> -1133861 | AX86: =+AU86+AV86-AW86 -> -1133861 | AY86: =+AX86-AS86 -> 62365 | AZ86: =VLOOKUP(A86,'Profit Loss-Amravati-25-26'!$A$9:$V$192,21,0) -> -1101849 | BC86: =+AZ86+BA86-BB86 -> -1101849 | BD86: =+BC86-AX86 -> 32012
A87: ELECTRICAL ITEM - GARMENT | C87: =VLOOKUP(A87,'Profit Loss-Amravati-25-26'!$A$13:$B$190,2,0) -> 59130.6 | D87: =VLOOKUP(A87,'Profit Loss-Betul-25-26'!$A$9:$B$140,2,0) -> 18120 | F87: =+B87+C87+D87 -> 77250.6 | G87: =VLOOKUP(A87,'Profit Loss-Amravati-25-26'!$A$9:$D$190,3,0) -> 373364.48 | H87: =VLOOKUP(A87,'Profit Loss-Betul-25-26'!$A$9:$D$140,3,0) -> 18120 | J87: =SUM(G87:I87) -> 391484.48 | K87: =+H87+G87-F87 -> 314233.88 | L87: =VLOOKUP(A87,'Profit Loss-Amravati-25-26'!$A$9:$F$190,5,0) -> 428677.54 | M87: =VLOOKUP(A87,'Profit Loss-Betul-25-26'!$A$9:$F$141,5,0) -> 96043.72 | O87: =SUM(L87:M87) -> 524721.26 | P87: =+O87-J87 -> 133236.78 | Q87: =VLOOKUP(A87,'Profit Loss-Amravati-25-26'!$A$9:$H$190,7,0) -> 470977.14 | R87: =VLOOKUP(A87,'Profit Loss-Betul-25-26'!$A$9:$H$141,7,0) -> 96043.72 | T87: =SUM(Q87:S87) -> 567020.86 | U87: =+T87-O87 -> 42299.6 | V87: =VLOOKUP(A87,'Profit Loss-Amravati-25-26'!$A$9:$J$190,9,0) -> 500499.18 | W87: =VLOOKUP(A87,'Profit Loss-Betul-25-26'!$A$9:$J$141,9,0) -> 96043.72 | Y87: =SUM(V87:X87) -> 596542.9 | Z87: =+Y87-T87 -> 29522.04 | AA87: =VLOOKUP(A87,'Profit Loss-Amravati-25-26'!$A$9:$L$192,11,0) -> 518256.82 | AB87: =VLOOKUP(A87,'Profit Loss-Betul-25-26'!$A$9:$L$141,11,0) -> 96043.72 | AD87: =+AA87+AB87 -> 614300.54 | AE87: =+AD87-Y87 -> 17757.64 | AF87: =VLOOKUP(A87,'Profit Loss-Amravati-25-26'!$A$9:$N$192,13,0) -> 518256.82 | AG87: =VLOOKUP(A87,'Profit Loss-Betul-25-26'!$A$9:$N$141,13,0) -> 96043.72 | AI87: =+AF87+AG87-AH87 -> 614300.54 | AJ87: =+AI87-AD87 -> 0 | AK87: =VLOOKUP(A87,'Profit Loss-Amravati-25-26'!$A$9:$P$192,15,0) -> 523880.5 | AL87: =VLOOKUP(A87,'Profit Loss-Betul-25-26'!$A$9:$P$141,15,0) -> 107043.72 | AN87: =+AK87+AL87-AM87 -> 630924.22 | AO87: =+AN87-AI87 -> 16623.68 | AP87: =VLOOKUP(A87,'Profit Loss-Amravati-25-26'!$A$9:$R$192,17,0) -> 602137.82 | AQ87: =VLOOKUP(A87,'Profit Loss-Betul-25-26'!$A$9:$R$141,17,0) -> 107043.72 | AS87: =+AP87+AQ87-AR87 -> 709181.54 | AT87: =+AS87-AN87 -> 78257.32 | AU87: =VLOOKUP(A87,'Profit Loss-Amravati-25-26'!$A$9:$T$192,19,0) -> 675450.3 | AV87: =VLOOKUP(A87,'Profit Loss-Betul-25-26'!$A$9:$T$141,19,0) -> 114384.12 | AX87: =+AU87+AV87-AW87 -> 789834.42 | AY87: =+AX87-AS87 -> 80652.88 | AZ87: =VLOOKUP(A87,'Profit Loss-Amravati-25-26'!$A$9:$V$192,21,0) -> 716961.3 | BA87: =VLOOKUP(A87,'Profit Loss-Betul-25-26'!$A$9:$V$141,21,0) -> 556145.76 | BC87: =+AZ87+BA87-BB87 -> 1273107.1 | BD87: =+BC87-AX87 -> 483272.64
A88: ADVERTISEMENT EXPENSE | K88: =+H88+G88-F88 -> 0 | L88: =VLOOKUP(A88,'Profit Loss-Amravati-25-26'!$A$9:$F$190,5,0) -> 1145 | O88: =SUM(L88:M88) -> 1145 | P88: =+O88-J88 -> 1145 | Q88: =VLOOKUP(A88,'Profit Loss-Amravati-25-26'!$A$9:$H$190,7,0) -> 1145 | T88: =SUM(Q88:S88) -> 1145 | U88: =+T88-O88 -> 0 | V88: =VLOOKUP(A88,'Profit Loss-Amravati-25-26'!$A$9:$J$190,9,0) -> 1145 | Y88: =SUM(V88:X88) -> 1145 | Z88: =+Y88-T88 -> 0 | AA88: =VLOOKUP(A88,'Profit Loss-Amravati-25-26'!$A$9:$L$192,11,0) -> 1145 | AD88: =+AA88+AB88 -> 1145 | AE88: =+AD88-Y88 -> 0 | AF88: =VLOOKUP(A88,'Profit Loss-Amravati-25-26'!$A$9:$N$192,13,0) -> 2290 | AI88: =+AF88+AG88-AH88 -> 2290 | AJ88: =+AI88-AD88 -> 1145 | AK88: =VLOOKUP(A88,'Profit Loss-Amravati-25-26'!$A$9:$P$192,15,0) -> 2290 | AN88: =+AK88+AL88-AM88 -> 2290 | AO88: =+AN88-AI88 -> 0 | AP88: =VLOOKUP(A88,'Profit Loss-Amravati-25-26'!$A$9:$R$192,17,0) -> 2290 | AS88: =+AP88+AQ88-AR88 -> 2290 | AT88: =+AS88-AN88 -> 0 | AU88: =VLOOKUP(A88,'Profit Loss-Amravati-25-26'!$A$9:$T$192,19,0) -> 2290 | AX88: =+AU88+AV88-AW88 -> 2290 | AY88: =+AX88-AS88 -> 0 | AZ88: =VLOOKUP(A88,'Profit Loss-Amravati-25-26'!$A$9:$V$192,21,0) -> 2290 | BC88: =+AZ88+BA88-BB88 -> 2290 | BD88: =+BC88-AX88 -> 0
A89: LABOUR CHARGES | C89: =VLOOKUP(A89,'Profit Loss-Amravati-25-26'!$A$13:$B$190,2,0) -> 149230.46 | D89: =VLOOKUP(A89,'Profit Loss-Betul-25-26'!$A$9:$B$140,2,0) -> 0 | F89: =+B89+C89+D89 -> 149230.46 | G89: =VLOOKUP(A89,'Profit Loss-Amravati-25-26'!$A$9:$D$190,3,0) -> 177400.46 | H89: =VLOOKUP(A89,'Profit Loss-Betul-25-26'!$A$9:$D$140,3,0) -> 0 | J89: =SUM(G89:I89) -> 177400.46 | K89: =+H89+G89-F89 -> 28170 | L89: =VLOOKUP(A89,'Profit Loss-Amravati-25-26'!$A$9:$F$190,5,0) -> 554755.46 | M89: =VLOOKUP(A89,'Profit Loss-Betul-25-26'!$A$9:$F$141,5,0) -> 0 | O89: =SUM(L89:M89) -> 554755.46 | P89: =+O89-J89 -> 377355 | Q89: =VLOOKUP(A89,'Profit Loss-Amravati-25-26'!$A$9:$H$190,7,0) -> 698450.46 | R89: =VLOOKUP(A89,'Profit Loss-Betul-25-26'!$A$9:$H$141,7,0) -> 0 | T89: =SUM(Q89:S89) -> 698450.46 | U89: =+T89-O89 -> 143695 | V89: =VLOOKUP(A89,'Profit Loss-Amravati-25-26'!$A$9:$J$190,9,0) -> 698750.46 | W89: =VLOOKUP(A89,'Profit Loss-Betul-25-26'!$A$9:$J$141,9,0) -> 0 | Y89: =SUM(V89:X89) -> 698750.46 | Z89: =+Y89-T89 -> 300 | AA89: =VLOOKUP(A89,'Profit Loss-Amravati-25-26'!$A$9:$L$192,11,0) -> 709950.46 | AB89: =VLOOKUP(A89,'Profit Loss-Betul-25-26'!$A$9:$L$141,11,0) -> 0 | AD89: =+AA89+AB89 -> 709950.46 | AE89: =+AD89-Y89 -> 11200 | AF89: =VLOOKUP(A89,'Profit Loss-Amravati-25-26'!$A$9:$N$192,13,0) -> 709950.46 | AG89: =VLOOKUP(A89,'Profit Loss-Betul-25-26'!$A$9:$N$141,13,0) -> 0 | AI89: =+AF89+AG89-AH89 -> 709950.46 | AJ89: =+AI89-AD89 -> 0 | AK89: =VLOOKUP(A89,'Profit Loss-Amravati-25-26'!$A$9:$P$192,15,0) -> 709950.46 | AL89: =VLOOKUP(A89,'Profit Loss-Betul-25-26'!$A$9:$P$141,15,0) -> 0 | AN89: =+AK89+AL89-AM89 -> 709950.46 | AO89: =+AN89-AI89 -> 0 | AP89: =VLOOKUP(A89,'Profit Loss-Amravati-25-26'!$A$9:$R$192,17,0) -> 709950.46 | AQ89: =VLOOKUP(A89,'Profit Loss-Betul-25-26'!$A$9:$R$141,17,0) -> 0 | AS89: =+AP89+AQ89-AR89 -> 709950.46 | AT89: =+AS89-AN89 -> 0 | AU89: =VLOOKUP(A89,'Profit Loss-Amravati-25-26'!$A$9:$T$192,19,0) -> 709950.46 | AV89: =VLOOKUP(A89,'Profit Loss-Betul-25-26'!$A$9:$T$141,19,0) -> 0 | AX89: =+AU89+AV89-AW89 -> 709950.46 | AY89: =+AX89-AS89 -> 0 | AZ89: =VLOOKUP(A89,'Profit Loss-Amravati-25-26'!$A$9:$V$192,21,0) -> 730200.46 | BA89: =VLOOKUP(A89,'Profit Loss-Betul-25-26'!$A$9:$V$141,21,0) -> 0 | BC89: =+AZ89+BA89-BB89 -> 730200.46 | BD89: =+BC89-AX89 -> 20250
A90: FUEL & OIL | C90: =VLOOKUP(A90,'Profit Loss-Amravati-25-26'!$A$13:$B$190,2,0) -> 0 | D90: =VLOOKUP(A90,'Profit Loss-Betul-25-26'!$A$9:$B$140,2,0) -> 0 | F90: =+B90+C90+D90 -> 0 | G90: =VLOOKUP(A90,'Profit Loss-Amravati-25-26'!$A$9:$D$190,3,0) -> 0 | H90: =VLOOKUP(A90,'Profit Loss-Betul-25-26'!$A$9:$D$140,3,0) -> 6700 | J90: =SUM(G90:I90) -> 6700 | K90: =+H90+G90-F90 -> 6700 | L90: =VLOOKUP(A90,'Profit Loss-Amravati-25-26'!$A$9:$F$190,5,0) -> 0 | M90: =VLOOKUP(A90,'Profit Loss-Betul-25-26'!$A$9:$F$141,5,0) -> 6700 | O90: =SUM(L90:M90) -> 6700 | P90: =+O90-J90 -> 0 | Q90: =VLOOKUP(A90,'Profit Loss-Amravati-25-26'!$A$9:$H$190,7,0) -> 0 | R90: =VLOOKUP(A90,'Profit Loss-Betul-25-26'!$A$9:$H$141,7,0) -> 6700 | T90: =SUM(Q90:S90) -> 6700 | U90: =+T90-O90 -> 0 | V90: =VLOOKUP(A90,'Profit Loss-Amravati-25-26'!$A$9:$J$190,9,0) -> 0 | W90: =VLOOKUP(A90,'Profit Loss-Betul-25-26'!$A$9:$J$141,9,0) -> 6700 | Y90: =SUM(V90:X90) -> 6700 | Z90: =+Y90-T90 -> 0 | AA90: =VLOOKUP(A90,'Profit Loss-Amravati-25-26'!$A$9:$L$192,11,0) -> 5075 | AB90: =VLOOKUP(A90,'Profit Loss-Betul-25-26'!$A$9:$L$141,11,0) -> 6700 | AD90: =+AA90+AB90 -> 11775 | AE90: =+AD90-Y90 -> 5075 | AF90: =VLOOKUP(A90,'Profit Loss-Amravati-25-26'!$A$9:$N$192,13,0) -> 5075 | AG90: =VLOOKUP(A90,'Profit Loss-Betul-25-26'!$A$9:$N$141,13,0) -> 6700 | AI90: =+AF90+AG90-AH90 -> 11775 | AJ90: =+AI90-AD90 -> 0 | AK90: =VLOOKUP(A90,'Profit Loss-Amravati-25-26'!$A$9:$P$192,15,0) -> 8757.24 | AL90: =VLOOKUP(A90,'Profit Loss-Betul-25-26'!$A$9:$P$141,15,0) -> 6700 | AN90: =+AK90+AL90-AM90 -> 15457.24 | AO90: =+AN90-AI90 -> 3682.24 | AP90: =VLOOKUP(A90,'Profit Loss-Amravati-25-26'!$A$9:$R$192,17,0) -> 8757.24 | AQ90: =VLOOKUP(A90,'Profit Loss-Betul-25-26'!$A$9:$R$141,17,0) -> 8370 | AS90: =+AP90+AQ90-AR90 -> 17127.24 | AT90: =+AS90-AN90 -> 1670 | AU90: =VLOOKUP(A90,'Profit Loss-Amravati-25-26'!$A$9:$T$192,19,0) -> 8757.24 | AV90: =VLOOKUP(A90,'Profit Loss-Betul-25-26'!$A$9:$T$141,19,0) -> 8370 | AX90: =+AU90+AV90-AW90 -> 17127.24 | AY90: =+AX90-AS90 -> 0 | AZ90: =VLOOKUP(A90,'Profit Loss-Amravati-25-26'!$A$9:$V$192,21,0) -> 8757.24 | BA90: =VLOOKUP(A90,'Profit Loss-Betul-25-26'!$A$9:$V$141,21,0) -> 13450 | BC90: =+AZ90+BA90-BB90 -> 22207.24 | BD90: =+BC90-AX90 -> 5080
A91: PURCHASE STORES & SPARES - IMPORT | F91: =+B91+C91+D91 -> 0 | J91: =SUM(G91:I91) -> 0 | K91: =+H91+G91-F91 -> 0 | O91: =SUM(L91:M91) -> 0 | P91: =+O91-J91 -> 0 | T91: =SUM(Q91:S91) -> 0 | U91: =+T91-O91 -> 0 | Y91: =SUM(V91:X91) -> 0 | Z91: =+Y91-T91 -> 0 | AD91: =+AA91+AB91 -> 0 | AE91: =+AD91-Y91 -> 0 | AI91: =+AF91+AG91-AH91 -> 0 | AJ91: =+AI91-AD91 -> 0 | AN91: =+AK91+AL91-AM91 -> 0 | AO91: =+AN91-AI91 -> 0 | AS91: =+AP91+AQ91-AR91 -> 0 | AT91: =+AS91-AN91 -> 0 | AX91: =+AU91+AV91-AW91 -> 0 | AY91: =+AX91-AS91 -> 0 | BC91: =+AZ91+BA91-BB91 -> 0 | BD91: =+BC91-AX91 -> 0
A92: PURCHASE STORES & SPARES (GARMENT) | C92: =VLOOKUP(A92,'Profit Loss-Amravati-25-26'!$A$13:$B$190,2,0) -> 661568.86 | D92: =VLOOKUP(A92,'Profit Loss-Betul-25-26'!$A$9:$B$140,2,0) -> 73178.92 | F92: =+B92+C92+D92 -> 734747.78 | G92: =VLOOKUP(A92,'Profit Loss-Amravati-25-26'!$A$9:$D$190,3,0) -> 1376215 | H92: =VLOOKUP(A92,'Profit Loss-Betul-25-26'!$A$9:$D$140,3,0) -> 170665.58 | J92: =SUM(G92:I92) -> 1546880.6 | K92: =+H92+G92-F92 -> 812132.8 | L92: =VLOOKUP(A92,'Profit Loss-Amravati-25-26'!$A$9:$F$190,5,0) -> 2001182.2 | M92: =VLOOKUP(A92,'Profit Loss-Betul-25-26'!$A$9:$F$141,5,0) -> 259554 | O92: =SUM(L92:M92) -> 2260736.2 | P92: =+O92-J92 -> 713855.58 | Q92: =VLOOKUP(A92,'Profit Loss-Amravati-25-26'!$A$9:$H$190,7,0) -> 2347243.4 | R92: =VLOOKUP(A92,'Profit Loss-Betul-25-26'!$A$9:$H$141,7,0) -> 400539.68 | T92: =SUM(Q92:S92) -> 2747783.1 | U92: =+T92-O92 -> 487046.9 | V92: =VLOOKUP(A92,'Profit Loss-Amravati-25-26'!$A$9:$J$190,9,0) -> 2703610.7 | W92: =VLOOKUP(A92,'Profit Loss-Betul-25-26'!$A$9:$J$141,9,0) -> 452689.68 | Y92: =SUM(V92:X92) -> 3156300.4 | Z92: =+Y92-T92 -> 408517.32 | AA92: =VLOOKUP(A92,'Profit Loss-Amravati-25-26'!$A$9:$L$192,11,0) -> 3051851.1 | AB92: =VLOOKUP(A92,'Profit Loss-Betul-25-26'!$A$9:$L$141,11,0) -> 478682.28 | AD92: =+AA92+AB92 -> 3530533.4 | AE92: =+AD92-Y92 -> 374233.04 | AF92: =VLOOKUP(A92,'Profit Loss-Amravati-25-26'!$A$9:$N$192,13,0) -> 3094182.7 | AG92: =VLOOKUP(A92,'Profit Loss-Betul-25-26'!$A$9:$N$141,13,0) -> 509340.28 | AI92: =+AF92+AG92-AH92 -> 3603523 | AJ92: =+AI92-AD92 -> 72989.54 | AK92: =VLOOKUP(A92,'Profit Loss-Amravati-25-26'!$A$9:$P$192,15,0) -> 3354516.6 | AL92: =VLOOKUP(A92,'Profit Loss-Betul-25-26'!$A$9:$P$141,15,0) -> 631653.67 | AN92: =+AK92+AL92-AM92 -> 3986170.2 | AO92: =+AN92-AI92 -> 382647.28 | AP92: =VLOOKUP(A92,'Profit Loss-Amravati-25-26'!$A$9:$R$192,17,0) -> 3569621.2 | AQ92: =VLOOKUP(A92,'Profit Loss-Betul-25-26'!$A$9:$R$141,17,0) -> 882569.46 | AS92: =+AP92+AQ92-AR92 -> 4452190.7 | AT92: =+AS92-AN92 -> 466020.41 | AU92: =VLOOKUP(A92,'Profit Loss-Amravati-25-26'!$A$9:$T$192,19,0) -> 3988477.6 | AV92: =VLOOKUP(A92,'Profit Loss-Betul-25-26'!$A$9:$T$141,19,0) -> 923959.56 | AX92: =+AU92+AV92-AW92 -> 4912437.1 | AY92: =+AX92-AS92 -> 460246.48 | AZ92: =VLOOKUP(A92,'Profit Loss-Amravati-25-26'!$A$9:$V$192,21,0) -> 4127708.8 | BA92: =VLOOKUP(A92,'Profit Loss-Betul-25-26'!$A$9:$V$141,21,0) -> 1103395.1 | BC92: =+AZ92+BA92-BB92 -> 5231103.8 | BD92: =+BC92-AX92 -> 318666.67
A93: FILING FEES | B93: =VLOOKUP(A93,'Profit Loss-Textile'!$A$8:$B$135,2,0) -> 0 | C93: =VLOOKUP(A93,'Profit Loss-Amravati-25-26'!$A$13:$B$190,2,0) -> 608.26 | D93: =VLOOKUP(A93,'Profit Loss-Betul-25-26'!$A$9:$B$140,2,0) -> 0 | F93: =+B93+C93+D93 -> 608.26 | G93: =VLOOKUP(A93,'Profit Loss-Amravati-25-26'!$A$9:$D$190,3,0) -> 608.26 | H93: =VLOOKUP(A93,'Profit Loss-Betul-25-26'!$A$9:$D$140,3,0) -> 0 | J93: =SUM(G93:I93) -> 608.26 | K93: =+H93+G93-F93 -> 0 | L93: =VLOOKUP(A93,'Profit Loss-Amravati-25-26'!$A$9:$F$190,5,0) -> 1824.78 | M93: =VLOOKUP(A93,'Profit Loss-Betul-25-26'!$A$9:$F$141,5,0) -> 0 | O93: =SUM(L93:M93) -> 1824.78 | P93: =+O93-J93 -> 1216.52 | Q93: =VLOOKUP(A93,'Profit Loss-Amravati-25-26'!$A$9:$H$190,7,0) -> 1824.78 | R93: =VLOOKUP(A93,'Profit Loss-Betul-25-26'!$A$9:$H$141,7,0) -> 0 | T93: =SUM(Q93:S93) -> 1824.78 | U93: =+T93-O93 -> 0 | V93: =VLOOKUP(A93,'Profit Loss-Amravati-25-26'!$A$9:$J$190,9,0) -> 1824.78 | W93: =VLOOKUP(A93,'Profit Loss-Betul-25-26'!$A$9:$J$141,9,0) -> 0 | Y93: =SUM(V93:X93) -> 1824.78 | Z93: =+Y93-T93 -> 0 | AA93: =VLOOKUP(A93,'Profit Loss-Amravati-25-26'!$A$9:$L$192,11,0) -> 1824.78 | AB93: =VLOOKUP(A93,'Profit Loss-Betul-25-26'!$A$9:$L$141,11,0) -> 0 | AD93: =+AA93+AB93 -> 1824.78 | AE93: =+AD93-Y93 -> 0 | AF93: =VLOOKUP(A93,'Profit Loss-Amravati-25-26'!$A$9:$N$192,13,0) -> 1824.78 | AG93: =VLOOKUP(A93,'Profit Loss-Betul-25-26'!$A$9:$N$141,13,0) -> 0 | AI93: =+AF93+AG93-AH93 -> 1824.78 | AJ93: =+AI93-AD93 -> 0 | AK93: =VLOOKUP(A93,'Profit Loss-Amravati-25-26'!$A$9:$P$192,15,0) -> 1824.78 | AL93: =VLOOKUP(A93,'Profit Loss-Betul-25-26'!$A$9:$P$141,15,0) -> 0 | AN93: =+AK93+AL93-AM93 -> 1824.78 | AO93: =+AN93-AI93 -> 0 | AP93: =VLOOKUP(A93,'Profit Loss-Amravati-25-26'!$A$9:$R$192,17,0) -> 3041.3 | AQ93: =VLOOKUP(A93,'Profit Loss-Betul-25-26'!$A$9:$R$141,17,0) -> 0 | AS93: =+AP93+AQ93-AR93 -> 3041.3 | AT93: =+AS93-AN93 -> 1216.52 | AU93: =VLOOKUP(A93,'Profit Loss-Amravati-25-26'!$A$9:$T$192,19,0) -> 3041.3 | AV93: =VLOOKUP(A93,'Profit Loss-Betul-25-26'!$A$9:$T$141,19,0) -> 0 | AX93: =+AU93+AV93-AW93 -> 3041.3 | AY93: =+AX93-AS93 -> 0 | AZ93: =VLOOKUP(A93,'Profit Loss-Amravati-25-26'!$A$9:$V$192,21,0) -> 3041.3 | BA93: =VLOOKUP(A93,'Profit Loss-Betul-25-26'!$A$9:$V$141,21,0) -> 0 | BC93: =+AZ93+BA93-BB93 -> 3041.3 | BD93: =+BC93-AX93 -> 0
A94: CONVEYANCE ALLOWANCE | B94: =VLOOKUP(A94,'Profit Loss-Textile'!$A$8:$B$135,2,0) -> 0 | AF94: =VLOOKUP(A94,'Profit Loss-Amravati-25-26'!$A$9:$N$192,13,0) -> 5630073 | AG94: =VLOOKUP(A94,'Profit Loss-Betul-25-26'!$A$9:$N$141,13,0) -> 233987 | AJ94: =+AI94-AD94 -> 0 | AK94: =VLOOKUP(A94,'Profit Loss-Amravati-25-26'!$A$9:$P$192,15,0) -> 6301018 | AL94: =VLOOKUP(A94,'Profit Loss-Betul-25-26'!$A$9:$P$141,15,0) -> 271419 | AO94: =+AN94-AI94 -> 0 | AP94: =VLOOKUP(A94,'Profit Loss-Amravati-25-26'!$A$9:$R$192,17,0) -> 6988729 | AQ94: =VLOOKUP(A94,'Profit Loss-Betul-25-26'!$A$9:$R$141,17,0) -> 536273 | AT94: =+AS94-AN94 -> 0 | AU94: =VLOOKUP(A94,'Profit Loss-Amravati-25-26'!$A$9:$T$192,19,0) -> 7689760 | AV94: =VLOOKUP(A94,'Profit Loss-Betul-25-26'!$A$9:$T$141,19,0) -> 580903 | AY94: =+AX94-AS94 -> 0 | AZ94: =VLOOKUP(A94,'Profit Loss-Amravati-25-26'!$A$9:$V$192,21,0) -> 8326027 | BA94: =VLOOKUP(A94,'Profit Loss-Betul-25-26'!$A$9:$V$141,21,0) -> 627503 | BD94: =+BC94-AX94 -> 0
A95: EDUCATION ALLOWANCE | B95: =VLOOKUP(A95,'Profit Loss-Textile'!$A$8:$B$135,2,0) -> 0 | AF95: =VLOOKUP(A95,'Profit Loss-Amravati-25-26'!$A$9:$N$192,13,0) -> 2222889 | AG95: =VLOOKUP(A95,'Profit Loss-Betul-25-26'!$A$9:$N$141,13,0) -> 245159 | AJ95: =+AI95-AD95 -> 0 | AK95: =VLOOKUP(A95,'Profit Loss-Amravati-25-26'!$A$9:$P$192,15,0) -> 2561975 | AL95: =VLOOKUP(A95,'Profit Loss-Betul-25-26'!$A$9:$P$141,15,0) -> 288410 | AO95: =+AN95-AI95 -> 0 | AP95: =VLOOKUP(A95,'Profit Loss-Amravati-25-26'!$A$9:$R$192,17,0) -> 2887079 | AQ95: =VLOOKUP(A95,'Profit Loss-Betul-25-26'!$A$9:$R$141,17,0) -> 337461 | AT95: =+AS95-AN95 -> 0 | AU95: =VLOOKUP(A95,'Profit Loss-Amravati-25-26'!$A$9:$T$192,19,0) -> 3214630 | AV95: =VLOOKUP(A95,'Profit Loss-Betul-25-26'!$A$9:$T$141,19,0) -> 386512 | AY95: =+AX95-AS95 -> 0 | AZ95: =VLOOKUP(A95,'Profit Loss-Amravati-25-26'!$A$9:$V$192,21,0) -> 3528747 | BA95: =VLOOKUP(A95,'Profit Loss-Betul-25-26'!$A$9:$V$141,21,0) -> 431710 | BD95: =+BC95-AX95 -> 0
A96: HOUSE RENT ALLOWANCE | B96: =VLOOKUP(A96,'Profit Loss-Textile'!$A$8:$B$135,2,0) -> 0 | AF96: =VLOOKUP(A96,'Profit Loss-Amravati-25-26'!$A$9:$N$192,13,0) -> 7166581 | AG96: =VLOOKUP(A96,'Profit Loss-Betul-25-26'!$A$9:$N$141,13,0) -> 348638 | AJ96: =+AI96-AD96 -> 0 | AK96: =VLOOKUP(A96,'Profit Loss-Amravati-25-26'!$A$9:$P$192,15,0) -> 8075385 | AL96: =VLOOKUP(A96,'Profit Loss-Betul-25-26'!$A$9:$P$141,15,0) -> 404004 | AO96: =+AN96-AI96 -> 0 | AP96: =VLOOKUP(A96,'Profit Loss-Amravati-25-26'!$A$9:$R$192,17,0) -> 9010122 | AQ96: =VLOOKUP(A96,'Profit Loss-Betul-25-26'!$A$9:$R$141,17,0) -> 473767 | AT96: =+AS96-AN96 -> 0 | AU96: =VLOOKUP(A96,'Profit Loss-Amravati-25-26'!$A$9:$T$192,19,0) -> 9964785 | AV96: =VLOOKUP(A96,'Profit Loss-Betul-25-26'!$A$9:$T$141,19,0) -> 543530 | AY96: =+AX96-AS96 -> 0 | AZ96: =VLOOKUP(A96,'Profit Loss-Amravati-25-26'!$A$9:$V$192,21,0) -> 11084831 | BA96: =VLOOKUP(A96,'Profit Loss-Betul-25-26'!$A$9:$V$141,21,0) -> 617231 | BD96: =+BC96-AX96 -> 0
A97: SPECIAL ALLOWANCE | B97: =VLOOKUP(A97,'Profit Loss-Textile'!$A$8:$B$135,2,0) -> 0 | AF97: =VLOOKUP(A97,'Profit Loss-Amravati-25-26'!$A$9:$N$192,13,0) -> 1403969 | AG97: =VLOOKUP(A97,'Profit Loss-Betul-25-26'!$A$9:$N$141,13,0) -> 0 | AJ97: =+AI97-AD97 -> 0 | AK97: =VLOOKUP(A97,'Profit Loss-Amravati-25-26'!$A$9:$P$192,15,0) -> 1586251 | AL97: =VLOOKUP(A97,'Profit Loss-Betul-25-26'!$A$9:$P$141,15,0) -> 0 | AO97: =+AN97-AI97 -> 0 | AP97: =VLOOKUP(A97,'Profit Loss-Amravati-25-26'!$A$9:$R$192,17,0) -> 1765214 | AQ97: =VLOOKUP(A97,'Profit Loss-Betul-25-26'!$A$9:$R$141,17,0) -> 1088 | AT97: =+AS97-AN97 -> 0 | AU97: =VLOOKUP(A97,'Profit Loss-Amravati-25-26'!$A$9:$T$192,19,0) -> 1949475 | AV97: =VLOOKUP(A97,'Profit Loss-Betul-25-26'!$A$9:$T$141,19,0) -> 18176 | AY97: =+AX97-AS97 -> 0 | AZ97: =VLOOKUP(A97,'Profit Loss-Amravati-25-26'!$A$9:$V$192,21,0) -> 2204405 | BA97: =VLOOKUP(A97,'Profit Loss-Betul-25-26'!$A$9:$V$141,21,0) -> 27264 | BD97: =+BC97-AX97 -> 0
A98: NEWSPAPER & PERIODICAL ALLOWANCE | B98: =VLOOKUP(A98,'Profit Loss-Textile'!$A$8:$B$135,2,0) -> 0 | AF98: =VLOOKUP(A98,'Profit Loss-Amravati-25-26'!$A$9:$N$192,13,0) -> 656263 | AG98: =VLOOKUP(A98,'Profit Loss-Betul-25-26'!$A$9:$N$141,13,0) -> 71861 | AJ98: =+AI98-AD98 -> 0 | AK98: =VLOOKUP(A98,'Profit Loss-Amravati-25-26'!$A$9:$P$192,15,0) -> 759125 | AL98: =VLOOKUP(A98,'Profit Loss-Betul-25-26'!$A$9:$P$141,15,0) -> 82010 | AO98: =+AN98-AI98 -> 0 | AP98: =VLOOKUP(A98,'Profit Loss-Amravati-25-26'!$A$9:$R$192,17,0) -> 861491 | AQ98: =VLOOKUP(A98,'Profit Loss-Betul-25-26'!$A$9:$R$141,17,0) -> 94625 | AT98: =+AS98-AN98 -> 0 | AU98: =VLOOKUP(A98,'Profit Loss-Amravati-25-26'!$A$9:$T$192,19,0) -> 963444 | AV98: =VLOOKUP(A98,'Profit Loss-Betul-25-26'!$A$9:$T$141,19,0) -> 107240 | AY98: =+AX98-AS98 -> 0 | AZ98: =VLOOKUP(A98,'Profit Loss-Amravati-25-26'!$A$9:$V$192,21,0) -> 1070523 | BA98: =VLOOKUP(A98,'Profit Loss-Betul-25-26'!$A$9:$V$141,21,0) -> 115884 | BD98: =+BC98-AX98 -> 0
A99: SALARY & WAGES | B99: =VLOOKUP(A99,'Profit Loss-Textile'!$A$8:$B$135,2,0) -> 0 | AJ99: =+AI99-AD99 -> 0 | AK99: =VLOOKUP(A99,'Profit Loss-Amravati-25-26'!$A$9:$P$192,15,0) -> 71861389 | AL99: =VLOOKUP(A99,'Profit Loss-Betul-25-26'!$A$9:$P$141,15,0) -> 3967232 | AO99: =+AN99-AI99 -> 0 | AP99: =VLOOKUP(A99,'Profit Loss-Amravati-25-26'!$A$9:$R$192,17,0) -> 83359776 | AQ99: =VLOOKUP(A99,'Profit Loss-Betul-25-26'!$A$9:$R$141,17,0) -> 4962944 | AT99: =+AS99-AN99 -> 0 | AU99: =VLOOKUP(A99,'Profit Loss-Amravati-25-26'!$A$9:$T$192,19,0) -> 94597284 | AV99: =VLOOKUP(A99,'Profit Loss-Betul-25-26'!$A$9:$T$141,19,0) -> 5957223 | AY99: =+AX99-AS99 -> 0 | AZ99: =VLOOKUP(A99,'Profit Loss-Amravati-25-26'!$A$9:$V$192,21,0) -> 106492400 | BA99: =VLOOKUP(A99,'Profit Loss-Betul-25-26'!$A$9:$V$141,21,0) -> 7272326 | BD99: =+BC99-AX99 -> 0
A100: SALARY & WAGES (OVER TIME) | AF100: =VLOOKUP(A100,'Profit Loss-Amravati-25-26'!$A$9:$N$192,13,0) -> 312704 | AG100: =VLOOKUP(A100,'Profit Loss-Betul-25-26'!$A$9:$N$141,13,0) -> 0 | AJ100: =+AI100-AD100 -> 0 | AK100: =VLOOKUP(A100,'Profit Loss-Amravati-25-26'!$A$9:$P$192,15,0) -> 312704 | AL100: =VLOOKUP(A100,'Profit Loss-Betul-25-26'!$A$9:$P$141,15,0) -> 0 | AO100: =+AN100-AI100 -> 0 | AP100: =VLOOKUP(A100,'Profit Loss-Amravati-25-26'!$A$9:$R$192,17,0) -> 312704 | AQ100: =VLOOKUP(A100,'Profit Loss-Betul-25-26'!$A$9:$R$141,17,0) -> 0 | AT100: =+AS100-AN100 -> 0 | AU100: =VLOOKUP(A100,'Profit Loss-Amravati-25-26'!$A$9:$T$192,19,0) -> 312704 | AV100: =VLOOKUP(A100,'Profit Loss-Betul-25-26'!$A$9:$T$141,19,0) -> 0 | AY100: =+AX100-AS100 -> 0 | AZ100: =VLOOKUP(A100,'Profit Loss-Amravati-25-26'!$A$9:$V$192,21,0) -> 312704 | BA100: =VLOOKUP(A100,'Profit Loss-Betul-25-26'!$A$9:$V$141,21,0) -> 0 | BD100: =+BC100-AX100 -> 0
A101: ATTENDENCE BONUS | AF101: =VLOOKUP(A101,'Profit Loss-Amravati-25-26'!$A$9:$N$192,13,0) -> 475414 | AG101: =VLOOKUP(A101,'Profit Loss-Betul-25-26'!$A$9:$N$141,13,0) -> 0 | AJ101: =+AI101-AD101 -> 0 | AK101: =VLOOKUP(A101,'Profit Loss-Amravati-25-26'!$A$9:$P$192,15,0) -> 475626 | AL101: =VLOOKUP(A101,'Profit Loss-Betul-25-26'!$A$9:$P$141,15,0) -> 0 | AO101: =+AN101-AI101 -> 0 | AP101: =VLOOKUP(A101,'Profit Loss-Amravati-25-26'!$A$9:$R$192,17,0) -> 475626 | AQ101: =VLOOKUP(A101,'Profit Loss-Betul-25-26'!$A$9:$R$141,17,0) -> 0 | AT101: =+AS101-AN101 -> 0 | AU101: =VLOOKUP(A101,'Profit Loss-Amravati-25-26'!$A$9:$T$192,19,0) -> 475626 | AV101: =VLOOKUP(A101,'Profit Loss-Betul-25-26'!$A$9:$T$141,19,0) -> 0 | AY101: =+AX101-AS101 -> 0 | AZ101: =VLOOKUP(A101,'Profit Loss-Amravati-25-26'!$A$9:$V$192,21,0) -> 475626 | BA101: =VLOOKUP(A101,'Profit Loss-Betul-25-26'!$A$9:$V$141,21,0) -> 0 | BD101: =+BC101-AX101 -> 0
A102: CONSULTANCY CHARGES | AF102: =VLOOKUP(A102,'Profit Loss-Amravati-25-26'!$A$9:$N$192,13,0) -> 3013914 | AG102: =VLOOKUP(A102,'Profit Loss-Betul-25-26'!$A$9:$N$141,13,0) -> 0 | AJ102: =+AI102-AD102 -> 0 | AK102: =VLOOKUP(A102,'Profit Loss-Amravati-25-26'!$A$9:$P$192,15,0) -> 3667981.5 | AL102: =VLOOKUP(A102,'Profit Loss-Betul-25-26'!$A$9:$P$141,15,0) -> 0 | AO102: =+AN102-AI102 -> 0 | AP102: =VLOOKUP(A102,'Profit Loss-Amravati-25-26'!$A$9:$R$192,17,0) -> 4092603.1 | AQ102: =VLOOKUP(A102,'Profit Loss-Betul-25-26'!$A$9:$R$141,17,0) -> 0 | AT102: =+AS102-AN102 -> 0 | AU102: =VLOOKUP(A102,'Profit Loss-Amravati-25-26'!$A$9:$T$192,19,0) -> 4501551.5 | AV102: =VLOOKUP(A102,'Profit Loss-Betul-25-26'!$A$9:$T$141,19,0) -> 84000 | AY102: =+AX102-AS102 -> 0 | AZ102: =VLOOKUP(A102,'Profit Loss-Amravati-25-26'!$A$9:$V$192,21,0) -> 5160162.8 | BA102: =VLOOKUP(A102,'Profit Loss-Betul-25-26'!$A$9:$V$141,21,0) -> 84000 | BD102: =+BC102-AX102 -> 0
A103: SHIFT ALLOWANCE | AF103: =VLOOKUP(A103,'Profit Loss-Amravati-25-26'!$A$9:$N$192,13,0) -> 1484 | AG103: =VLOOKUP(A103,'Profit Loss-Betul-25-26'!$A$9:$N$141,13,0) -> 0 | AJ103: =+AI103-AD103 -> 0 | AK103: =VLOOKUP(A103,'Profit Loss-Amravati-25-26'!$A$9:$P$192,15,0) -> 1696 | AL103: =VLOOKUP(A103,'Profit Loss-Betul-25-26'!$A$9:$P$141,15,0) -> 0 | AO103: =+AN103-AI103 -> 0 | AP103: =VLOOKUP(A103,'Profit Loss-Amravati-25-26'!$A$9:$R$192,17,0) -> 1696 | AQ103: =VLOOKUP(A103,'Profit Loss-Betul-25-26'!$A$9:$R$141,17,0) -> 0 | AT103: =+AS103-AN103 -> 0 | AU103: =VLOOKUP(A103,'Profit Loss-Amravati-25-26'!$A$9:$T$192,19,0) -> 1696 | AV103: =VLOOKUP(A103,'Profit Loss-Betul-25-26'!$A$9:$T$141,19,0) -> 0 | AY103: =+AX103-AS103 -> 0 | AZ103: =VLOOKUP(A103,'Profit Loss-Amravati-25-26'!$A$9:$V$192,21,0) -> 1696 | BA103: =VLOOKUP(A103,'Profit Loss-Betul-25-26'!$A$9:$V$141,21,0) -> 0 | BD103: =+BC103-AX103 -> 0
...

Sheet Prepaid
C2: Total | D2: April,25 | E2: May,25 | F2: June,25 | G2: July,25
B3: SOFTWARE RENEWAL CHARGES PAID | C3: 3421 | D3: =+C3/12*11 -> 3135.9167 | E3: =+C3/12*10 -> 2850.8333 | F3: =+C3/12*9 -> 2565.75 | G3: =+C3/12*8 -> 2280.6667 | H3: =+C3/12*7 -> 1995.5833 | I3: =+C3/12*6 -> 1710.5 | J3: =+C3/12*5 -> 1425.4167 | K3: =+C3/12*4 -> 1140.3333 | L3: =+C3/12*3 -> 855.25 | M3: =+C3/12*2 -> 570.16667 | N3: =+C3/12*1 -> 285.08333
B4: POLLUTION CONTROL EXPENSES | C4: 25000 | D4: =+C4/12*11 -> 22916.667 | E4: =+C4/12*10 -> 20833.333 | F4: =+C4/12*9 -> 18750 | G4: =+C4/12*8 -> 16666.667 | H4: =+C4/12*7 -> 14583.333 | I4: =+C4/12*6 -> 12500 | J4: =+C4/12*5 -> 10416.667 | K4: =+C4/12*4 -> 8333.3333 | L4: =+C4/12*3 -> 6250 | M4: =+C4/12*2 -> 4166.6667 | N4: =+C4/12*1 -> 2083.3333
B5: REPAIRS & MAINTENANCE | C5: 355019 | D5: =+C5/12*11 -> 325434.08 | E5: =+C5/12*10 -> 295849.17 | F5: =+C5/12*9 -> 266264.25 | G5: =+C5/12*8 -> 236679.33 | H5: =+C5/12*7 -> 207094.42 | I5: =+C5/12*6 -> 177509.5 | J5: =+C5/12*5 -> 147924.58 | K5: =+C5/12*4 -> 118339.67 | L5: =+C5/12*3 -> 88754.75 | M5: =+C5/12*2 -> 59169.833 | N5: =+C5/12*1 -> 29584.917
B6: STAFF/WORKERS INSURANCE | C6: 243974 | D6: =+C6/12*11 -> 223642.83 | E6: =+C6/12*10 -> 203311.67 | F6: =+C6/12*9 -> 182980.5 | G6: =+C6/12*8 -> 162649.33 | H6: =+C6/12*7 -> 142318.17 | I6: =+C6/12*6 -> 121987 | J6: =+C6/12*5 -> 101655.83 | K6: =+C6/12*4 -> 81324.667 | L6: =+C6/12*3 -> 60993.5 | M6: =+C6/12*2 -> 40662.333 | N6: =+C6/12*1 -> 20331.167
B7: FACTORY LICENCE FEES | C7: 78756 | D7: =+C7/12*11 -> 72193 | E7: =+C7/12*10 -> 65630 | F7: =+C7/12*9 -> 59067 | G7: =+C7/12*8 -> 52504 | H7: =+C7/12*7 -> 45941 | I7: =+C7/12*6 -> 39378 | J7: =+C7/12*5 -> 32815 | K7: =+C7/12*4 -> 26252 | L7: =+C7/12*3 -> 19689 | M7: =+C7/12*2 -> 13126 | N7: =+C7/12*1 -> 6563
B8: INSURANCE (GENERAL) | C8: 272842 | D8: =+C8/12*11 -> 250105.17 | E8: =+C8/12*10 -> 227368.33 | F8: =+C8/12*9 -> 204631.5 | G8: =+C8/12*8 -> 181894.67 | H8: =+C8/12*7 -> 159157.83 | I8: =+C8/12*6 -> 136421 | J8: =+C8/12*5 -> 113684.17 | K8: =+C8/12*4 -> 90947.333 | L8: =+C8/12*3 -> 68210.5 | M8: =+C8/12*2 -> 45473.667 | N8: =+C8/12*1 -> 22736.833
B9: BANK GUARANTEE CHARGES | C9: 699 | D9: =+C9/12*11 -> 640.75 | E9: =+C9/12*10 -> 582.5 | F9: =+C9/12*9 -> 524.25 | G9: =+C9/12*8 -> 466 | H9: =+C9/12*7 -> 407.75 | I9: =+C9/12*6 -> 349.5 | J9: =+C9/12*5 -> 291.25 | K9: =+C9/12*4 -> 233 | L9: =+C9/12*3 -> 174.75 | M9: =+C9/12*2 -> 116.5 | N9: =+C9/12*1 -> 58.25
B10: TRAVELLING EXPENSES | C10: 7657 | D10: =+C10/12*11 -> 7018.9167 | E10: =+C10/12*10 -> 6380.8333 | F10: =+C10/12*9 -> 5742.75 | G10: =+C10/12*8 -> 5104.6667 | H10: =+C10/12*7 -> 4466.5833 | I10: =+C10/12*6 -> 3828.5 | J10: =+C10/12*5 -> 3190.4167 | K10: =+C10/12*4 -> 2552.3333 | L10: =+C10/12*3 -> 1914.25 | M10: =+C10/12*2 -> 1276.1667 | N10: =+C10/12*1 -> 638.08333
B11: FOREIGN TRAVELLING | C11: 116590 | D11: =+C11/12*11 -> 106874.17 | E11: =+C11/12*10 -> 97158.333 | F11: =+C11/12*9 -> 87442.5 | G11: =+C11/12*8 -> 77726.667 | H11: =+C11/12*7 -> 68010.833 | I11: =+C11/12*6 -> 58295 | J11: =+C11/12*5 -> 48579.167 | K11: =+C11/12*4 -> 38863.333 | L11: =+C11/12*3 -> 29147.5 | M11: =+C11/12*2 -> 19431.667 | N11: =+C11/12*1 -> 9715.8333
B12: LICENCE & LEGAL FEES | C12: -11432.8 | D12: =+C12/12*11 -> -10480.067 | E12: =+C12/12*10 -> -9527.3333 | F12: =+C12/12*9 -> -8574.6 | G12: =+C12/12*8 -> -7621.8667 | H12: =+C12/12*7 -> -6669.1333 | I12: =+C12/12*6 -> -5716.4 | J12: =+C12/12*5 -> -4763.6667 | K12: =+C12/12*4 -> -3810.9333 | L12: =+C12/12*3 -> -2858.2 | M12: =+C12/12*2 -> -1905.4667 | N12: =+C12/12*1 -> -952.73333
B13: Total | C13: =SUM(C3:C12) -> 1092525.2 | D13: =+C13/12*11 -> 1001481.4 | E13: =SUM(E3:E12) -> 910437.67 | F13: =SUM(F3:F12) -> 819393.9 | G13: =SUM(G3:G12) -> 728350.13 | J13: =SUM(J3:J12) -> 455218.83 | L13: =SUM(L3:L12) -> 273131.3 | N13: =SUM(N3:N12) -> 91043.767

Sheet Profit Loss-Amravati-25-26
A1: TECHNOCRAFT FASHIONS LIMITED-AMRAVATI DIVISION
A3: Profit & Loss for the period ended Feb, 2026
A6: PARTICULARS | B6: April, 25 | C6: Upto May, 25 | D6: For May, 25 | E6: Upto June, 25 | F6: For June, 25 | G6: Upto July, 25 | H6: For July, 25 | I6: Upto August, 25 | J6: For Aug, 25 | K6: Upto Sept, 25 | L6: For Sept, 25 | M6: Upto Oct, 25 | N6: For Oct, 25 | O6: Upto Nov, 25 | P6: For Nov, 25 | Q6: Upto Dec, 25 | R6: For Dec, 25 | S6: Upto Jan, 26 | T6: For Jan, 26 | U6: Upto Feb, 26 | V6: For Feb, 26
A7: INCOME
A8: SALES
A9: SALE EXPORT (GARMENT)) | C9: =VLOOKUP(A9,'May-A'!$B$10:$C$103,2,0) -> 17488529 | D9: =+C9-B9 -> 17488529 | E9: =VLOOKUP(A9,'June,25-A'!$B$10:$C$123,2,0) -> 17488529 | F9: =+E9-C9 -> 0 | G9: =VLOOKUP(A9,'July-A'!$B$10:$C$129,2,0) -> 28044991 | H9: =+G9-E9 -> 10556462 | I9: =VLOOKUP(A9,'TB-A-Aug'!$B$10:$C$132,2,0) -> 38932993 | J9: =+I9-G9 -> 10888002 | K9: =VLOOKUP(A9,'TFA-Sept,25'!$B$9:$C$136,2,0) -> 31936237 | L9: =+K9-I9 -> -6996756 | M9: =VLOOKUP(A9,'PL-TFA-Oct'!$B$9:$C$138,2,0) -> 58108673 | N9: =+M9-K9 -> 26172436 | O9: =VLOOKUP(A9,'TFA-Nov,25'!$B$10:$C$144,2,0) -> 73649850 | P9: =+O9-M9 -> 15541177 | Q9: =VLOOKUP(A9,'TB-TFL-A-Dec,25'!$B$10:$C$147,2,0) -> 84681620 | R9: =+Q9-O9 -> 11031770 | S9: =VLOOKUP(A9,'TB-TFL-A-Jan,26'!$B$9:$C$151,2,0) -> 84702821 | T9: =+S9-Q9 -> 21201 | U9: =VLOOKUP(A9,'TB-Feb,26-a'!$B$10:$C$153,2,0) -> 105750522 | V9: =+U9-S9 -> 21047701
A10: SALE EXPORT FABRIC | O10: =VLOOKUP(A10,'TFA-Nov,25'!$B$10:$C$144,2,0) -> 72061522 | P10: =+O10-M10 -> 72061522 | Q10: =VLOOKUP(A10,'TB-TFL-A-Dec,25'!$B$10:$C$147,2,0) -> 150117512 | R10: =+Q10-O10 -> 78055990 | S10: =VLOOKUP(A10,'TB-TFL-A-Jan,26'!$B$9:$C$151,2,0) -> 150117512 | T10: =+S10-Q10 -> 0 | U10: =VLOOKUP(A10,'TB-Feb,26-a'!$B$10:$C$153,2,0) -> 158852699 | V10: =+U10-S10 -> 8735187
A11: SALE EXPORT - FABRIC- (SAMPLE) | T11: =+S11-Q11 -> 0 | V11: =+U11-S11 -> 0
A12: SAMPLE DEVELOPMENT SERVICES | S12: =VLOOKUP(A12,'TB-TFL-A-Jan,26'!$B$9:$C$151,2,0)+180790 -> 646961 | T12: =+S12-Q12 -> 646961 | U12: =VLOOKUP(A12,'TB-Feb,26-a'!$B$10:$C$153,2,0) -> 646961 | V12: =+U12-S12 -> 0
A13: SALE LOCAL - MISCELLANEOUS ITEMS | B13: =VLOOKUP(A13,'TFL A-April,25'!$B$9:$C$95,2,0) -> 21860 | C13: =VLOOKUP(A13,'May-A'!$B$10:$C$103,2,0) -> 21860 | D13: =+C13-B13 -> 0 | E13: =VLOOKUP(A13,'June,25-A'!$B$10:$C$123,2,0) -> 21860 | F13: =+E13-C13 -> 0 | G13: =VLOOKUP(A13,'July-A'!$B$10:$C$129,2,0) -> 21860 | H13: =+G13-E13 -> 0 | I13: =VLOOKUP(A13,'TB-A-Aug'!$B$10:$C$132,2,0) -> 21860 | J13: =+I13-G13 -> 0 | K13: =VLOOKUP(A13,'TFA-Sept,25'!$B$9:$C$136,2,0) -> 21860 | L13: =+K13-I13 -> 0 | M13: =VLOOKUP(A13,'PL-TFA-Oct'!$B$9:$C$138,2,0) -> 21860 | N13: =+M13-K13 -> 0 | O13: =VLOOKUP(A13,'TFA-Nov,25'!$B$10:$C$144,2,0) -> 21860 | P13: =+O13-M13 -> 0 | Q13: =VLOOKUP(A13,'TB-TFL-A-Dec,25'!$B$10:$C$147,2,0) -> 21860 | R13: =+Q13-O13 -> 0 | S13: =VLOOKUP(A13,'TB-TFL-A-Jan,26'!$B$9:$C$151,2,0) -> 21860 | T13: =+S13-Q13 -> 0 | U13: =VLOOKUP(A13,'TB-Feb,26-a'!$B$10:$C$153,2,0) -> 21860 | V13: =+U13-S13 -> 0
A14: SALE LOCAL (GARMENT) | B14: =VLOOKUP(A14,'TFL A-April,25'!$B$9:$C$95,2,0) -> 47838869 | C14: =VLOOKUP(A14,'May-A'!$B$10:$C$103,2,0)-18103 -> 93255699 | D14: =+C14-B14 -> 45416830 | E14: =VLOOKUP(A14,'June,25-A'!$B$10:$C$123,2,0)-110927 -> 1.4859851e+08 | F14: =+E14-C14 -> 55342806 | G14: =VLOOKUP(A14,'July-A'!$B$10:$C$129,2,0) -> 2.2662015e+08 | H14: =+G14-E14 -> 78021644 | I14: =VLOOKUP(A14,'TB-A-Aug'!$B$10:$C$132,2,0) -> 2.7676371e+08 | J14: =+I14-G14 -> 50143556 | K14: =VLOOKUP(A14,'TFA-Sept,25'!$B$9:$C$136,2,0)-5839-20081-4468 -> 3.6038358e+08 | L14: =+K14-I14 -> 83619871 | M14: =VLOOKUP(A14,'PL-TFA-Oct'!$B$9:$C$138,2,0) -> 3.919506e+08 | N14: =+M14-K14 -> 31567025 | O14: =VLOOKUP(A14,'TFA-Nov,25'!$B$10:$C$144,2,0)-5229-4638 -> 4.3805378e+08 | P14: =+O14-M14 -> 46103174 | Q14: =VLOOKUP(A14,'TB-TFL-A-Dec,25'!$B$10:$C$147,2,0)-1839-20065-1760 -> 5.1824433e+08 | R14: =+Q14-O14 -> 80190553 | S14: =VLOOKUP(A14,'TB-TFL-A-Jan,26'!$B$9:$C$151,2,0)-(1311+6076+5650)-54021 -> 5.9101041e+08 | T14: =+S14-Q14 -> 72766078 | U14: =VLOOKUP(A14,'TB-Feb,26-a'!$B$10:$C$153,2,0)-6616-3651 -> 6.4868176e+08 | V14: =+U14-S14 -> 57671352
A15: SALE LOCAL | B15: =VLOOKUP(A15,'TFL A-April,25'!$B$9:$C$95,2,0) -> 26900 | C15: =VLOOKUP(A15,'May-A'!$B$10:$C$103,2,0) -> 162790 | D15: =+C15-B15 -> 135890 | E15: =VLOOKUP(A15,'June,25-A'!$B$10:$C$123,2,0) -> 162790 | F15: =+E15-C15 -> 0 | G15: =VLOOKUP(A15,'July-A'!$B$10:$C$129,2,0) -> 185950 | H15: =+G15-E15 -> 23160 | I15: =VLOOKUP(A15,'TB-A-Aug'!$B$10:$C$132,2,0) -> 205290 | J15: =+I15-G15 -> 19340 | K15: =VLOOKUP(A15,'TFA-Sept,25'!$B$9:$C$136,2,0) -> 439540 | L15: =+K15-I15 -> 234250 | M15: =VLOOKUP(A15,'PL-TFA-Oct'!$B$9:$C$138,2,0) -> 471500 | N15: =+M15-K15 -> 31960 | O15: =VLOOKUP(A15,'TFA-Nov,25'!$B$10:$C$144,2,0) -> 471500.01 | P15: =+O15-M15 -> 0.01 | Q15: =VLOOKUP(A15,'TB-TFL-A-Dec,25'!$B$10:$C$147,2,0) -> 471500.01 | R15: =+Q15-O15 -> 0 | S15: =VLOOKUP(A15,'TB-TFL-A-Jan,26'!$B$9:$C$151,2,0) -> 471500.01 | T15: =+S15-Q15 -> 0 | U15: =VLOOKUP(A15,'TB-Feb,26-a'!$B$10:$C$153,2,0) -> 471500.01 | V15: =+U15-S15 -> 0
A16: SALE TRADING - LOCAL - GARMENT | G16: =VLOOKUP(A16,'July-A'!$B$10:$C$129,2,0) -> 1961392 | H16: =+G16-E16 -> 1961392 | I16: =VLOOKUP(A16,'TB-A-Aug'!$B$10:$C$132,2,0) -> 2001211 | J16: =+I16-G16 -> 39819 | K16: =VLOOKUP(A16,'TFA-Sept,25'!$B$9:$C$136,2,0) -> 2001211 | L16: =+K16-I16 -> 0 | M16: =VLOOKUP(A16,'PL-TFA-Oct'!$B$9:$C$138,2,0) -> 2419148 | N16: =+M16-K16 -> 417937 | O16: =VLOOKUP(A16,'TFA-Nov,25'!$B$10:$C$144,2,0) -> 2419148 | P16: =+O16-M16 -> 0 | Q16: =VLOOKUP(A16,'TB-TFL-A-Dec,25'!$B$10:$C$147,2,0) -> 2821225 | R16: =+Q16-O16 -> 402077 | S16: =VLOOKUP(A16,'TB-TFL-A-Jan,26'!$B$9:$C$151,2,0) -> 3094230 | T16: =+S16-Q16 -> 273005 | U16: =VLOOKUP(A16,'TB-Feb,26-a'!$B$10:$C$153,2,0) -> 4971595 | V16: =+U16-S16 -> 1877365
A17: SALE TRADING - LOCAL - FABRIC | B17: =VLOOKUP(A17,'TFL A-April,25'!$B$9:$C$95,2,0) -> 1704310 | C17: =VLOOKUP(A17,'May-A'!$B$10:$C$103,2,0) -> 1704310 | D17: =+C17-B17 -> 0 | E17: =VLOOKUP(A17,'June,25-A'!$B$10:$C$123,2,0) -> 3480367 | F17: =+E17-C17 -> 1776057 | G17: =VLOOKUP(A17,'July-A'!$B$10:$C$129,2,0) -> 4008793 | H17: =+G17-E17 -> 528426 | I17: =VLOOKUP(A17,'TB-A-Aug'!$B$10:$C$132,2,0) -> 4930093 | J17: =+I17-G17 -> 921300 | K17: =VLOOKUP(A17,'TFA-Sept,25'!$B$9:$C$136,2,0) -> 5699323 | L17: =+K17-I17 -> 769230 | M17: =VLOOKUP(A17,'PL-TFA-Oct'!$B$9:$C$138,2,0) -> 5699323 | N17: =+M17-K17 -> 0 | O17: =VLOOKUP(A17,'TFA-Nov,25'!$B$10:$C$144,2,0) -> 6121968 | P17: =+O17-M17 -> 422645 | Q17: =VLOOKUP(A17,'TB-TFL-A-Dec,25'!$B$10:$C$147,2,0) -> 7995966 | R17: =+Q17-O17 -> 1873998 | S17: =VLOOKUP(A17,'TB-TFL-A-Jan,26'!$B$9:$C$151,2,0) -> 9757463 | T17: =+S17-Q17 -> 1761497 | U17: =VLOOKUP(A17,'TB-Feb,26-a'!$B$10:$C$153,2,0) -> 9760163 | V17: =+U17-S17 -> 2700
A18: GROSS SALES | B18: =SUM(B9:B17) -> 49591939 | C18: =SUM(C9:C17) -> 112633188 | D18: =SUM(D9:D17) -> 63041249 | E18: =SUM(E9:E17) -> 1.6975205e+08 | F18: =SUM(F9:F17) -> 57118863 | G18: =SUM(G9:G17) -> 2.6084314e+08 | H18: =SUM(H9:H17) -> 91091084 | I18: =SUM(I9:I17) -> 3.2285515e+08 | ... V18: =SUM(V9:V17) -> 89334305
A19: EXPENSES RELATED TO SALES
A20: PACKING EXPENSES | B20: =VLOOKUP(A20,'TFL A-April,25'!$B$9:$C$95,2,0) -> 370 | C20: =VLOOKUP(A20,'May-A'!$B$10:$C$103,2,0) -> 370 | D20: =+C20-B20 -> 0 | E20: =VLOOKUP(A20,'June,25-A'!$B$10:$C$123,2,0) -> 1170 | F20: =+E20-C20 -> 800 | G20: =VLOOKUP(A20,'July-A'!$B$10:$C$129,2,0) -> 1170 | H20: =+G20-E20 -> 0 | I20: =VLOOKUP(A20,'TB-A-Aug'!$B$10:$C$132,2,0) -> 1170 | J20: =+I20-G20 -> 0 | K20: =VLOOKUP(A20,'TFA-Sept,25'!$B$9:$C$136,2,0) -> 1170 | L20: =+K20-I20 -> 0 | M20: =VLOOKUP(A20,'PL-TFA-Oct'!$B$9:$C$138,2,0) -> 2270 | N20: =+M20-K20 -> 1100 | O20: =VLOOKUP(A20,'TFA-Nov,25'!$B$10:$C$144,2,0) -> 2470 | P20: =+O20-M20 -> 200 | Q20: =VLOOKUP(A20,'TB-TFL-A-Dec,25'!$B$10:$C$147,2,0) -> 3275 | R20: =+Q20-O20 -> 805 | S20: =VLOOKUP(A20,'TB-TFL-A-Jan,26'!$B$9:$C$151,2,0) -> 3275 | T20: =+S20-Q20 -> 0 | U20: =VLOOKUP(A20,'TB-Feb,26-a'!$B$10:$C$153,2,0) -> 3275 | V20: =+U20-S20 -> 0
A21: DELIVERY CHARGES ON SALES | B21: =VLOOKUP(A21,'TFL A-April,25'!$B$9:$C$95,2,0) -> 15803 | C21: =VLOOKUP(A21,'May-A'!$B$10:$C$103,2,0)+79714 -> 304524.24 | D21: =+C21-B21 -> 288721.24 | E21: =VLOOKUP(A21,'June,25-A'!$B$10:$C$123,2,0) -> 486121.24 | F21: =+E21-C21 -> 181597 | G21: =VLOOKUP(A21,'July-A'!$B$10:$C$129,2,0)+81644 -> 2209530.2 | H21: =+G21-E21 -> 1723409 | I21: =VLOOKUP(A21,'TB-A-Aug'!$B$10:$C$132,2,0)-57625 -> 2668553.2 | J21: =+I21-G21 -> 459022.98 | K21: =VLOOKUP(A21,'TFA-Sept,25'!$B$9:$C$136,2,0) -> 3139356.7 | L21: =+K21-I21 -> 470803.52 | M21: =VLOOKUP(A21,'PL-TFA-Oct'!$B$9:$C$138,2,0) -> 3321370.4 | N21: =+M21-K21 -> 182013.69 | O21: =VLOOKUP(A21,'TFA-Nov,25'!$B$10:$C$144,2,0) -> 3628852.1 | P21: =+O21-M21 -> 307481.71 | Q21: =VLOOKUP(A21,'TB-TFL-A-Dec,25'!$B$10:$C$147,2,0)+691760+308598 -> 4645461 | R21: =+Q21-O21 -> 1016608.9 | S21: =VLOOKUP(A21,'TB-TFL-A-Jan,26'!$B$9:$C$151,2,0)+176598+852906 -> 5114840.2 | T21: =+S21-Q21 -> 469379.11 | U21: =VLOOKUP(A21,'TB-Feb,26-a'!$B$10:$C$153,2,0)+1026514 -> 5627752.2 | V21: =+U21-S21 -> 512912
A22: DELIVERY CHARGES ON SALE -GARMENT | B22: =VLOOKUP(A22,'TFL A-April,25'!$B$9:$C$95,2,0) -> 212973.3 | C22: =VLOOKUP(A22,'May-A'!$B$10:$C$103,2,0) -> 382533.84 | D22: =+C22-B22 -> 169560.54 | E22: =VLOOKUP(A22,'June,25-A'!$B$10:$C$123,2,0)+617400 -> 1381133.8 | F22: =+E22-C22 -> 998600 | G22: =VLOOKUP(A22,'July-A'!$B$10:$C$129,2,0)+79715+669619 -> 1717980.4 | H22: =+G22-E22 -> 336846.6 | I22: =VLOOKUP(A22,'TB-A-Aug'!$B$10:$C$132,2,0)+58705+364483+57625 -> 1717980.4 | J22: =+I22-G22 -> 0 | K22: =VLOOKUP(A22,'TFA-Sept,25'!$B$9:$C$136,2,0)+500508 -> 2180159.7 | L22: =+K22-I22 -> 462179.23 | M22: =VLOOKUP(A22,'PL-TFA-Oct'!$B$9:$C$138,2,0)+'PL-TFA-Oct'!C69+411085 -> 2862982.8 | N22: =+M22-K22 -> 682823.14 | O22: =VLOOKUP(A22,'TFA-Nov,25'!$B$10:$C$144,2,0)+'TFA-Nov,25'!C71+631068 -> 3241559.8 | P22: =+O22-M22 -> 378577.02 | Q22: =VLOOKUP(A22,'TB-TFL-A-Dec,25'!$B$10:$C$147,2,0) -> 3456402.8 | R22: =+Q22-O22 -> 214843 | S22: =VLOOKUP(A22,'TB-TFL-A-Jan,26'!$B$9:$C$151,2,0) -> 3906763.1 | T22: =+S22-Q22 -> 450360.24 | U22: =VLOOKUP(A22,'TB-Feb,26-a'!$B$10:$C$153,2,0) -> 4065545.8 | V22: =+U22-S22 -> 158782.69
A23: CLEARING CHARGES ON EXPORT | D23: =+C23-B23 -> 0 | F23: =+E23-C23 -> 0 | H23: =+G23-E23 -> 0 | J23: =+I23-G23 -> 0 | L23: =+K23-I23 -> 0 | N23: =+M23-K23 -> 0 | P23: =+O23-M23 -> 0 | R23: =+Q23-O23 -> 0 | T23: =+S23-Q23 -> 0 | V23: =+U23-S23 -> 0
A24: DOCUMENTATION CHARGES | D24: =+C24-B24 -> 0 | F24: =+E24-C24 -> 0 | H24: =+G24-E24 -> 0 | J24: =+I24-G24 -> 0 | L24: =+K24-I24 -> 0 | N24: =+M24-K24 -> 0 | P24: =+O24-M24 -> 0 | R24: =+Q24-O24 -> 0 | T24: =+S24-Q24 -> 0 | V24: =+U24-S24 -> 0
A25: FREIGHT ON EXPORT
A26: FREIGHT ON EXPORT - (AIR) | D26: =+C26-B26 -> 0 | F26: =+E26-C26 -> 0 | H26: =+G26-E26 -> 0 | J26: =+I26-G26 -> 0 | L26: =+K26-I26 -> 0 | N26: =+M26-K26 -> 0 | P26: =+O26-M26 -> 0 | R26: =+Q26-O26 -> 0 | T26: =+S26-Q26 -> 0 | V26: =+U26-S26 -> 0
A27: TERMINAL HANDLING CHARGES | D27: =+C27-B27 -> 0 | F27: =+E27-C27 -> 0 | H27: =+G27-E27 -> 0 | J27: =+I27-G27 -> 0 | L27: =+K27-I27 -> 0 | N27: =+M27-K27 -> 0 | P27: =+O27-M27 -> 0 | R27: =+Q27-O27 -> 0 | T27: =+S27-Q27 -> 0 | V27: =+U27-S27 -> 0
A28: COOLIE & CARTAGE ON SALES | L28: =+K28-I28 -> 0 | N28: =+M28-K28 -> 0 | P28: =+O28-M28 -> 0 | R28: =+Q28-O28 -> 0 | T28: =+S28-Q28 -> 0 | V28: =+U28-S28 -> 0
A29: INSURANCE FOR EXPORT
A30: DELIVERY CHARGES ON SALE-FABRIC
A31: EXPORT EXPENSES | C31: =+SUM('May-A'!C46:C50)-'May-A'!C48 -> 207710.22 | D31: =+C31-B31 -> 207710.22 | E31: 207710 | F31: =+E31-C31 -> -0.22 | G31: =256403.22 -> 256403.22 | H31: =+G31-E31 -> 48693.22 | I31: =268673.22+144964 -> 413637.22 | J31: =+I31-G31 -> 157234 | K31: =VLOOKUP(A31,'TFA-Sept,25'!$B$9:$C$136,2,0)+340147+132287 -> 474954 | L31: =+K31-I31 -> 61316.78 | M31: =2520+526552-63882+61611+132287 -> 659088 | N31: =+M31-K31 -> 184134 | O31: =1019685.22+130425 -> 1150110.2 | P31: =+O31-M31 -> 491022.22 | Q31: =1501885.22+52450+241870 -> 1796205.2 | R31: =+Q31-O31 -> 646095 | S31: =1808425.02 -> 1808425 | T31: =+S31-Q31 -> 12219.8 | U31: 1974917.5 | V31: =+U31-S31 -> 166492.44
A32: DETENTION CHARGES ON EXPORT | D32: =+C32-B32 -> 0 | F32: =+E32-C32 -> 0 | H32: =+G32-E32 -> 0 | J32: =+I32-G32 -> 0 | L32: =+K32-I32 -> 0 | N32: =+M32-K32 -> 0 | P32: =+O32-M32 -> 0 | R32: =+Q32-O32 -> 0 | T32: =+S32-Q32 -> 0 | V32: =+U32-S32 -> 0
A33: MARKETING DEVELOPMENT ASSISTANCE | K33: =VLOOKUP(A33,'TFA-Sept,25'!$B$9:$C$136,2,0) -> 88549 | L33: =+K33-I33 -> 88549 | M33: =VLOOKUP(A33,'PL-TFA-Oct'!$B$9:$C$138,2,0) -> 88549 | N33: =+M33-K33 -> 0 | O33: =VLOOKUP(A33,'TFA-Nov,25'!$B$10:$C$144,2,0) -> 88549 | P33: =+O33-M33 -> 0 | Q33: =VLOOKUP(A33,'TB-TFL-A-Dec,25'!$B$10:$C$147,2,0) -> 88549 | R33: =+Q33-O33 -> 0 | S33: =VLOOKUP(A33,'TB-TFL-A-Jan,26'!$B$9:$C$151,2,0) -> 88549 | T33: =+S33-Q33 -> 0 | U33: =VLOOKUP(A33,'TB-Feb,26-a'!$B$10:$C$153,2,0) -> 88549 | V33: =+U33-S33 -> 0
A34: BUSINESS SUPPORT SERVICES | C34: 184166 | D34: =+C34-B34 -> 184166 | E34: 183672 | F34: =+E34-C34 -> -494 | G34: 183672 | H34: =+G34-E34 -> 0 | I34: 183672 | J34: =+I34-G34 -> 0 | K34: 190161 | L34: =+K34-I34 -> 6489 | M34: 190161 | N34: =+M34-K34 -> 0 | O34: =238351+3688936.7508 -> 3927287.8 | P34: =+O34-M34 -> 3737126.8 | Q34: =241278+7604791 -> 7846069 | R34: =+Q34-O34 -> 3918781.2 | S34: =241278+7604791 -> 7846069 | T34: =+S34-Q34 -> 0 | U34: =VLOOKUP(A34,'TB-Feb,26-a'!$B$10:$C$153,2,0)+2543939+92175 -> 8387918.4 | V34: =+U34-S34 -> 541849.43
A35: COMMISSION/BROKERAGE | O35: =VLOOKUP(A35,'TFA-Nov,25'!$B$10:$C$144,2,0) -> 70000 | P35: =+O35-M35 -> 70000 | Q35: =VLOOKUP(A35,'TB-TFL-A-Dec,25'!$B$10:$C$147,2,0) -> 70000 | R35: =+Q35-O35 -> 0 | S35: =VLOOKUP(A35,'TB-TFL-A-Jan,26'!$B$9:$C$151,2,0) -> 70000 | T35: =+S35-Q35 -> 0 | U35: =VLOOKUP(A35,'TB-Feb,26-a'!$B$10:$C$153,2,0) -> 70000 | V35: =+U35-S35 -> 0
A36: TOTAL EXPENSES RELATED TO SALES | B36: =SUM(B20:B34) -> 229146.3 | C36: =SUM(C20:C34) -> 1079304.3 | D36: =SUM(D20:D34) -> 850158 | E36: =SUM(E20:E34) -> 2259807.1 | F36: =SUM(F20:F34) -> 1180502.8 | G36: =SUM(G20:G34) -> 4368755.9 | H36: =SUM(H20:H34) -> 2108948.8 | I36: =SUM(I20:I34) -> 4985012.9 | ... N36: =SUM(N20:N34) -> 1050070.8 | O36: =SUM(O20:O35) -> 12108829 | P36: =SUM(P20:P35) -> 4984407.7 | Q36: =SUM(Q20:Q35) -> 17905962 | R36: =SUM(R20:R35) -> 5797133.1 | S36: =SUM(S20:S35) -> 18837921 | T36: =SUM(T20:T35) -> 931959.15 | U36: =SUM(U20:U35) -> 20217958 | V36: =SUM(V20:V35) -> 1380036.6
A37: NET SALES | B37: =B18-B36 -> 49362792 | C37: =C18-C36 -> 1.1155388e+08 | D37: =D18-D36 -> 62191091 | E37: =E18-E36 -> 1.6749224e+08 | F37: =F18-F36 -> 55938361 | G37: =G18-G36 -> 2.5647438e+08 | H37: =H18-H36 -> 88982135 | I37: =I18-I36 -> 3.1787014e+08 | ... V37: =V18-V36 -> 87954268
A38: OTHER OPERATING INCOME
A39: DUTY DRAWBACK RECEIVED | C39: 517983 | D39: =+C39-B39 -> 517983 | E39: =VLOOKUP(A39,'June,25-A'!$B$10:$C$123,2,0)+2190 -> 517983 | F39: =+E39-D39 -> 0 | G39: =VLOOKUP(A39,'July-A'!$B$10:$C$129,2,0)+45560 -> 836371 | H39: =+G39-E39 -> 318388 | I39: =VLOOKUP(A39,'TB-A-Aug'!$B$10:$C$132,2,0)+329601 -> 1163782 | J39: =+I39-G39 -> 327411 | K39: =VLOOKUP(A39,'TFA-Sept,25'!$B$9:$C$136,2,0)+372686 -> 1248612 | L39: =+K39-I39 -> 84830 | M39: =VLOOKUP(A39,'PL-TFA-Oct'!$B$9:$C$138,2,0)+790611 -> 1751367 | N39: =+M39-K39 -> 502755 | O39: =VLOOKUP(A39,'TFA-Nov,25'!$B$10:$C$144,2,0)+1948603 -> 3861478 | P39: =+O39-M39 -> 2110111 | Q39: =VLOOKUP(A39,'TB-TFL-A-Dec,25'!$B$10:$C$147,2,0)-427543+3559740 -> 6018309 | R39: =+Q39-O39 -> 2156831 | S39: =VLOOKUP(A39,'TB-TFL-A-Jan,26'!$B$9:$C$151,2,0)+875342-209645 -> 6018905 | T39: =+S39-Q39 -> 596 | U39: =VLOOKUP(A39,'TB-Feb,26-a'!$B$10:$C$153,2,0)+1301521 -> 6655556 | V39: =+U39-S39 -> 636651
A40: DEPB LICENCE SALE | C40: =VLOOKUP(A40,'May-A'!$B$10:$C$103,2,0) -> 316074 | D40: =+C40-B40 -> 316074 | E40: =VLOOKUP(A40,'June,25-A'!$B$10:$C$123,2,0) -> 316074 | F40: =+E40-C40 -> 0 | G40: =VLOOKUP(A40,'July-A'!$B$10:$C$129,2,0) -> 316074 | H40: =+G40-E40 -> 0 | I40: =VLOOKUP(A40,'TB-A-Aug'!$B$10:$C$132,2,0) -> 316074 | J40: =+I40-G40 -> 0 | K40: =VLOOKUP(A40,'TFA-Sept,25'!$B$9:$C$136,2,0) -> 6259301 | L40: =+K40-I40 -> 5943227 | M40: =VLOOKUP(A40,'PL-TFA-Oct'!$B$9:$C$138,2,0) -> 6259301 | N40: =+M40-K40 -> 0 | O40: =VLOOKUP(A40,'TFA-Nov,25'!$B$10:$C$144,2,0) -> 6259301 | P40: =+O40-M40 -> 0 | Q40: =VLOOKUP(A40,'TB-TFL-A-Dec,25'!$B$10:$C$147,2,0) -> 6259301 | R40: =+Q40-O40 -> 0 | S40: =VLOOKUP(A40,'TB-TFL-A-Jan,26'!$B$9:$C$151,2,0) -> 7320935 | T40: =+S40-Q40 -> 1061634 | U40: =VLOOKUP(A40,'TB-Feb,26-a'!$B$10:$C$153,2,0) -> 7320935 | V40: =+U40-S40 -> 0
A41: Rodtep Licence as per Receipt basis | C41: =-C40 -> -316074 | D41: =+C41-B41 -> -316074 | E41: =-E40 -> -316074 | F41: =+E41-C41 -> 0 | G41: =-G40 -> -316074 | H41: =+G41-E41 -> 0 | I41: =-I40 -> -316074 | J41: =+I41-G41 -> 0 | K41: =-K40 -> -6259301 | L41: =+K41-I41 -> -5943227 | M41: =-M40 -> -6259301 | N41: =+M41-K41 -> 0 | O41: =-O40 -> -6259301 | P41: =+O41-M41 -> 0 | Q41: =-Q40 -> -6259301 | R41: =+Q41-O41 -> 0 | S41: =-S40 -> -7320935 | T41: =+S41-Q41 -> -1061634 | U41: =-U40 -> -7320935 | V41: =+U41-S41 -> 0
A42: Rodtep Licence as per Accrual basis | C42: 859887 | D42: =+C42-B42 -> 859887 | E42: 859887 | F42: =+E42-C42 -> 0 | G42: 1347177 | H42: =+G42-E42 -> 487290 | I42: 1755145 | J42: =+I42-G42 -> 407968 | K42: 1849897 | L42: =+K42-I42 -> 94752 | M42: 2694207 | N42: =+M42-K42 -> 844310 | O42: 5431594 | P42: =+O42-M42 -> 2737387 | Q42: =4042289+4093906 -> 8136195 | R42: =+Q42-O42 -> 2704601 | S42: 8137208 | T42: =+S42-Q42 -> 1013 | U42: 8978541 | V42: =+U42-S42 -> 841333
A43: SALE SCRAP | B43: =VLOOKUP(A43,'TFL A-April,25'!$B$9:$C$95,2,0) -> 21100 | C43: =VLOOKUP(A43,'May-A'!$B$10:$C$103,2,0) -> 75856 | D43: =+C43-B43 -> 54756 | E43: =VLOOKUP(A43,'June,25-A'!$B$10:$C$123,2,0) -> 122094 | F43: =+E43-C43 -> 46238 | G43: =VLOOKUP(A43,'July-A'!$B$10:$C$129,2,0) -> 155784 | H43: =+G43-E43 -> 33690 | I43: =VLOOKUP(A43,'TB-A-Aug'!$B$10:$C$132,2,0) -> 510434 | J43: =+I43-G43 -> 354650 | K43: =VLOOKUP(A43,'TFA-Sept,25'!$B$9:$C$136,2,0) -> 533514 | L43: =+K43-I43 -> 23080 | M43: =VLOOKUP(A43,'PL-TFA-Oct'!$B$9:$C$138,2,0) -> 533514 | N43: =+M43-K43 -> 0 | O43: =VLOOKUP(A43,'TFA-Nov,25'!$B$10:$C$144,2,0) -> 575364 | P43: =+O43-M43 -> 41850 | Q43: =VLOOKUP(A43,'TB-TFL-A-Dec,25'!$B$10:$C$147,2,0) -> 627514 | R43: =+Q43-O43 -> 52150 | S43: =VLOOKUP(A43,'TB-TFL-A-Jan,26'!$B$9:$C$151,2,0) -> 644564 | T43: =+S43-Q43 -> 17050 | U43: =VLOOKUP(A43,'TB-Feb,26-a'!$B$10:$C$153,2,0) -> 682214 | V43: =+U43-S43 -> 37650
A44: SALE FABRIC WASTE | B44: =VLOOKUP(A44,'TFL A-April,25'!$B$9:$C$95,2,0) -> 235670 | C44: =VLOOKUP(A44,'May-A'!$B$10:$C$103,2,0) -> 864560 | D44: =+C44-B44 -> 628890 | E44: =VLOOKUP(A44,'June,25-A'!$B$10:$C$123,2,0) -> 1524524 | F44: =+E44-C44 -> 659964 | G44: =VLOOKUP(A44,'July-A'!$B$10:$C$129,2,0) -> 2117005 | H44: =+G44-E44 -> 592481 | I44: =VLOOKUP(A44,'TB-A-Aug'!$B$10:$C$132,2,0) -> 2839665 | J44: =+I44-G44 -> 722660 | K44: =VLOOKUP(A44,'TFA-Sept,25'!$B$9:$C$136,2,0) -> 3196865 | L44: =+K44-I44 -> 357200 | M44: =VLOOKUP(A44,'PL-TFA-Oct'!$B$9:$C$138,2,0) -> 3839855 | N44: =+M44-K44 -> 642990 | O44: =VLOOKUP(A44,'TFA-Nov,25'!$B$10:$C$144,2,0) -> 4155695 | P44: =+O44-M44 -> 315840 | Q44: =VLOOKUP(A44,'TB-TFL-A-Dec,25'!$B$10:$C$147,2,0) -> 5026115 | R44: =+Q44-O44 -> 870420 | S44: =VLOOKUP(A44,'TB-TFL-A-Jan,26'!$B$9:$C$151,2,0) -> 5800745 | T44: =+S44-Q44 -> 774630 | U44: =VLOOKUP(A44,'TB-Feb,26-a'!$B$10:$C$153,2,0) -> 6318995 | V44: =+U44-S44 -> 518250
A45: TOTAL OTHER OPERATING INCOME | B45: =SUM(B39:B44) -> 256770 | C45: =SUM(C39:C44) -> 2318286 | D45: =SUM(D39:D44) -> 2061516 | E45: =SUM(E39:E44) -> 3024488 | F45: =SUM(F39:F44) -> 706202 | G45: =SUM(G39:G44) -> 4456337 | H45: =SUM(H39:H44) -> 1431849 | I45: =SUM(I39:I44) -> 6269026 | ... V45: =SUM(V39:V44) -> 2033884
A46: REVENUE FROM OPERATIONS | B46: =B37+B45 -> 49619562 | C46: =C37+C45 -> 1.1387217e+08 | D46: =D37+D45 -> 64252607 | E46: =E37+E45 -> 1.7051673e+08 | F46: =F37+F45 -> 56644563 | G46: =G37+G45 -> 2.6093072e+08 | H46: =H37+H45 -> 90413984 | I46: =I37+I45 -> 3.2413917e+08 | ... V46: =V37+V45 -> 89988152
A48: EXPENSES
A49: COST OF GOODS SOLD
A50: OPENING STOCK | B50: =162055789-564066 -> 161491723 | C50: =162055789-564066 -> 161491723 | D50: =+C50-B50 -> 0 | E50: =162055789-564066 -> 161491723 | F50: =+E50-C50 -> 0 | G50: =162055789-564066 -> 161491723 | H50: =+G50-E50 -> 0 | I50: =162055789-564066 -> 161491723 | J50: =+I50-G50 -> 0 | K50: =162055789-564066 -> 161491723 | L50: =+K50-I50 -> 0 | M50: =162055789-564066 -> 161491723 | N50: =+M50-K50 -> 0 | O50: =162055789-564066 -> 161491723 | P50: =+O50-M50 -> 0 | Q50: =162055789-564066 -> 161491723 | R50: =+Q50-O50 -> 0 | S50: =162055789-564066 -> 161491723 | T50: =+S50-Q50 -> 0 | U50: =162055789-564066 -> 161491723 | V50: =+U50-S50 -> 0
A51: PURCHASE FABRICS & HOSIERY LOCAL | B51: =VLOOKUP(A51,'TFL A-April,25'!$B$9:$C$95,2,0)+7765413 -> 21624068 | C51: =VLOOKUP(A51,'May-A'!$B$10:$C$103,2,0)+11685002 -> 56514483 | D51: =+C51-B51 -> 34890415 | E51: =VLOOKUP(A51,'June,25-A'!$B$10:$C$123,2,0)+157027 -> 92339270 | F51: =+E51-C51 -> 35824787 | G51: =VLOOKUP(A51,'July-A'!$B$10:$C$129,2,0)+305450 -> 1.340444e+08 | H51: =+G51-E51 -> 41705125 | I51: =VLOOKUP(A51,'TB-A-Aug'!$B$10:$C$132,2,0)+3925110 -> 1.731658e+08 | J51: =+I51-G51 -> 39121406 | K51: =VLOOKUP(A51,'TFA-Sept,25'!$B$9:$C$136,2,0)+4116311 -> 2.2478117e+08 | L51: =+K51-I51 -> 51615372 | M51: =VLOOKUP(A51,'PL-TFA-Oct'!$B$9:$C$138,2,0)+4221936 -> 2.6947259e+08 | N51: =+M51-K51 -> 44691418 | O51: =VLOOKUP(A51,'TFA-Nov,25'!$B$10:$C$144,2,0)+4300-3691041 -> 3.7264743e+08 | P51: =+O51-M51 -> 1.0317484e+08 | Q51: =VLOOKUP(A51,'TB-TFL-A-Dec,25'!$B$10:$C$147,2,0)+5415792-7648453 -> 4.869369e+08 | R51: =+Q51-O51 -> 1.1428947e+08 | S51: =VLOOKUP(A51,'TB-TFL-A-Jan,26'!$B$9:$C$151,2,0)+20795591-7648453 -> 5.5895829e+08 | T51: =+S51-Q51 -> 72021391 | U51: =VLOOKUP(A51,'TB-Feb,26-a'!$B$10:$C$153,2,0)+5765800 -> 6.1342312e+08 | V51: =+U51-S51 -> 54464837
A52: PURCHASE YARN - LOCAL | C52: 4363200 | D52: =+C52-B52 -> 4363200 | E52: =VLOOKUP(A52,'June,25-A'!$B$10:$C$123,2,0) -> 15711171 | F52: =+E52-C52 -> 11347971 | G52: =VLOOKUP(A52,'July-A'!$B$10:$C$129,2,0) -> 16255569 | H52: =+G52-E52 -> 544398.18 | I52: =VLOOKUP(A52,'TB-A-Aug'!$B$10:$C$132,2,0) -> 16255569 | J52: =+I52-G52 -> 0 | K52: =VLOOKUP(A52,'TFA-Sept,25'!$B$9:$C$136,2,0) -> 21505900 | L52: =+K52-I52 -> 5250331 | M52: =VLOOKUP(A52,'PL-TFA-Oct'!$B$9:$C$138,2,0) -> 21505900 | N52: =+M52-K52 -> 0 | O52: =VLOOKUP(A52,'TFA-Nov,25'!$B$10:$C$144,2,0) -> 21505900 | P52: =+O52-M52 -> 0 | Q52: =VLOOKUP(A52,'TB-TFL-A-Dec,25'!$B$10:$C$147,2,0) -> 21505900 | R52: =+Q52-O52 -> 0 | S52: =VLOOKUP(A52,'TB-TFL-A-Jan,26'!$B$9:$C$151,2,0) -> 21505900 | T52: =+S52-Q52 -> 0 | U52: =VLOOKUP(A52,'TB-Feb,26-a'!$B$10:$C$153,2,0) -> 21505900 | V52: =+U52-S52 -> 0
A53: DELIVERY CHARGES ON PURCHASES | B53: =VLOOKUP(A53,'TFL A-April,25'!$B$9:$C$95,2,0) -> 49560 | C53: =VLOOKUP(A53,'May-A'!$B$10:$C$103,2,0) -> 130704 | D53: =+C53-B53 -> 81144 | E53: =VLOOKUP(A53,'June,25-A'!$B$10:$C$123,2,0) -> 151414 | F53: =+E53-C53 -> 20710 | G53: =VLOOKUP(A53,'July-A'!$B$10:$C$129,2,0) -> 246584 | H53: =+G53-E53 -> 95170 | I53: =VLOOKUP(A53,'TB-A-Aug'!$B$10:$C$132,2,0) -> 279664 | J53: =+I53-G53 -> 33080 | K53: =VLOOKUP(A53,'TFA-Sept,25'!$B$9:$C$136,2,0) -> 333003 | L53: =+K53-I53 -> 53339 | M53: =VLOOKUP(A53,'PL-TFA-Oct'!$B$9:$C$138,2,0) -> 359828 | N53: =+M53-K53 -> 26825 | O53: =VLOOKUP(A53,'TFA-Nov,25'!$B$10:$C$144,2,0)+144353 -> 525972 | P53: =+O53-M53 -> 166144 | Q53: =VLOOKUP(A53,'TB-TFL-A-Dec,25'!$B$10:$C$147,2,0)+403169 -> 805876 | R53: =+Q53-O53 -> 279904 | S53: =VLOOKUP(A53,'TB-TFL-A-Jan,26'!$B$9:$C$151,2,0)+17197+1031650 -> 1474114 | T53: =+S53-Q53 -> 668238 | U53: =VLOOKUP(A53,'TB-Feb,26-a'!$B$10:$C$153,2,0)+1120442 -> 1577814 | V53: =+U53-S53 -> 103700
A54: DELIVERY CHARGES - PURCHASE- FABRIC | C54: =VLOOKUP(A54,'May-A'!$B$10:$C$103,2,0)+266245 -> 422014 | D54: =+C54-B54 -> 422014 | E54: =VLOOKUP(A54,'June,25-A'!$B$10:$C$123,2,0)+299941 -> 472710 | F54: =+E54-C54 -> 50696 | G54: =VLOOKUP(A54,'July-A'!$B$10:$C$129,2,0)+663700 -> 1060184.4 | H54: =+G54-E54 -> 587474.41 | I54: =VLOOKUP(A54,'TB-A-Aug'!$B$10:$C$132,2,0)+239000 -> 1784563.4 | J54: =+I54-G54 -> 724379.02 | K54: =VLOOKUP(A54,'TFA-Sept,25'!$B$9:$C$136,2,0) -> 2217544.7 | L54: =+K54-I54 -> 432981.25 | M54: =VLOOKUP(A54,'PL-TFA-Oct'!$B$9:$C$138,2,0)+269000 -> 2561544.7 | N54: =+M54-K54 -> 344000 | O54: =VLOOKUP(A54,'TFA-Nov,25'!$B$10:$C$144,2,0) -> 2786461.1 | P54: =+O54-M54 -> 224916.46 | Q54: =VLOOKUP(A54,'TB-TFL-A-Dec,25'!$B$10:$C$147,2,0) -> 2949461.1 | R54: =+Q54-O54 -> 163000 | S54: =VLOOKUP(A54,'TB-TFL-A-Jan,26'!$B$9:$C$151,2,0) -> 2949461.1 | T54: =+S54-Q54 -> 0 | U54: =VLOOKUP(A54,'TB-Feb,26-a'!$B$10:$C$153,2,0) -> 3127405.8 | V54: =+U54-S54 -> 177944.63
A55: DELIVERY CHARGES - PURCHASE-GARMENT | B55: =VLOOKUP(A55,'TFL A-April,25'!$B$9:$C$95,2,0) -> 136918.62 | C55: =VLOOKUP(A55,'May-A'!$B$10:$C$103,2,0) -> 258906.48 | D55: =+C55-B55 -> 121987.86 | E55: =VLOOKUP(A55,'June,25-A'!$B$10:$C$123,2,0)+538052 -> 1048958.5 | F55: =+E55-C55 -> 790052 | G55: =VLOOKUP(A55,'July-A'!$B$10:$C$129,2,0)+288715 -> 1291929.1 | H55: =+G55-E55 -> 242970.59 | I55: =VLOOKUP(A55,'TB-A-Aug'!$B$10:$C$132,2,0)+754454.5 -> 1951692 | J55: =+I55-G55 -> 659762.92 | K55: =VLOOKUP(A55,'TFA-Sept,25'!$B$9:$C$136,2,0)+581466 -> 2294085.4 | L55: =+K55-I55 -> 342393.41 | M55: =VLOOKUP(A55,'PL-TFA-Oct'!$B$9:$C$138,2,0)+938468 -> 3099076.1 | N55: =+M55-K55 -> 804990.72 | O55: =VLOOKUP(A55,'TFA-Nov,25'!$B$10:$C$144,2,0) -> 3182557.7 | P55: =+O55-M55 -> 83481.6 | Q55: =VLOOKUP(A55,'TB-TFL-A-Dec,25'!$B$10:$C$147,2,0) -> 3492809.1 | R55: =+Q55-O55 -> 310251.34 | S55: =VLOOKUP(A55,'TB-TFL-A-Jan,26'!$B$9:$C$151,2,0) -> 3768745.3 | T55: =+S55-Q55 -> 275936.24 | U55: =VLOOKUP(A55,'TB-Feb,26-a'!$B$10:$C$153,2,0) -> 4211205.7 | V55: =+U55-S55 -> 442460.41
A56: PURCHASE FOR TRADING - GARMENT | C56: =VLOOKUP(A56,'May-A'!$B$10:$C$103,2,0) -> 8460079 | D56: =+C56-B56 -> 8460079 | E56: =VLOOKUP(A56,'June,25-A'!$B$10:$C$123,2,0) -> 8460079 | F56: =+E56-C56 -> 0 | G56: =VLOOKUP(A56,'July-A'!$B$10:$C$129,2,0) -> 8460079 | H56: =+G56-E56 -> 0 | I56: =VLOOKUP(A56,'TB-A-Aug'!$B$10:$C$132,2,0) -> 8460079 | J56: =+I56-G56 -> 0 | K56: =VLOOKUP(A56,'TFA-Sept,25'!$B$9:$C$136,2,0) -> 8460079 | L56: =+K56-I56 -> 0 | M56: =VLOOKUP(A56,'PL-TFA-Oct'!$B$9:$C$138,2,0) -> 8460079 | N56: =+M56-K56 -> 0 | O56: =VLOOKUP(A56,'TFA-Nov,25'!$B$10:$C$144,2,0) -> 8460079 | P56: =+O56-M56 -> 0 | Q56: =VLOOKUP(A56,'TB-TFL-A-Dec,25'!$B$10:$C$147,2,0) -> 8460079 | R56: =+Q56-O56 -> 0 | S56: =VLOOKUP(A56,'TB-TFL-A-Jan,26'!$B$9:$C$151,2,0) -> 8460079 | T56: =+S56-Q56 -> 0 | U56: =VLOOKUP(A56,'TB-Feb,26-a'!$B$10:$C$153,2,0) -> 8460079 | V56: =+U56-S56 -> 0
A57: PUR. THREAD & TRIM ITEMS | B57: =VLOOKUP(A57,'TFL A-April,25'!$B$9:$C$95,2,0)+1566967 -> 6052378.4 | C57: =VLOOKUP(A57,'May-A'!$B$10:$C$103,2,0)+1552677 -> 10960901 | D57: =+C57-B57 -> 4908522.1 | E57: =VLOOKUP(A57,'June,25-A'!$B$10:$C$123,2,0)+386905 -> 14613110 | F57: =+E57-C57 -> 3652209.1 | G57: =VLOOKUP(A57,'July-A'!$B$10:$C$129,2,0)+1623551+20170 -> 23264220 | H57: =+G57-E57 -> 8651109.9 | I57: =VLOOKUP(A57,'TB-A-Aug'!$B$10:$C$132,2,0)+2133317+20170 -> 26880068 | J57: =+I57-G57 -> 3615848.9 | K57: =VLOOKUP(A57,'TFA-Sept,25'!$B$9:$C$136,2,0)+602048+20170 -> 33028070 | L57: =+K57-I57 -> 6148002 | M57: =VLOOKUP(A57,'PL-TFA-Oct'!$B$9:$C$138,2,0)+752418 -> 36987494 | N57: =+M57-K57 -> 3959423.7 | O57: =VLOOKUP(A57,'TFA-Nov,25'!$B$10:$C$144,2,0)+666227 -> 41174309 | P57: =+O57-M57 -> 4186814.7 | Q57: =VLOOKUP(A57,'TB-TFL-A-Dec,25'!$B$10:$C$147,2,0)+491863 -> 45966285 | R57: =+Q57-O57 -> 4791976.5 | S57: =VLOOKUP(A57,'TB-TFL-A-Jan,26'!$B$9:$C$151,2,0)+1270700 -> 50431955 | T57: =+S57-Q57 -> 4465669.9 | U57: =VLOOKUP(A57,'TB-Feb,26-a'!$B$10:$C$153,2,0)+1581804 -> 55409554 | V57: =+U57-S57 -> 4977598.8
A58: PUR. THREAD & TRIM ITEMS- IMPORT | B58: =VLOOKUP(A58,'TFL A-April,25'!$B$9:$C$95,2,0) -> 211799.78 | C58: =VLOOKUP(A58,'May-A'!$B$10:$C$103,2,0) -> 211799.78 | D58: =+C58-B58 -> 0 | E58: =VLOOKUP(A58,'June,25-A'!$B$10:$C$123,2,0)+37664 -> 601203.68 | F58: =+E58-C58 -> 389403.9 | G58: =VLOOKUP(A58,'July-A'!$B$10:$C$129,2,0) -> 601204.02 | H58: =+G58-E58 -> 0.34 | I58: =VLOOKUP(A58,'TB-A-Aug'!$B$10:$C$132,2,0) -> 601204.02 | J58: =+I58-G58 -> 0 | K58: =VLOOKUP(A58,'TFA-Sept,25'!$B$9:$C$136,2,0) -> 865612.81 | L58: =+K58-I58 -> 264408.79 | M58: =VLOOKUP(A58,'PL-TFA-Oct'!$B$9:$C$138,2,0) -> 1564521.1 | N58: =+M58-K58 -> 698908.33 | O58: =VLOOKUP(A58,'TFA-Nov,25'!$B$10:$C$144,2,0) -> 1664942.1 | P58: =+O58-M58 -> 100421 | Q58: =VLOOKUP(A58,'TB-TFL-A-Dec,25'!$B$10:$C$147,2,0) -> 2020313.7 | R58: =+Q58-O58 -> 355371.56 | S58: =VLOOKUP(A58,'TB-TFL-A-Jan,26'!$B$9:$C$151,2,0)+666598 -> 2686911.7 | T58: =+S58-Q58 -> 666598 | U58: =VLOOKUP(A58,'TB-Feb,26-a'!$B$10:$C$153,2,0) -> 2728363.2 | V58: =+U58-S58 -> 41451.48
A59: PURCHASE PACKING MATERIAL | K59: =VLOOKUP(A59,'TFA-Sept,25'!$B$9:$C$136,2,0) -> 40306.78 | L59: =+K59-I59 -> 40306.78 | M59: =VLOOKUP(A59,'PL-TFA-Oct'!$B$9:$C$138,2,0)+214188 -> 254494.78 | N59: =+M59-K59 -> 214188 | O59: =VLOOKUP(A59,'TFA-Nov,25'!$B$10:$C$144,2,0)+439535 -> 479841.78 | P59: =+O59-M59 -> 225347 | Q59: =VLOOKUP(A59,'TB-TFL-A-Dec,25'!$B$10:$C$147,2,0)+826887 -> 867193.78 | R59: =+Q59-O59 -> 387352 | S59: =VLOOKUP(A59,'TB-TFL-A-Jan,26'!$B$9:$C$151,2,0)+826887 -> 867193.78 | T59: =+S59-Q59 -> 0 | U59: =VLOOKUP(A59,'TB-Feb,26-a'!$B$10:$C$153,2,0)+1982383 -> 2022689.8 | V59: =+U59-S59 -> 1155496
A60: PURCHASE PACKING MATERIAL (GARMENT) | B60: =VLOOKUP(A60,'TFL A-April,25'!$B$9:$C$95,2,0)+1721211 -> 3621747.6 | C60: =VLOOKUP(A60,'May-A'!$B$10:$C$103,2,0)+150626 -> 9323779.6 | D60: =+C60-B60 -> 5702032 | E60: =VLOOKUP(A60,'June,25-A'!$B$10:$C$123,2,0)+386595 -> 12981156 | F60: =+E60-C60 -> 3657376.6 | G60: =VLOOKUP(A60,'July-A'!$B$10:$C$129,2,0)+1030649 -> 18489486 | H60: =+G60-E60 -> 5508330 | I60: =VLOOKUP(A60,'TB-A-Aug'!$B$10:$C$132,2,0)+1000186 -> 24958004 | J60: =+I60-G60 -> 6468518.1 | K60: =VLOOKUP(A60,'TFA-Sept,25'!$B$9:$C$136,2,0)+878343 -> 30061663 | L60: =+K60-I60 -> 5103658.4 | M60: =VLOOKUP(A60,'PL-TFA-Oct'!$B$9:$C$138,2,0)+1493297 -> 35530936 | N60: =+M60-K60 -> 5469273.6 | O60: =VLOOKUP(A60,'TFA-Nov,25'!$B$10:$C$144,2,0) -> 38947941 | P60: =+O60-M60 -> 3417005 | Q60: =VLOOKUP(A60,'TB-TFL-A-Dec,25'!$B$10:$C$147,2,0) -> 42673335 | R60: =+Q60-O60 -> 3725393.5 | S60: =VLOOKUP(A60,'TB-TFL-A-Jan,26'!$B$9:$C$151,2,0)+2213023-826887 -> 47951382 | T60: =+S60-Q60 -> 5278046.6 | U60: =VLOOKUP(A60,'TB-Feb,26-a'!$B$10:$C$153,2,0) -> 51707465 | V60: =+U60-S60 -> 3756083.6
A61: PURCHASE PACKING MATERIAL-(IMPORT) | B61: =VLOOKUP(A61,'TFL A-April,25'!$B$9:$C$95,2,0)+147781 -> 149392.31 | C61: =VLOOKUP(A61,'May-A'!$B$10:$C$103,2,0) -> 149392.18 | D61: =+C61-B61 -> -0.13 | E61: =VLOOKUP(A61,'June,25-A'!$B$10:$C$123,2,0) -> 261205.55 | F61: =+E61-C61 -> 111813.37 | G61: =VLOOKUP(A61,'July-A'!$B$10:$C$129,2,0) -> 261205.55 | H61: =+G61-E61 -> 0 | I61: =VLOOKUP(A61,'TB-A-Aug'!$B$10:$C$132,2,0)+879518 -> 1140723.6 | J61: =+I61-G61 -> 879518 | K61: =VLOOKUP(A61,'TFA-Sept,25'!$B$9:$C$136,2,0) -> 1183834.9 | L61: =+K61-I61 -> 43111.32 | M61: =VLOOKUP(A61,'PL-TFA-Oct'!$B$9:$C$138,2,0) -> 1316638.7 | N61: =+M61-K61 -> 132803.85 | O61: =VLOOKUP(A61,'TFA-Nov,25'!$B$10:$C$144,2,0) -> 2087500.6 | P61: =+O61-M61 -> 770861.86 | Q61: =VLOOKUP(A61,'TB-TFL-A-Dec,25'!$B$10:$C$147,2,0) -> 2744904.7 | R61: =+Q61-O61 -> 657404.16 | S61: =VLOOKUP(A61,'TB-TFL-A-Jan,26'!$B$9:$C$151,2,0) -> 2744904.7 | T61: =+S61-Q61 -> 0 | U61: =VLOOKUP(A61,'TB-Feb,26-a'!$B$10:$C$153,2,0) -> 2744904.7 | V61: =+U61-S61 -> 0
A62: PURCHASE - INTER UNIT TRANSACTION | D62: =+C62-B62 -> 0 | F62: =+E62-C62 -> 0 | H62: =+G62-E62 -> 0 | J62: =+I62-G62 -> 0 | L62: =+K62-I62 -> 0 | N62: =+M62-K62 -> 0 | P62: =+O62-M62 -> 0 | R62: =+Q62-O62 -> 0 | T62: =+S62-Q62 -> 0 | V62: =+U62-S62 -> 0
A63: PURCHASE (JOB WORK) - INTER UNIT | B63: =VLOOKUP(A63,'TFL A-April,25'!$B$9:$C$95,2,0) -> 1501872 | C63: =VLOOKUP(A63,'May-A'!$B$10:$C$103,2,0) -> 2501098 | D63: =+C63-B63 -> 999226 | E63: =VLOOKUP(A63,'June,25-A'!$B$10:$C$123,2,0) -> 5286179 | F63: =+E63-C63 -> 2785081 | G63: =VLOOKUP(A63,'July-A'!$B$10:$C$129,2,0) -> 9026583 | H63: =+G63-E63 -> 3740404 | I63: =VLOOKUP(A63,'TB-A-Aug'!$B$10:$C$132,2,0) -> 12193532 | J63: =+I63-G63 -> 3166949 | K63: =VLOOKUP(A63,'TFA-Sept,25'!$B$9:$C$136,2,0) -> 15382914 | L63: =+K63-I63 -> 3189382 | M63: =VLOOKUP(A63,'PL-TFA-Oct'!$B$9:$C$138,2,0) -> 16435708 | N63: =+M63-K63 -> 1052794 | O63: =VLOOKUP(A63,'TFA-Nov,25'!$B$10:$C$144,2,0) -> 18524580 | P63: =+O63-M63 -> 2088872 | Q63: =VLOOKUP(A63,'TB-TFL-A-Dec,25'!$B$10:$C$147,2,0) -> 21712831 | R63: =+Q63-O63 -> 3188251 | S63: =VLOOKUP(A63,'TB-TFL-A-Jan,26'!$B$9:$C$151,2,0) -> 25000388 | T63: =+S63-Q63 -> 3287557 | U63: =VLOOKUP(A63,'TB-Feb,26-a'!$B$10:$C$153,2,0) -> 27034065 | V63: =+U63-S63 -> 2033677
A64: PURCHASE FOR TRADING - (SCRAP) | G64: =VLOOKUP(A64,'July-A'!$B$10:$C$129,2,0)-20170 -> 0 | H64: =+G64-E64 -> 0 | I64: =VLOOKUP(A64,'TB-A-Aug'!$B$10:$C$132,2,0)-20170 -> 0 | J64: =+I64-G64 -> 0 | K64: =VLOOKUP(A64,'TFA-Sept,25'!$B$9:$C$136,2,0)-20170 -> 0 | L64: =+K64-I64 -> 0 | N64: =+M64-K64 -> 0 | P64: =+O64-M64 -> 0 | R64: =+Q64-O64 -> 0 | T64: =+S64-Q64 -> 0 | V64: =+U64-S64 -> 0
A65: COOLIE & CARTAGE ON PURCHASE | B65: =VLOOKUP(A65,'TFL A-April,25'!$B$9:$C$95,2,0) -> 2740 | C65: =VLOOKUP(A65,'May-A'!$B$10:$C$103,2,0) -> 11610 | D65: =+C65-B65 -> 8870 | E65: =VLOOKUP(A65,'June,25-A'!$B$10:$C$123,2,0) -> 100160 | F65: =+E65-C65 -> 88550 | G65: =VLOOKUP(A65,'July-A'!$B$10:$C$129,2,0) -> 109690 | H65: =+G65-E65 -> 9530 | I65: =VLOOKUP(A65,'TB-A-Aug'!$B$10:$C$132,2,0) -> 139690 | J65: =+I65-G65 -> 30000 | K65: =VLOOKUP(A65,'TFA-Sept,25'!$B$9:$C$136,2,0) -> 141130 | L65: =+K65-I65 -> 1440 | M65: =VLOOKUP(A65,'PL-TFA-Oct'!$B$9:$C$138,2,0) -> 145330 | N65: =+M65-K65 -> 4200 | O65: =VLOOKUP(A65,'TFA-Nov,25'!$B$10:$C$144,2,0) -> 145330 | P65: =+O65-M65 -> 0 | Q65: =VLOOKUP(A65,'TB-TFL-A-Dec,25'!$B$10:$C$147,2,0) -> 152770 | R65: =+Q65-O65 -> 7440 | S65: =VLOOKUP(A65,'TB-TFL-A-Jan,26'!$B$9:$C$151,2,0) -> 152770 | T65: =+S65-Q65 -> 0 | U65: =VLOOKUP(A65,'TB-Feb,26-a'!$B$10:$C$153,2,0) -> 152770 | V65: =+U65-S65 -> 0
A66: COOLIE & CARTAGE -PURCHASE -GARMENT | D66: =+C66-B66 -> 0 | F66: =+E66-C66 -> 0 | H66: =+G66-E66 -> 0 | J66: =+I66-G66 -> 0 | L66: =+K66-I66 -> 0 | N66: =+M66-K66 -> 0 | P66: =+O66-M66 -> 0 | R66: =+Q66-O66 -> 0 | T66: =+S66-Q66 -> 0 | V66: =+U66-S66 -> 0
A67: CLEARING CHARGES ON IMPORT | B67: =VLOOKUP(A67,'TFL A-April,25'!$B$9:$C$95,2,0) -> 31619 | C67: =VLOOKUP(A67,'May-A'!$B$10:$C$103,2,0) -> 34440 | D67: =+C67-B67 -> 2821 | E67: =VLOOKUP(A67,'June,25-A'!$B$10:$C$123,2,0) -> 314381.98 | F67: =+E67-C67 -> 279941.98 | G67: =VLOOKUP(A67,'July-A'!$B$10:$C$129,2,0) -> 324058.98 | H67: =+G67-E67 -> 9677 | I67: =VLOOKUP(A67,'TB-A-Aug'!$B$10:$C$132,2,0) -> 432611.98 | J67: =+I67-G67 -> 108553 | K67: =VLOOKUP(A67,'TFA-Sept,25'!$B$9:$C$136,2,0) -> 445689.98 | L67: =+K67-I67 -> 13078 | M67: =VLOOKUP(A67,'PL-TFA-Oct'!$B$9:$C$138,2,0) -> 559064.98 | N67: =+M67-K67 -> 113375 | O67: =VLOOKUP(A67,'TFA-Nov,25'!$B$10:$C$144,2,0) -> 581312.84 | P67: =+O67-M67 -> 22247.86 | Q67: =VLOOKUP(A67,'TB-TFL-A-Dec,25'!$B$10:$C$147,2,0) -> 603849.48 | R67: =+Q67-O67 -> 22536.64 | S67: =VLOOKUP(A67,'TB-TFL-A-Jan,26'!$B$9:$C$151,2,0) -> 639212.44 | T67: =+S67-Q67 -> 35362.96 | U67: =VLOOKUP(A67,'TB-Feb,26-a'!$B$10:$C$153,2,0) -> 701107.44 | V67: =+U67-S67 -> 61895
A68: CUSTOM DUTY ON IMPORT | B68: =VLOOKUP(A68,'TFL A-April,25'!$B$9:$C$95,2,0) -> 1857 | C68: =VLOOKUP(A68,'May-A'!$B$10:$C$103,2,0) -> 6454 | D68: =+C68-B68 -> 4597 | E68: =VLOOKUP(A68,'June,25-A'!$B$10:$C$123,2,0) -> 7937 | F68: =+E68-C68 -> 1483 | G68: =VLOOKUP(A68,'July-A'!$B$10:$C$129,2,0) -> 28237 | H68: =+G68-E68 -> 20300 | I68: =VLOOKUP(A68,'TB-A-Aug'!$B$10:$C$132,2,0) -> 110359 | J68: =+I68-G68 -> 82122 | K68: =VLOOKUP(A68,'TFA-Sept,25'!$B$9:$C$136,2,0) -> 112239 | L68: =+K68-I68 -> 1880 | M68: =VLOOKUP(A68,'PL-TFA-Oct'!$B$9:$C$138,2,0) -> 118941 | N68: =+M68-K68 -> 6702 | O68: =VLOOKUP(A68,'TFA-Nov,25'!$B$10:$C$144,2,0) -> 152321 | P68: =+O68-M68 -> 33380 | Q68: =VLOOKUP(A68,'TB-TFL-A-Dec,25'!$B$10:$C$147,2,0) -> 209507 | R68: =+Q68-O68 -> 57186 | S68: =VLOOKUP(A68,'TB-TFL-A-Jan,26'!$B$9:$C$151,2,0) -> 459679.5 | T68: =+S68-Q68 -> 250172.5 | U68: =VLOOKUP(A68,'TB-Feb,26-a'!$B$10:$C$153,2,0) -> 472048.5 | V68: =+U68-S68 -> 12369
A69: JOB WORK | B69: =VLOOKUP(A69,'TFL A-April,25'!$B$9:$C$95,2,0)+1309189 -> 2021221.8 | C69: =VLOOKUP(A69,'May-A'!$B$10:$C$103,2,0)+954522 -> 2841923.8 | D69: =+C69-B69 -> 820702 | E69: =VLOOKUP(A69,'June,25-A'!$B$10:$C$123,2,0)+97561 -> 3962292.2 | F69: =+E69-C69 -> 1120368.4 | G69: =VLOOKUP(A69,'July-A'!$B$10:$C$129,2,0)+214820 -> 7942144.6 | H69: =+G69-E69 -> 3979852.4 | I69: =VLOOKUP(A69,'TB-A-Aug'!$B$10:$C$132,2,0)+1601777 -> 10354344 | J69: =+I69-G69 -> 2412198.9 | K69: =VLOOKUP(A69,'TFA-Sept,25'!$B$9:$C$136,2,0)+1901970 -> 13260813 | L69: =+K69-I69 -> 2906469.5 | M69: =VLOOKUP(A69,'PL-TFA-Oct'!$B$9:$C$138,2,0)+6887905 -> 19834441 | N69: =+M69-K69 -> 6573628 | O69: =VLOOKUP(A69,'TFA-Nov,25'!$B$10:$C$144,2,0)+630146 -> 21276764 | P69: =+O69-M69 -> 1442323.1 | Q69: =VLOOKUP(A69,'TB-TFL-A-Dec,25'!$B$10:$C$147,2,0)+1059392.29 -> 22496109 | R69: =+Q69-O69 -> 1219344.7 | S69: =VLOOKUP(A69,'TB-TFL-A-Jan,26'!$B$9:$C$151,2,0)+1029263 -> 23705684 | T69: =+S69-Q69 -> 1209575.4 | U69: =VLOOKUP(A69,'TB-Feb,26-a'!$B$10:$C$153,2,0)+957203 -> 25013475 | V69: =+U69-S69 -> 1307791
A70: CLOSING STOCK | B70: =156407453-583066 -> 155824387 | C70: 160389511 | D70: =+C70-B70 -> 4565124 | E70: =163927851-671047 -> 163256804 | F70: =+E70-C70 -> 2867293 | G70: =159308762-841953.9 -> 1.5846681e+08 | H70: =+G70-E70 -> -4789995.9 | I70: =153758777.844-1480923.7 -> 1.5227785e+08 | J70: =+I70-G70 -> -6188954 | K70: =162256495-826333 -> 161430162 | L70: =+K70-I70 -> 9152307.9 | M70: =170221642+M85-1283549 -> 167843857 | N70: =+M70-K70 -> 6413695 | O70: =183418960+O85 -> 182285500 | P70: =+O70-M70 -> 14441643 | Q70: =171871280+Q85 -> 170675054 | R70: =+Q70-O70 -> -11610446 | S70: =189652766.493848+S85 -> 1.8851891e+08 | T70: =+S70-Q70 -> 17843851 | U70: =170627607+U85 -> 169525758 | V70: =+U70-S70 -> -18993147
A71: TOTAL COST OF GOODS SOLD | B71: =SUM(B50:B69)-B70 -> 41072511 | C71: =SUM(C50:C69)-C70 -> 97292996 | D71: =SUM(D50:D69)-D70 -> 56220486 | E71: =SUM(E50:E69)-E70 -> 1.5454615e+08 | F71: =SUM(F50:F69)-F70 -> 57253151 | G71: =SUM(G50:G69)-G70 -> 2.2443049e+08 | H71: =SUM(H50:H69)-H70 -> 69884338 | I71: =SUM(I50:I69)-I70 -> 2.8792177e+08 | ... V71: =SUM(V50:V69)-V70 -> 87528452
A72: THROUGHPUT | B72: =B46-B71 -> 8547051.8 | C72: =C46-C71 -> 16579173 | D72: =D46-D71 -> 8032121.6 | E72: =E46-E71 -> 15970585 | F72: =F46-F71 -> -608588.46 | G72: =G46-G71 -> 36500231 | H72: =H46-H71 -> 20529646 | I72: =I46-I71 -> 36217391 | ... V72: =V46-V71 -> 2459700.7
A73: Throughput as % of Revenue from operations | B73: =+B72/B46 -> 0.17225166 | C73: =+C72/C46 -> 0.1455946 | D73: =+D72/D46 -> 0.12500849 | E73: =+E72/E46 -> 0.093659929 | F73: =+F72/F46 -> -0.010743987 | G73: =+G72/G46 -> 0.13988476 | H73: =+H72/H46 -> 0.22706273 | I73: =+I72/I46 -> 0.11173408 | ... V73: =+V72/V46 -> 0.027333606
A74: FIXED EXPENSES
A75: JEEP HIRE EXPENSES | B75: 81942 | C75: =VLOOKUP(A75,'May-A'!$B$10:$C$103,2,0) -> 163613 | D75: =+C75-B75 -> 81671 | E75: =VLOOKUP(A75,'June,25-A'!$B$10:$C$123,2,0)+97561 -> 261174 | F75: =+E75-C75 -> 97561 | G75: =VLOOKUP(A75,'July-A'!$B$10:$C$129,2,0)+97478 -> 358569.5 | H75: =+G75-E75 -> 97395.5 | I75: =VLOOKUP(A75,'TB-A-Aug'!$B$10:$C$132,2,0) -> 460433 | J75: =+I75-G75 -> 101863.5 | K75: =VLOOKUP(A75,'TFA-Sept,25'!$B$9:$C$136,2,0)+97478 -> 557911 | L75: =+K75-I75 -> 97478 | M75: =VLOOKUP(A75,'PL-TFA-Oct'!$B$9:$C$138,2,0) -> 714506 | N75: =+M75-K75 -> 156595 | O75: =VLOOKUP(A75,'TFA-Nov,25'!$B$10:$C$144,2,0) -> 926292 | P75: =+O75-M75 -> 211786 | Q75: =VLOOKUP(A75,'TB-TFL-A-Dec,25'!$B$10:$C$147,2,0)+255263 -> 1181555 | R75: =+Q75-O75 -> 255263 | S75: =VLOOKUP(A75,'TB-TFL-A-Jan,26'!$B$9:$C$151,2,0) -> 1347273.5 | T75: =+S75-Q75 -> 165718.5 | U75: =VLOOKUP(A75,'TB-Feb,26-a'!$B$10:$C$153,2,0)+165000 -> 1512273.5 | V75: =+U75-S75 -> 165000
A76: CRANE HIRE CHARGES | B76: =VLOOKUP(A76,'TFL A-April,25'!$B$9:$C$95,2,0) -> 5775 | C76: =VLOOKUP(A76,'May-A'!$B$10:$C$103,2,0) -> 5775 | D76: =+C76-B76 -> 0 | E76: =VLOOKUP(A76,'June,25-A'!$B$10:$C$123,2,0) -> 5775 | F76: =+E76-C76 -> 0 | G76: =VLOOKUP(A76,'July-A'!$B$10:$C$129,2,0) -> 5775 | H76: =+G76-E76 -> 0 | I76: =VLOOKUP(A76,'TB-A-Aug'!$B$10:$C$132,2,0) -> 5775 | J76: =+I76-G76 -> 0 | K76: =VLOOKUP(A76,'TFA-Sept,25'!$B$9:$C$136,2,0) -> 5775 | L76: =+K76-I76 -> 0 | M76: =VLOOKUP(A76,'PL-TFA-Oct'!$B$9:$C$138,2,0) -> 5775 | N76: =+M76-K76 -> 0 | O76: =VLOOKUP(A76,'TFA-Nov,25'!$B$10:$C$144,2,0) -> 5775 | P76: =+O76-M76 -> 0 | Q76: =VLOOKUP(A76,'TB-TFL-A-Dec,25'!$B$10:$C$147,2,0) -> 5775 | R76: =+Q76-O76 -> 0 | S76: =VLOOKUP(A76,'TB-TFL-A-Jan,26'!$B$9:$C$151,2,0) -> 5775 | T76: =+S76-Q76 -> 0 | U76: =VLOOKUP(A76,'TB-Feb,26-a'!$B$10:$C$153,2,0) -> 5775 | V76: =+U76-S76 -> 0
A77: PURCHASE STORES & SPARES | C77: =VLOOKUP(A77,'May-A'!$B$10:$C$103,2,0) -> 44156 | D77: =+C77-B77 -> 44156 | E77: =VLOOKUP(A77,'June,25-A'!$B$10:$C$123,2,0) -> 51481 | F77: =+E77-C77 -> 7325 | G77: =VLOOKUP(A77,'July-A'!$B$10:$C$129,2,0) -> 67930 | H77: =+G77-E77 -> 16449 | I77: =VLOOKUP(A77,'TB-A-Aug'!$B$10:$C$132,2,0) -> 91530 | J77: =+I77-G77 -> 23600 | K77: =VLOOKUP(A77,'TFA-Sept,25'!$B$9:$C$136,2,0) -> 112236.22 | L77: =+K77-I77 -> 20706.22 | M77: =VLOOKUP(A77,'PL-TFA-Oct'!$B$9:$C$138,2,0)+154304 -> 282891.22 | N77: =+M77-K77 -> 170655 | O77: =VLOOKUP(A77,'TFA-Nov,25'!$B$10:$C$144,2,0)+209689 -> 352598.22 | P77: =+O77-M77 -> 69707 | Q77: =VLOOKUP(A77,'TB-TFL-A-Dec,25'!$B$10:$C$147,2,0)+376112 -> 529427.22 | R77: =+Q77-O77 -> 176829 | S77: =VLOOKUP(A77,'TB-TFL-A-Jan,26'!$B$9:$C$151,2,0)+372378 -> 529427.22 | T77: =+S77-Q77 -> 0 | U77: =VLOOKUP(A77,'TB-Feb,26-a'!$B$10:$C$153,2,0)+523491 -> 685459.22 | V77: =+U77-S77 -> 156032
A78: PURCHASE STORES & SPARES (GARMENT) | B78: =VLOOKUP(A78,'TFL A-April,25'!$B$9:$C$95,2,0)+271938 -> 661568.86 | C78: =VLOOKUP(A78,'May-A'!$B$10:$C$103,2,0)+237941 -> 1376215 | D78: =+C78-B78 -> 714646.14 | E78: =VLOOKUP(A78,'June,25-A'!$B$10:$C$123,2,0)+389240 -> 2001182.2 | F78: =+E78-C78 -> 624967.16 | G78: =VLOOKUP(A78,'July-A'!$B$10:$C$129,2,0)+555818 -> 2347243.4 | H78: =+G78-E78 -> 346061.22 | I78: =VLOOKUP(A78,'TB-A-Aug'!$B$10:$C$132,2,0)+486465.56 -> 2703610.7 | J78: =+I78-G78 -> 356367.32 | K78: =VLOOKUP(A78,'TFA-Sept,25'!$B$9:$C$136,2,0)+187939 -> 3051851.1 | L78: =+K78-I78 -> 348240.44 | M78: =VLOOKUP(A78,'PL-TFA-Oct'!$B$9:$C$138,2,0) -> 3094182.7 | N78: =+M78-K78 -> 42331.54 | O78: =VLOOKUP(A78,'TFA-Nov,25'!$B$10:$C$144,2,0) -> 3354516.6 | P78: =+O78-M78 -> 260333.89 | Q78: =VLOOKUP(A78,'TB-TFL-A-Dec,25'!$B$10:$C$147,2,0) -> 3569621.2 | R78: =+Q78-O78 -> 215104.62 | S78: =VLOOKUP(A78,'TB-TFL-A-Jan,26'!$B$9:$C$151,2,0)+611912-372378 -> 3988477.6 | T78: =+S78-Q78 -> 418856.38 | U78: =VLOOKUP(A78,'TB-Feb,26-a'!$B$10:$C$153,2,0) -> 4127708.8 | V78: =+U78-S78 -> 139231.18
A79: ADVERTISEMENT EXPENSE | D79: =+C79-B79 -> 0 | E79: =VLOOKUP(A79,'June,25-A'!$B$10:$C$123,2,0) -> 1145 | F79: =+E79-C79 -> 1145 | G79: =VLOOKUP(A79,'July-A'!$B$10:$C$129,2,0) -> 1145 | H79: =+G79-E79 -> 0 | I79: =VLOOKUP(A79,'TB-A-Aug'!$B$10:$C$132,2,0) -> 1145 | J79: =+I79-G79 -> 0 | K79: =VLOOKUP(A79,'TFA-Sept,25'!$B$9:$C$136,2,0) -> 1145 | L79: =+K79-I79 -> 0 | M79: =VLOOKUP(A79,'PL-TFA-Oct'!$B$9:$C$138,2,0) -> 2290 | N79: =+M79-K79 -> 1145 | O79: =VLOOKUP(A79,'TFA-Nov,25'!$B$10:$C$144,2,0) -> 2290 | P79: =+O79-M79 -> 0 | Q79: =VLOOKUP(A79,'TB-TFL-A-Dec,25'!$B$10:$C$147,2,0) -> 2290 | R79: =+Q79-O79 -> 0 | S79: =VLOOKUP(A79,'TB-TFL-A-Jan,26'!$B$9:$C$151,2,0) -> 2290 | T79: =+S79-Q79 -> 0 | U79: =VLOOKUP(A79,'TB-Feb,26-a'!$B$10:$C$153,2,0) -> 2290 | V79: =+U79-S79 -> 0
A80: PURCHASE STORE & SPARES (FABRIC) | D80: =+C80-B80 -> 0 | F80: =+E80-C80 -> 0 | G80: =VLOOKUP(A80,'July-A'!$B$10:$C$129,2,0) -> 8825 | H80: =+G80-E80 -> 8825 | I80: =VLOOKUP(A80,'TB-A-Aug'!$B$10:$C$132,2,0) -> 8825 | J80: =+I80-G80 -> 0 | K80: =VLOOKUP(A80,'TFA-Sept,25'!$B$9:$C$136,2,0) -> 21784.8 | L80: =+K80-I80 -> 12959.8 | M80: =VLOOKUP(A80,'PL-TFA-Oct'!$B$9:$C$138,2,0) -> 21784.8 | N80: =+M80-K80 -> 0 | O80: =VLOOKUP(A80,'TFA-Nov,25'!$B$10:$C$144,2,0) -> 21784.8 | P80: =+O80-M80 -> 0 | Q80: =VLOOKUP(A80,'TB-TFL-A-Dec,25'!$B$10:$C$147,2,0) -> 21784.8 | R80: =+Q80-O80 -> 0 | S80: =VLOOKUP(A80,'TB-TFL-A-Jan,26'!$B$9:$C$151,2,0) -> 21784.8 | T80: =+S80-Q80 -> 0 | U80: =VLOOKUP(A80,'TB-Feb,26-a'!$B$10:$C$153,2,0) -> 21784.8 | V80: =+U80-S80 -> 0
A81: DETENTION CHARGES ON IMPORT | S81: =VLOOKUP(A81,'TB-TFL-A-Jan,26'!$B$9:$C$151,2,0) -> 1817 | T81: =+S81-Q81 -> 1817 | U81: =VLOOKUP(A81,'TB-Feb,26-a'!$B$10:$C$153,2,0) -> 1817 | V81: =+U81-S81 -> 0
A82: POWER | B82: =VLOOKUP(A82,'TFL A-April,25'!$B$9:$C$95,2,0) -> -1100 | C82: =VLOOKUP(A82,'May-A'!$B$10:$C$103,2,0) -> -1670 | D82: =+C82-B82 -> -570 | E82: =VLOOKUP(A82,'June,25-A'!$B$10:$C$123,2,0) -> -2260 | F82: =+E82-C82 -> -590 | G82: =VLOOKUP(A82,'July-A'!$B$10:$C$129,2,0) -> -3110 | H82: =+G82-E82 -> -850 | I82: =VLOOKUP(A82,'TB-A-Aug'!$B$10:$C$132,2,0) -> -4140 | J82: =+I82-G82 -> -1030 | K82: =VLOOKUP(A82,'TFA-Sept,25'!$B$9:$C$136,2,0) -> -5020 | L82: =+K82-I82 -> -880 | M82: =VLOOKUP(A82,'PL-TFA-Oct'!$B$9:$C$138,2,0) -> -6020 | N82: =+M82-K82 -> -1000 | O82: =VLOOKUP(A82,'TFA-Nov,25'!$B$10:$C$144,2,0) -> -6020 | P82: =+O82-M82 -> 0 | Q82: =VLOOKUP(A82,'TB-TFL-A-Dec,25'!$B$10:$C$147,2,0)+120000 -> 231120 | R82: =+Q82-O82 -> 237140 | S82: =VLOOKUP(A82,'TB-TFL-A-Jan,26'!$B$9:$C$151,2,0)+120000 -> 351120 | T82: =+S82-Q82 -> 120000 | U82: =VLOOKUP(A82,'TB-Feb,26-a'!$B$10:$C$153,2,0)+103410 -> 444490 | V82: =+U82-S82 -> 93370
A83: INSPECTION/TESTING | B83: =VLOOKUP(A83,'TFL A-April,25'!$B$9:$C$95,2,0)+25400 -> 154906.9 | C83: =VLOOKUP(A83,'May-A'!$B$10:$C$103,2,0) -> 448759.9 | D83: =+C83-B83 -> 293853 | E83: =VLOOKUP(A83,'June,25-A'!$B$10:$C$123,2,0) -> 559200.9 | F83: =+E83-C83 -> 110441 | G83: =VLOOKUP(A83,'July-A'!$B$10:$C$129,2,0)+16650 -> 789858.5 | H83: =+G83-E83 -> 230657.6 | I83: =VLOOKUP(A83,'TB-A-Aug'!$B$10:$C$132,2,0)+81766 -> 954250.7 | J83: =+I83-G83 -> 164392.2 | K83: =VLOOKUP(A83,'TFA-Sept,25'!$B$9:$C$136,2,0)+16650+26384 -> 1251679.7 | L83: =+K83-I83 -> 297429.03 | M83: =VLOOKUP(A83,'PL-TFA-Oct'!$B$9:$C$138,2,0) -> 1683085.6 | N83: =+M83-K83 -> 431405.85 | O83: =VLOOKUP(A83,'TFA-Nov,25'!$B$10:$C$144,2,0) -> 1939596.4 | P83: =+O83-M83 -> 256510.87 | Q83: =VLOOKUP(A83,'TB-TFL-A-Dec,25'!$B$10:$C$147,2,0) -> 2017706.4 | R83: =+Q83-O83 -> 78110 | S83: =VLOOKUP(A83,'TB-TFL-A-Jan,26'!$B$9:$C$151,2,0)+14385 -> 2282203.2 | T83: =+S83-Q83 -> 264496.8 | U83: =VLOOKUP(A83,'TB-Feb,26-a'!$B$10:$C$153,2,0) -> 2398712.2 | V83: =+U83-S83 -> 116509
A84: Opening Stock of Electrical Item | B84: 564066 | C84: =+B84 -> 564066 | D84: =+C84-B84 -> 0 | E84: =+C84 -> 564066 | F84: =+E84-C84 -> 0 | G84: =+E84 -> 564066 | H84: =+G84-E84 -> 0 | I84: =+G84 -> 564066 | J84: =+I84-G84 -> 0 | K84: =+I84 -> 564066 | L84: =+K84-I84 -> 0 | M84: =+K84 -> 564066 | N84: =+M84-K84 -> 0 | O84: =+M84 -> 564066 | P84: =+O84-M84 -> 0 | Q84: =+O84 -> 564066 | R84: =+Q84-O84 -> 0 | S84: =+Q84 -> 564066 | T84: =+S84-Q84 -> 0 | U84: =+S84 -> 564066 | V84: =+U84-S84 -> 0
A85: Closing Stock of Electrical Item | B85: -583066 | C85: 0 | D85: =+C85-B85 -> 583066 | E85: -671047 | F85: =+E85-C85 -> -671047 | G85: -841953.5 | H85: =+G85-E85 -> -170906.5 | I85: -1480923.7 | J85: =+I85-G85 -> -638970.2 | K85: -826333 | L85: =+K85-I85 -> 654590.7 | M85: =-863731-230505 -> -1094236 | N85: =+M85-K85 -> -267903 | O85: =-(778907+354553) -> -1133460 | P85: =+O85-M85 -> -39224 | Q85: =-(1157029+39197) -> -1196226 | R85: =+Q85-O85 -> -62766 | S85: =-1060395-73466 -> -1133861 | T85: =+S85-Q85 -> 62365 | U85: =-(999950+101899) -> -1101849 | V85: =+U85-S85 -> 32012
A86: FUEL & OIL | D86: =+C86-B86 -> 0 | F86: =+E86-C86 -> 0 | H86: =+G86-E86 -> 0 | J86: =+I86-G86 -> 0 | K86: =VLOOKUP(A86,'TFA-Sept,25'!$B$9:$C$136,2,0) -> 5075 | L86: =+K86-I86 -> 5075 | M86: =VLOOKUP(A86,'PL-TFA-Oct'!$B$9:$C$138,2,0) -> 5075 | N86: =+M86-K86 -> 0 | O86: =VLOOKUP(A86,'TFA-Nov,25'!$B$10:$C$144,2,0) -> 8757.24 | P86: =+O86-M86 -> 3682.24 | Q86: =VLOOKUP(A86,'TB-TFL-A-Dec,25'!$B$10:$C$147,2,0) -> 8757.24 | R86: =+Q86-O86 -> 0 | S86: =VLOOKUP(A86,'TB-TFL-A-Jan,26'!$B$9:$C$151,2,0) -> 8757.24 | T86: =+S86-Q86 -> 0 | U86: =VLOOKUP(A86,'TB-Feb,26-a'!$B$10:$C$153,2,0) -> 8757.24 | V86: =+U86-S86 -> 0
A87: ELECTRICAL ITEMS | B87: =VLOOKUP(A87,'TFL A-April,25'!$B$9:$C$95,2,0) -> 5020.4 | C87: =VLOOKUP(A87,'May-A'!$B$10:$C$103,2,0) -> 5020.4 | D87: =+C87-B87 -> 0 | E87: =VLOOKUP(A87,'June,25-A'!$B$10:$C$123,2,0) -> 10511.88 | F87: =+E87-C87 -> 5491.48 | G87: =VLOOKUP(A87,'July-A'!$B$10:$C$129,2,0)+26382 -> 36893.88 | H87: =+G87-E87 -> 26382 | I87: =VLOOKUP(A87,'TB-A-Aug'!$B$10:$C$132,2,0) -> 10511.88 | J87: =+I87-G87 -> -26382 | K87: =VLOOKUP(A87,'TFA-Sept,25'!$B$9:$C$136,2,0) -> 13011.88 | L87: =+K87-I87 -> 2500 | M87: =VLOOKUP(A87,'PL-TFA-Oct'!$B$9:$C$138,2,0) -> 13011.88 | N87: =+M87-K87 -> 0 | O87: =VLOOKUP(A87,'TFA-Nov,25'!$B$10:$C$144,2,0) -> 13011.88 | P87: =+O87-M87 -> 0 | Q87: =VLOOKUP(A87,'TB-TFL-A-Dec,25'!$B$10:$C$147,2,0) -> 39393.88 | R87: =+Q87-O87 -> 26382 | S87: =VLOOKUP(A87,'TB-TFL-A-Jan,26'!$B$9:$C$151,2,0) -> 39393.88 | T87: =+S87-Q87 -> 0 | U87: =VLOOKUP(A87,'TB-Feb,26-a'!$B$10:$C$153,2,0) -> 39393.88 | V87: =+U87-S87 -> 0
A88: ELECTRICAL ITEM - GARMENT | B88: =VLOOKUP(A88,'TFL A-April,25'!$B$9:$C$95,2,0) -> 59130.6 | C88: =VLOOKUP(A88,'May-A'!$B$10:$C$103,2,0) -> 373364.48 | D88: =+C88-B88 -> 314233.88 | E88: =VLOOKUP(A88,'June,25-A'!$B$10:$C$123,2,0)+3080 -> 428677.54 | F88: =+E88-C88 -> 55313.06 | G88: =VLOOKUP(A88,'July-A'!$B$10:$C$129,2,0) -> 470977.14 | H88: =+G88-E88 -> 42299.6 | I88: =VLOOKUP(A88,'TB-A-Aug'!$B$10:$C$132,2,0) -> 500499.18 | J88: =+I88-G88 -> 29522.04 | K88: =VLOOKUP(A88,'TFA-Sept,25'!$B$9:$C$136,2,0) -> 518256.82 | L88: =+K88-I88 -> 17757.64 | M88: =VLOOKUP(A88,'PL-TFA-Oct'!$B$9:$C$138,2,0) -> 518256.82 | N88: =+M88-K88 -> 0 | O88: =VLOOKUP(A88,'TFA-Nov,25'!$B$10:$C$144,2,0) -> 523880.5 | P88: =+O88-M88 -> 5623.68 | Q88: =VLOOKUP(A88,'TB-TFL-A-Dec,25'!$B$10:$C$147,2,0) -> 602137.82 | R88: =+Q88-O88 -> 78257.32 | S88: =VLOOKUP(A88,'TB-TFL-A-Jan,26'!$B$9:$C$151,2,0) -> 675450.3 | T88: =+S88-Q88 -> 73312.48 | U88: =VLOOKUP(A88,'TB-Feb,26-a'!$B$10:$C$153,2,0)+25711 -> 716961.3 | V88: =+U88-S88 -> 41511
A89: WATER CHARGES | B89: =VLOOKUP(A89,'TFL A-April,25'!$B$9:$C$95,2,0) -> 510 | C89: =VLOOKUP(A89,'May-A'!$B$10:$C$103,2,0) -> 1198 | D89: =+C89-B89 -> 688 | E89: =VLOOKUP(A89,'June,25-A'!$B$10:$C$123,2,0) -> 1198 | F89: =+E89-C89 -> 0 | G89: =VLOOKUP(A89,'July-A'!$B$10:$C$129,2,0) -> 1198 | H89: =+G89-E89 -> 0 | I89: =VLOOKUP(A89,'TB-A-Aug'!$B$10:$C$132,2,0) -> 1198 | J89: =+I89-G89 -> 0 | K89: =VLOOKUP(A89,'TFA-Sept,25'!$B$9:$C$136,2,0) -> 1198 | L89: =+K89-I89 -> 0 | M89: =VLOOKUP(A89,'PL-TFA-Oct'!$B$9:$C$138,2,0) -> 1198 | N89: =+M89-K89 -> 0 | O89: =VLOOKUP(A89,'TFA-Nov,25'!$B$10:$C$144,2,0) -> 1198 | P89: =+O89-M89 -> 0 | Q89: =VLOOKUP(A89,'TB-TFL-A-Dec,25'!$B$10:$C$147,2,0) -> 1198 | R89: =+Q89-O89 -> 0 | S89: =VLOOKUP(A89,'TB-TFL-A-Jan,26'!$B$9:$C$151,2,0) -> 2198 | T89: =+S89-Q89 -> 1000 | U89: =VLOOKUP(A89,'TB-Feb,26-a'!$B$10:$C$153,2,0) -> 2698 | V89: =+U89-S89 -> 500
A90: LABOUR CHARGES | B90: =VLOOKUP(A90,'TFL A-April,25'!$B$9:$C$95,2,0) -> 149230.46 | C90: =VLOOKUP(A90,'May-A'!$B$10:$C$103,2,0) -> 177400.46 | D90: =+C90-B90 -> 28170 | E90: =VLOOKUP(A90,'June,25-A'!$B$10:$C$123,2,0) -> 554755.46 | F90: =+E90-C90 -> 377355 | G90: =VLOOKUP(A90,'July-A'!$B$10:$C$129,2,0) -> 698450.46 | H90: =+G90-E90 -> 143695 | I90: =VLOOKUP(A90,'TB-A-Aug'!$B$10:$C$132,2,0) -> 698750.46 | J90: =+I90-G90 -> 300 | K90: =VLOOKUP(A90,'TFA-Sept,25'!$B$9:$C$136,2,0) -> 709950.46 | L90: =+K90-I90 -> 11200 | M90: =VLOOKUP(A90,'PL-TFA-Oct'!$B$9:$C$138,2,0) -> 709950.46 | N90: =+M90-K90 -> 0 | O90: =VLOOKUP(A90,'TFA-Nov,25'!$B$10:$C$144,2,0) -> 709950.46 | P90: =+O90-M90 -> 0 | Q90: =VLOOKUP(A90,'TB-TFL-A-Dec,25'!$B$10:$C$147,2,0) -> 709950.46 | R90: =+Q90-O90 -> 0 | S90: =VLOOKUP(A90,'TB-TFL-A-Jan,26'!$B$9:$C$151,2,0) -> 709950.46 | T90: =+S90-Q90 -> 0 | U90: =VLOOKUP(A90,'TB-Feb,26-a'!$B$10:$C$153,2,0) -> 730200.46 | V90: =+U90-S90 -> 20250
A91: LABORATORY EXPENSES | I91: =VLOOKUP(A91,'TB-A-Aug'!$B$10:$C$132,2,0) -> 13353.84 | J91: =+I91-G91 -> 13353.84 | K91: =VLOOKUP(A91,'TFA-Sept,25'!$B$9:$C$136,2,0) -> 33513.84 | L91: =+K91-I91 -> 20160 | M91: =VLOOKUP(A91,'PL-TFA-Oct'!$B$9:$C$138,2,0) -> 33513.84 | N91: =+M91-K91 -> 0 | O91: =VLOOKUP(A91,'TFA-Nov,25'!$B$10:$C$144,2,0) -> 33513.84 | P91: =+O91-M91 -> 0 | Q91: =VLOOKUP(A91,'TB-TFL-A-Dec,25'!$B$10:$C$147,2,0) -> 33513.84 | R91: =+Q91-O91 -> 0 | S91: =VLOOKUP(A91,'TB-TFL-A-Jan,26'!$B$9:$C$151,2,0) -> 33513.84 | T91: =+S91-Q91 -> 0 | U91: =VLOOKUP(A91,'TB-Feb,26-a'!$B$10:$C$153,2,0) -> 33513.84 | V91: =+U91-S91 -> 0
A92: GARDEN EXPENSES | D92: =+C92-B92 -> 0 | E92: =VLOOKUP(A92,'June,25-A'!$B$10:$C$123,2,0) -> 5550 | F92: =+E92-C92 -> 5550 | G92: =VLOOKUP(A92,'July-A'!$B$10:$C$129,2,0) -> 5550 | H92: =+G92-E92 -> 0 | I92: =VLOOKUP(A92,'TB-A-Aug'!$B$10:$C$132,2,0) -> 5550 | J92: =+I92-G92 -> 0 | K92: =VLOOKUP(A92,'TFA-Sept,25'!$B$9:$C$136,2,0) -> 5550 | L92: =+K92-I92 -> 0 | M92: =VLOOKUP(A92,'PL-TFA-Oct'!$B$9:$C$138,2,0) -> 5550 | N92: =+M92-K92 -> 0 | O92: =VLOOKUP(A92,'TFA-Nov,25'!$B$10:$C$144,2,0) -> 14700 | P92: =+O92-M92 -> 9150 | Q92: =VLOOKUP(A92,'TB-TFL-A-Dec,25'!$B$10:$C$147,2,0) -> 15080 | R92: =+Q92-O92 -> 380 | S92: =VLOOKUP(A92,'TB-TFL-A-Jan,26'!$B$9:$C$151,2,0) -> 16050 | T92: =+S92-Q92 -> 970 | U92: =VLOOKUP(A92,'TB-Feb,26-a'!$B$10:$C$153,2,0) -> 22660 | V92: =+U92-S92 -> 6610
A93: INSURANCE (GENERAL) | D93: =+C93-B93 -> 0 | E93: =VLOOKUP(A93,'June,25-A'!$B$10:$C$123,2,0)-Prepaid!F8 -> 94474.5 | F93: =+E93-C93 -> 94474.5 | G93: =VLOOKUP(A93,'July-A'!$B$10:$C$129,2,0)-Prepaid!G8 -> 117211.33 | H93: =+G93-E93 -> 22736.833 | I93: =VLOOKUP(A93,'TB-A-Aug'!$B$10:$C$132,2,0)-Prepaid!H8 -> 179078.17 | J93: =+I93-G93 -> 61866.833 | K93: =VLOOKUP(A93,'TFA-Sept,25'!$B$9:$C$136,2,0)-Prepaid!I8 -> 201815 | L93: =+K93-I93 -> 22736.833 | M93: =VLOOKUP(A93,'PL-TFA-Oct'!$B$9:$C$138,2,0)-Prepaid!J8 -> 224551.83 | N93: =+M93-K93 -> 22736.833 | O93: =VLOOKUP(A93,'TFA-Nov,25'!$B$10:$C$144,2,0)-Prepaid!K8 -> 247288.67 | P93: =+O93-M93 -> 22736.833 | Q93: =VLOOKUP(A93,'TB-TFL-A-Dec,25'!$B$10:$C$147,2,0)-Prepaid!L8 -> 270025.5 | R93: =+Q93-O93 -> 22736.833 | S93: =VLOOKUP(A93,'TB-TFL-A-Jan,26'!$B$9:$C$151,2,0)-Prepaid!M8 -> 292762.33 | T93: =+S93-Q93 -> 22736.833 | U93: =VLOOKUP(A93,'TB-Feb,26-a'!$B$10:$C$153,2,0)-Prepaid!N8 -> 351373.17 | V93: =+U93-S93 -> 58610.833
A94: SECURITY CHARGES | B94: =VLOOKUP(A94,'TFL A-April,25'!$B$9:$C$95,2,0) -> 39267 | C94: =VLOOKUP(A94,'May-A'!$B$10:$C$103,2,0) -> 77880 | D94: =+C94-B94 -> 38613 | E94: =VLOOKUP(A94,'June,25-A'!$B$10:$C$123,2,0)+46335 -> 124215 | F94: =+E94-C94 -> 46335 | G94: =VLOOKUP(A94,'July-A'!$B$10:$C$129,2,0)+46335-46335 -> 107013 | H94: =+G94-E94 -> -17202 | I94: =VLOOKUP(A94,'TB-A-Aug'!$B$10:$C$132,2,0) -> 121336 | J94: =+I94-G94 -> 14323 | K94: =VLOOKUP(A94,'TFA-Sept,25'!$B$9:$C$136,2,0) -> 121336 | L94: =+K94-I94 -> 0 | M94: =VLOOKUP(A94,'PL-TFA-Oct'!$B$9:$C$138,2,0) -> 121336 | N94: =+M94-K94 -> 0 | O94: =VLOOKUP(A94,'TFA-Nov,25'!$B$10:$C$144,2,0) -> 121336 | P94: =+O94-M94 -> 0 | Q94: =VLOOKUP(A94,'TB-TFL-A-Dec,25'!$B$10:$C$147,2,0) -> 121336 | R94: =+Q94-O94 -> 0 | S94: =VLOOKUP(A94,'TB-TFL-A-Jan,26'!$B$9:$C$151,2,0) -> 121336 | T94: =+S94-Q94 -> 0 | U94: =VLOOKUP(A94,'TB-Feb,26-a'!$B$10:$C$153,2,0) -> 121336 | V94: =+U94-S94 -> 0
A95: PRINTING & STATIONERY | B95: =VLOOKUP(A95,'TFL A-April,25'!$B$9:$C$95,2,0)+65486 -> 125618.86 | C95: =VLOOKUP(A95,'May-A'!$B$10:$C$103,2,0)+48391 -> 154895.42 | D95: =+C95-B95 -> 29276.56 | E95: =VLOOKUP(A95,'June,25-A'!$B$10:$C$123,2,0)+65681 -> 181047.62 | F95: =+E95-C95 -> 26152.2 | G95: =VLOOKUP(A95,'July-A'!$B$10:$C$129,2,0)+45519 -> 290889.78 | H95: =+G95-E95 -> 109842.16 | I95: =VLOOKUP(A95,'TB-A-Aug'!$B$10:$C$132,2,0)+10937 -> 326700.22 | J95: =+I95-G95 -> 35810.44 | K95: =VLOOKUP(A95,'TFA-Sept,25'!$B$9:$C$136,2,0)+63015 -> 436283.26 | L95: =+K95-I95 -> 109583.04 | M95: =VLOOKUP(A95,'PL-TFA-Oct'!$B$9:$C$138,2,0)+29605 -> 486474.98 | N95: =+M95-K95 -> 50191.72 | O95: =VLOOKUP(A95,'TFA-Nov,25'!$B$10:$C$144,2,0) -> 543738.74 | P95: =+O95-M95 -> 57263.76 | Q95: =VLOOKUP(A95,'TB-TFL-A-Dec,25'!$B$10:$C$147,2,0)+71447 -> 620555.74 | R95: =+Q95-O95 -> 76817 | S95: =VLOOKUP(A95,'TB-TFL-A-Jan,26'!$B$9:$C$151,2,0)+41743 -> 715918.44 | T95: =+S95-Q95 -> 95362.7 | U95: =VLOOKUP(A95,'TB-Feb,26-a'!$B$10:$C$153,2,0)+99162 -> 781330.44 | V95: =+U95-S95 -> 65412
A96: CONVEYANCE RE-IMBURSEMENT | B96: =VLOOKUP(A96,'TFL A-April,25'!$B$9:$C$95,2,0) -> 112531 | C96: =VLOOKUP(A96,'May-A'!$B$10:$C$103,2,0) -> 314618 | D96: =+C96-B96 -> 202087 | E96: =VLOOKUP(A96,'June,25-A'!$B$10:$C$123,2,0) -> 436862 | F96: =+E96-C96 -> 122244 | G96: =VLOOKUP(A96,'July-A'!$B$10:$C$129,2,0) -> 594613 | H96: =+G96-E96 -> 157751 | I96: =VLOOKUP(A96,'TB-A-Aug'!$B$10:$C$132,2,0) -> 740747 | J96: =+I96-G96 -> 146134 | K96: =VLOOKUP(A96,'TFA-Sept,25'!$B$9:$C$136,2,0) -> 912109 | L96: =+K96-I96 -> 171362 | M96: =VLOOKUP(A96,'PL-TFA-Oct'!$B$9:$C$138,2,0) -> 1134569 | N96: =+M96-K96 -> 222460 | O96: =VLOOKUP(A96,'TFA-Nov,25'!$B$10:$C$144,2,0) -> 1388181 | P96: =+O96-M96 -> 253612 | Q96: =VLOOKUP(A96,'TB-TFL-A-Dec,25'!$B$10:$C$147,2,0) -> 1536321 | R96: =+Q96-O96 -> 148140 | S96: =VLOOKUP(A96,'TB-TFL-A-Jan,26'!$B$9:$C$151,2,0) -> 1671868 | T96: =+S96-Q96 -> 135547 | U96: =VLOOKUP(A96,'TB-Feb,26-a'!$B$10:$C$153,2,0) -> 1850082 | V96: =+U96-S96 -> 178214
A97: TRAVELLING EXPENSES | B97: =VLOOKUP(A97,'TFL A-April,25'!$B$9:$C$95,2,0) -> 202772.75 | C97: =VLOOKUP(A97,'May-A'!$B$10:$C$103,2,0) -> 723256.55 | D97: =+C97-B97 -> 520483.8 | E97: =VLOOKUP(A97,'June,25-A'!$B$10:$C$123,2,0)-Prepaid!F10 -> 1015166 | F97: =+E97-C97 -> 291909.49 | G97: =VLOOKUP(A97,'July-A'!$B$10:$C$129,2,0)-Prepaid!G10 -> 1400483.7 | H97: =+G97-E97 -> 385317.68 | I97: =VLOOKUP(A97,'TB-A-Aug'!$B$10:$C$132,2,0)-Prepaid!H10 -> 1789059.5 | J97: =+I97-G97 -> 388575.78 | K97: =VLOOKUP(A97,'TFA-Sept,25'!$B$9:$C$136,2,0)+5679-Prepaid!I10 -> 2154280.6 | L97: =+K97-I97 -> 365221.08 | M97: =VLOOKUP(A97,'PL-TFA-Oct'!$B$9:$C$138,2,0)-Prepaid!J10 -> 2585546 | N97: =+M97-K97 -> 431265.4 | O97: =VLOOKUP(A97,'TFA-Nov,25'!$B$10:$C$144,2,0)-Prepaid!K10 -> 2823586.1 | P97: =+O97-M97 -> 238040.08 | Q97: =VLOOKUP(A97,'TB-TFL-A-Dec,25'!$B$10:$C$147,2,0)-Prepaid!L10 -> 3243823.7 | R97: =+Q97-O97 -> 420237.61 | S97: =VLOOKUP(A97,'TB-TFL-A-Jan,26'!$B$9:$C$151,2,0)-Prepaid!M10 -> 3589408.8 | T97: =+S97-Q97 -> 345585.08 | U97: =VLOOKUP(A97,'TB-Feb,26-a'!$B$10:$C$153,2,0)-Prepaid!N10 -> 3808571.7 | V97: =+U97-S97 -> 219162.9
A98: GST EXPENSES-NOT CLAIMABLE-REVENUE | B98: =VLOOKUP(A98,'TFL A-April,25'!$B$9:$C$95,2,0) -> 43574.94 | C98: =VLOOKUP(A98,'May-A'!$B$10:$C$103,2,0) -> 49108.94 | D98: =+C98-B98 -> 5534 | E98: =VLOOKUP(A98,'June,25-A'!$B$10:$C$123,2,0) -> 56205.16 | F98: =+E98-C98 -> 7096.22 | G98: =VLOOKUP(A98,'July-A'!$B$10:$C$129,2,0) -> 81359.4 | H98: =+G98-E98 -> 25154.24 | I98: =VLOOKUP(A98,'TB-A-Aug'!$B$10:$C$132,2,0) -> 105974.4 | J98: =+I98-G98 -> 24615 | K98: =VLOOKUP(A98,'TFA-Sept,25'!$B$9:$C$136,2,0) -> 137299.04 | L98: =+K98-I98 -> 31324.64 | M98: =VLOOKUP(A98,'PL-TFA-Oct'!$B$9:$C$138,2,0) -> 156392.99 | N98: =+M98-K98 -> 19093.95 | O98: =VLOOKUP(A98,'TFA-Nov,25'!$B$10:$C$144,2,0) -> 181534.99 | P98: =+O98-M98 -> 25142 | Q98: =VLOOKUP(A98,'TB-TFL-A-Dec,25'!$B$10:$C$147,2,0) -> 193552.99 | R98: =+Q98-O98 -> 12018 | S98: =VLOOKUP(A98,'TB-TFL-A-Jan,26'!$B$9:$C$151,2,0) -> 211784.23 | T98: =+S98-Q98 -> 18231.24 | U98: =VLOOKUP(A98,'TB-Feb,26-a'!$B$10:$C$153,2,0) -> 223845.87 | V98: =+U98-S98 -> 12061.64
A99: POSTAGE & TELEGRAM | B99: =VLOOKUP(A99,'TFL A-April,25'!$B$9:$C$95,2,0)+48469 -> 230608.12 | C99: =VLOOKUP(A99,'May-A'!$B$10:$C$103,2,0) -> 405140.26 | D99: =+C99-B99 -> 174532.14 | E99: =VLOOKUP(A99,'June,25-A'!$B$10:$C$123,2,0)+33051 -> 635556.73 | F99: =+E99-C99 -> 230416.47 | G99: =VLOOKUP(A99,'July-A'!$B$10:$C$129,2,0)+82065 -> 888717.07 | H99: =+G99-E99 -> 253160.34 | I99: =VLOOKUP(A99,'TB-A-Aug'!$B$10:$C$132,2,0)+74878 -> 1266026.4 | J99: =+I99-G99 -> 377309.28 | K99: =VLOOKUP(A99,'TFA-Sept,25'!$B$9:$C$136,2,0)+78242 -> 1832512.4 | L99: =+K99-I99 -> 566486.07 | M99: =VLOOKUP(A99,'PL-TFA-Oct'!$B$9:$C$138,2,0)+44068 -> 2022888 | N99: =+M99-K99 -> 190375.54 | O99: =VLOOKUP(A99,'TFA-Nov,25'!$B$10:$C$144,2,0)+63559.34+132215 -> 2576432.6 | P99: =+O99-M99 -> 553544.69 | Q99: =VLOOKUP(A99,'TB-TFL-A-Dec,25'!$B$10:$C$147,2,0)+127761 -> 2942534.5 | R99: =+Q99-O99 -> 366101.87 | S99: =VLOOKUP(A99,'TB-TFL-A-Jan,26'!$B$9:$C$151,2,0)+116334+42343 -> 3298594.5 | T99: =+S99-Q99 -> 356059.96 | U99: =VLOOKUP(A99,'TB-Feb,26-a'!$B$10:$C$153,2,0)+102273+371852 -> 3792426.4 | V99: =+U99-S99 -> 493831.95
A100: TELEPHONE EXPENSES | B100: =VLOOKUP(A100,'TFL A-April,25'!$B$9:$C$95,2,0) -> -8460.32 | C100: =VLOOKUP(A100,'May-A'!$B$10:$C$103,2,0) -> -17094.5 | D100: =+C100-B100 -> -8634.18 | E100: =VLOOKUP(A100,'June,25-A'!$B$10:$C$123,2,0) -> -25669.68 | F100: =+E100-C100 -> -8575.18 | G100: =VLOOKUP(A100,'July-A'!$B$10:$C$129,2,0) -> -33945.86 | H100: =+G100-E100 -> -8276.18 | I100: =VLOOKUP(A100,'TB-A-Aug'!$B$10:$C$132,2,0) -> -41411.6 | J100: =+I100-G100 -> -7465.74 | K100: =VLOOKUP(A100,'TFA-Sept,25'!$B$9:$C$136,2,0) -> -49680.88 | L100: =+K100-I100 -> -8269.28 | M100: =VLOOKUP(A100,'PL-TFA-Oct'!$B$9:$C$138,2,0) -> -50630.56 | N100: =+M100-K100 -> -949.68 | O100: =VLOOKUP(A100,'TFA-Nov,25'!$B$10:$C$144,2,0) -> -58057.74 | P100: =+O100-M100 -> -7427.18 | Q100: =VLOOKUP(A100,'TB-TFL-A-Dec,25'!$B$10:$C$147,2,0) -> -61011.92 | R100: =+Q100-O100 -> -2954.18 | S100: =VLOOKUP(A100,'TB-TFL-A-Jan,26'!$B$9:$C$151,2,0) -> -66367.1 | T100: =+S100-Q100 -> -5355.18 | U100: =VLOOKUP(A100,'TB-Feb,26-a'!$B$10:$C$153,2,0) -> -67246.28 | V100: =+U100-S100 -> -879.18
A101: CERTIFICATION CHARGES | D101: =+C101-B101 -> 0 | F101: =+E101-C101 -> 0 | H101: =+G101-E101 -> 0 | J101: =+I101-G101 -> 0 | L101: =+K101-I101 -> 0 | N101: =+M101-K101 -> 0 | P101: =+O101-M101 -> 0 | R101: =+Q101-O101 -> 0 | T101: =+S101-Q101 -> 0 | V101: =+U101-S101 -> 0
A102: COMPUTER EXPENSES PAID | B102: =VLOOKUP(A102,'TFL A-April,25'!$B$9:$C$95,2,0) -> 13000 | C102: =VLOOKUP(A102,'May-A'!$B$10:$C$103,2,0) -> 26300 | D102: =+C102-B102 -> 13300 | E102: =VLOOKUP(A102,'June,25-A'!$B$10:$C$123,2,0) -> 36670.4 | F102: =+E102-C102 -> 10370.4 | G102: =VLOOKUP(A102,'July-A'!$B$10:$C$129,2,0) -> 36670.4 | H102: =+G102-E102 -> 0 | I102: =VLOOKUP(A102,'TB-A-Aug'!$B$10:$C$132,2,0) -> 36670.4 | J102: =+I102-G102 -> 0 | K102: =VLOOKUP(A102,'TFA-Sept,25'!$B$9:$C$136,2,0)-27150 -> 39120.4 | L102: =+K102-I102 -> 2450 | M102: =VLOOKUP(A102,'PL-TFA-Oct'!$B$9:$C$138,2,0) -> 39120.6 | N102: =+M102-K102 -> 0.2 | O102: =VLOOKUP(A102,'TFA-Nov,25'!$B$10:$C$144,2,0) -> 46806.04 | P102: =+O102-M102 -> 7685.44 | Q102: =VLOOKUP(A102,'TB-TFL-A-Dec,25'!$B$10:$C$147,2,0) -> 55606.04 | R102: =+Q102-O102 -> 8800 | S102: =VLOOKUP(A102,'TB-TFL-A-Jan,26'!$B$9:$C$151,2,0) -> 55606.04 | T102: =+S102-Q102 -> 0 | U102: =VLOOKUP(A102,'TB-Feb,26-a'!$B$10:$C$153,2,0) -> 130606.04 | V102: =+U102-S102 -> 75000
A103: FACTORY CLEANING CHARGES | C103: =VLOOKUP(A103,'May-A'!$B$10:$C$103,2,0) -> 66675 | D103: =+C103-B103 -> 66675 | E103: =VLOOKUP(A103,'June,25-A'!$B$10:$C$123,2,0)+40941 -> 107616 | F103: =+E103-C103 -> 40941 | G103: =VLOOKUP(A103,'July-A'!$B$10:$C$129,2,0)+32886 -> 150822.1 | H103: =+G103-E103 -> 43206.1 | I103: =VLOOKUP(A103,'TB-A-Aug'!$B$10:$C$132,2,0) -> 221331.08 | J103: =+I103-G103 -> 70508.98 | K103: =VLOOKUP(A103,'TFA-Sept,25'!$B$9:$C$136,2,0)+34200 -> 255531.08 | L103: =+K103-I103 -> 34200 | M103: =VLOOKUP(A103,'PL-TFA-Oct'!$B$9:$C$138,2,0)+42041 -> 316287.76 | N103: =+M103-K103 -> 60756.68 | O103: =VLOOKUP(A103,'TFA-Nov,25'!$B$10:$C$144,2,0)+49746 -> 405666.32 | P103: =+O103-M103 -> 89378.56 | Q103: =VLOOKUP(A103,'TB-TFL-A-Dec,25'!$B$10:$C$147,2,0)+13000 -> 460533.32 | R103: =+Q103-O103 -> 54867 | S103: =VLOOKUP(A103,'TB-TFL-A-Jan,26'!$B$9:$C$151,2,0) -> 499724.5 | T103: =+S103-Q103 -> 39191.18 | U103: =VLOOKUP(A103,'TB-Feb,26-a'!$B$10:$C$153,2,0)+41942 -> 541666.5 | V103: =+U103-S103 -> 41942
A104: FACTORY LICENCE FEES | D104: =+C104-B104 -> 0 | E104: =VLOOKUP(A104,'June,25-A'!$B$10:$C$123,2,0)-Prepaid!F7 -> 19689 | F104: =+E104-C104 -> 19689 | G104: =VLOOKUP(A104,'July-A'!$B$10:$C$129,2,0)-Prepaid!G7 -> 26252 | H104: =+G104-E104 -> 6563 | I104: =VLOOKUP(A104,'TB-A-Aug'!$B$10:$C$132,2,0)-Prepaid!H7 -> 32815 | J104: =+I104-G104 -> 6563 | K104: =VLOOKUP(A104,'TFA-Sept,25'!$B$9:$C$136,2,0)-Prepaid!I7 -> 39378 | L104: =+K104-I104 -> 6563 | M104: =VLOOKUP(A104,'PL-TFA-Oct'!$B$9:$C$138,2,0)-Prepaid!J7 -> 45941 | N104: =+M104-K104 -> 6563 | O104: =VLOOKUP(A104,'TFA-Nov,25'!$B$10:$C$144,2,0)-Prepaid!K7 -> 52504 | P104: =+O104-M104 -> 6563 | Q104: =VLOOKUP(A104,'TB-TFL-A-Dec,25'!$B$10:$C$147,2,0)-Prepaid!L7 -> 59067 | R104: =+Q104-O104 -> 6563 | S104: =VLOOKUP(A104,'TB-TFL-A-Jan,26'!$B$9:$C$151,2,0)-Prepaid!M7 -> 65630 | T104: =+S104-Q104 -> 6563 | U104: =VLOOKUP(A104,'TB-Feb,26-a'!$B$10:$C$153,2,0)-Prepaid!N7 -> 72193 | V104: =+U104-S104 -> 6563
...

Sheet Profit Loss-Betul-25-26
A1: TECHNOCRAFT FASHIONS LIMITED-BETUL
A3: Profit & Loss for the period ended Feb, 2026
A6: PARTICULARS | B6: April, 25 | C6: Upto May, 25 | D6: For May, 25 | E6: Upto June, 25 | F6: For June, 25 | G6: Upto July, 25 | H6: For July, 25 | I6: Upto August, 25 | J6: For Aug, 25 | K6: Upto Sept, 25 | L6: For Sept, 25 | M6: Upto Oct, 25 | N6: For Oct, 25 | O6: Upto Nov, 25 | P6: For Nov, 25 | Q6: Upto Dec, 25 | R6: For Dec, 25 | S6: Upto Jan, 26 | T6: For Jan, 26 | U6: Upto Feb, 26 | V6: For Feb, 26
A7: INCOME
A8: SALES
A9: SALES (LABOUR JOB) - INTER UNIT | B9: =VLOOKUP(A9,'TFL- B-April,25'!$B$9:$C$33,2,0) -> 1501872 | C9: =VLOOKUP(A9,'May-B'!$B$9:$C$39,2,0) -> 2501098 | D9: =+C9-B9 -> 999226 | E9: =VLOOKUP(A9,'June,25-B'!$B$9:$C$46,2,0) -> 5286179 | F9: =+E9-C9 -> 2785081 | G9: =VLOOKUP(A9,'July-B'!$B$9:$C$51,2,0) -> 9026583 | H9: =+G9-E9 -> 3740404 | I9: =VLOOKUP(A9,'TB-B-Aug'!$B$1:$C$53,2,0) -> 12193532 | J9: =+I9-G9 -> 3166949 | K9: =VLOOKUP(A9,'TFB-Sept,25'!$B$9:$C$54,2,0) -> 15382914 | L9: =+K9-I9 -> 3189382 | M9: =VLOOKUP(A9,'PL-TFB-Oct'!$B$9:$C$57,2,0) -> 16435708 | N9: =+M9-K9 -> 1052794 | O9: {=VLOOKUP(A9,+'TFB-Nov,25'!$B$9:$C$58,2,0)} -> 18524580 | P9: =+O9-M9 -> 2088872 | Q9: =VLOOKUP(A9,'TB -TFL-B-Dec,25'!$B$9:$C$62,2,0) -> 21712831 | R9: =+Q9-O9 -> 3188251 | S9: =VLOOKUP(A9,'TB-TFL-B-Jan,26'!$B$9:$C$67,2,0) -> 25000388 | T9: =+S9-Q9 -> 3287557 | U9: =VLOOKUP(A9,'TB-Feb,26-B'!$B$9:$C$67,2,0) -> 27034065 | V9: =+U9-S9 -> 2033677
A10: GROSS SALES | B10: =SUM(B9:B9) -> 1501872 | C10: =SUM(C9:C9) -> 2501098 | D10: =SUM(D9:D9) -> 999226 | E10: =SUM(E9:E9) -> 5286179 | F10: =SUM(F9:F9) -> 2785081 | G10: =SUM(G9:G9) -> 9026583 | H10: =SUM(H9:H9) -> 3740404 | I10: =SUM(I9:I9) -> 12193532 | ... V10: =SUM(V9:V9) -> 2033677
A11: EXPENSES RELATED TO SALES
A12: DETENTION CHARGES ON EXPORT
A13: DELIVERY CHARGES ON SALES | E13: =VLOOKUP(A13,'June,25-B'!$B$9:$C$46,2,0) -> 12500 | F13: =+E13-C13 -> 12500 | G13: =VLOOKUP(A13,'July-B'!$B$9:$C$51,2,0) -> 12500 | H13: =+G13-E13 -> 0 | I13: =VLOOKUP(A13,'TB-B-Aug'!$B$1:$C$53,2,0) -> 12500 | J13: =+I13-G13 -> 0 | K13: =VLOOKUP(A13,'TFB-Sept,25'!$B$9:$C$54,2,0) -> 12500 | L13: =+K13-I13 -> 0 | M13: =VLOOKUP(A13,'PL-TFB-Oct'!$B$9:$C$57,2,0) -> 12500 | N13: =+M13-K13 -> 0 | O13: {=VLOOKUP(A13,+'TFB-Nov,25'!$B$9:$C$58,2,0)} -> 12500 | P13: =+O13-M13 -> 0 | Q13: =VLOOKUP(A13,'TB -TFL-B-Dec,25'!$B$9:$C$62,2,0) -> 12500 | R13: =+Q13-O13 -> 0 | S13: =VLOOKUP(A13,'TB-TFL-B-Jan,26'!$B$9:$C$67,2,0) -> 12500 | T13: =+S13-Q13 -> 0 | U13: =VLOOKUP(A13,'TB-Feb,26-B'!$B$9:$C$67,2,0) -> 12500 | V13: =+U13-S13 -> 0
A14: DELIVERY CHARGES ON SALE -GARMENT | M14: =VLOOKUP(A14,'PL-TFB-Oct'!$B$9:$C$57,2,0)+12000 -> 18000 | N14: =+M14-K14 -> 18000 | O14: {=VLOOKUP(A14,+'TFB-Nov,25'!$B$9:$C$58,2,0)} -> 6000 | P14: =+O14-M14 -> -12000 | Q14: =VLOOKUP(A14,'TB -TFL-B-Dec,25'!$B$9:$C$62,2,0) -> 6000 | R14: =+Q14-O14 -> 0 | S14: =VLOOKUP(A14,'TB-TFL-B-Jan,26'!$B$9:$C$67,2,0) -> 6000 | T14: =+S14-Q14 -> 0 | U14: =VLOOKUP(A14,'TB-Feb,26-B'!$B$9:$C$67,2,0) -> 6000 | V14: =+U14-S14 -> 0
A15: TOTAL EXPENSES RELATED TO SALES | B15: =SUM(B12:B12) -> 0 | C15: =SUM(C12:C12) -> 0 | D15: =SUM(D12:D12) -> 0 | E15: =SUM(E12:E13) -> 12500 | F15: =SUM(F12:F13) -> 12500 | G15: =SUM(G12:G13) -> 12500 | H15: =SUM(H12:H13) -> 0 | I15: =SUM(I12:I13) -> 12500 | J15: =SUM(J12:J13) -> 0 | K15: =SUM(K12:K13) -> 12500 | L15: =SUM(L12:L13) -> 0 | M15: =SUM(M13:M14) -> 30500 | N15: =SUM(N13:N14) -> 18000 | O15: =SUM(O13:O14) -> 18500 | P15: =SUM(P13:P14) -> -12000 | Q15: =SUM(Q13:Q14) -> 18500 | R15: =SUM(R13:R14) -> 0 | S15: =SUM(S13:S14) -> 18500 | T15: =SUM(T13:T14) -> 0 | ... V15: =SUM(V13:V14) -> 0
A16: NET SALES | B16: =B10-B15 -> 1501872 | C16: =C10-C15 -> 2501098 | D16: =D10-D15 -> 999226 | E16: =E10-E15 -> 5273679 | F16: =F10-F15 -> 2772581 | G16: =G10-G15 -> 9014083 | H16: =H10-H15 -> 3740404 | I16: =I10-I15 -> 12181032 | ... V16: =V10-V15 -> 2033677
A17: OTHER OPERATING INCOME
A18: Rodtep Licence as per Accrual basis
A19: TOTAL OTHER OPERATING INCOME | B19: =SUM(B18:B18) -> 0 | C19: =SUM(C18:C18) -> 0 | D19: =SUM(D18:D18) -> 0 | E19: =SUM(E18:E18) -> 0 | F19: =SUM(F18:F18) -> 0 | G19: =SUM(G18:G18) -> 0 | H19: =SUM(H18:H18) -> 0 | I19: =SUM(I18:I18) -> 0 | ... V19: =SUM(V18:V18) -> 0
A20: REVENUE FROM OPERATIONS | B20: =B16+B19 -> 1501872 | C20: =C16+C19 -> 2501098 | D20: =D16+D19 -> 999226 | E20: =E16+E19 -> 5273679 | F20: =F16+F19 -> 2772581 | G20: =G16+G19 -> 9014083 | H20: =H16+H19 -> 3740404 | I20: =I16+I19 -> 12181032 | ... V20: =V16+V19 -> 2033677
A22: EXPENSES
A23: COST OF GOODS SOLD
A24: OPENING STOCK
A25: DELIVERY CHARGES ON PURCHASES | G25: =VLOOKUP(A25,'July-B'!$B$9:$C$51,2,0) -> 400 | H25: =+G25-E25 -> 400 | I25: =VLOOKUP(A25,'TB-B-Aug'!$B$1:$C$18,2,0) -> 400 | J25: =+I25-G25 -> 0 | K25: =VLOOKUP(A25,'TFB-Sept,25'!$B$9:$C$54,2,0) -> 400 | L25: =+K25-I25 -> 0 | M25: =VLOOKUP(A25,'PL-TFB-Oct'!$B$9:$C$57,2,0)+1070 -> 1470 | N25: =+M25-K25 -> 1070 | O25: {=VLOOKUP(A25,+'TFB-Nov,25'!$B$9:$C$58,2,0)+'TFB-Nov,25'!C11} -> 13190 | P25: =+O25-M25 -> 11720 | Q25: =VLOOKUP(A25,'TB -TFL-B-Dec,25'!$B$9:$C$62,2,0) -> 2370 | R25: =+Q25-O25 -> -10820 | S25: =VLOOKUP(A25,'TB-TFL-B-Jan,26'!$B$9:$C$67,2,0) -> 2370 | T25: =+S25-Q25 -> 0 | U25: =VLOOKUP(A25,'TB-Feb,26-B'!$B$9:$C$67,2,0) -> 2370 | V25: =+U25-S25 -> 0
A26: JOB WORK | S26: =VLOOKUP(A26,'TB-TFL-B-Jan,26'!$B$9:$C$67,2,0) -> 50381.2 | T26: =+S26-Q26 -> 50381.2 | U26: =VLOOKUP(A26,'TB-Feb,26-B'!$B$9:$C$67,2,0) -> 142097.9 | V26: =+U26-S26 -> 91716.7
A27: DELIVERY CHARGES - PURCHASE-GARMENT | Q27: =VLOOKUP(A27,'TB -TFL-B-Dec,25'!$B$9:$C$62,2,0)-10820+10820 -> 45070 | R27: =+Q27-O27 -> 45070 | S27: =VLOOKUP(A27,'TB-TFL-B-Jan,26'!$B$9:$C$67,2,0) -> 45070 | T27: =+S27-Q27 -> 0 | U27: =VLOOKUP(A27,'TB-Feb,26-B'!$B$9:$C$67,2,0) -> 45070 | V27: =+U27-S27 -> 0
A28: CLOSING STOCK | R28: =+Q28-O28 -> 0 | T28: =+S28-Q28 -> 0 | V28: =+U28-S28 -> 0
A29: TOTAL COST OF GOODS SOLD | B29: =+B24-B28 -> 0 | C29: =+C24-C28 -> 0 | D29: =+D24-D28 -> 0 | E29: =+E24-E28 -> 0 | F29: =+F24-F28 -> 0 | G29: =+G24+G25-G28 -> 400 | H29: =+H24+H25-H28 -> 400 | I29: =+I24+I25-I28 -> 400 | J29: =+J24+J25-J28 -> 0 | K29: =+K24+K25-K28 -> 400 | L29: =+L24+L25-L28 -> 0 | M29: =+M24+M25-M28 -> 1470 | N29: =+N24+N25-N28 -> 1070 | ... P29: =+P24+P25-P28 -> 11720 | Q29: =+Q24+Q25-Q28+Q27 -> 47440 | R29: =+R24+R25-R28+R27 -> 34250 | S29: =SUM(S25:S27) -> 97821.2 | T29: =SUM(T25:T27) -> 50381.2 | U29: =SUM(U25:U27) -> 189537.9 | V29: =SUM(V25:V27) -> 91716.7
A30: CONTRIBUTION / GROSS PROFIT | B30: =B20-B29 -> 1501872 | C30: =C20-C29 -> 2501098 | D30: =D20-D29 -> 999226 | E30: =E20-E29 -> 5273679 | F30: =F20-F29 -> 2772581 | G30: =G20-G29 -> 9013683 | H30: =H20-H29 -> 3740004 | I30: =I20-I29 -> 12180632 | ... V30: =V20-V29 -> 1941960.3
A31: CONTRIBUTION / GROSS PROFIT (% of Revenue) | B31: =+B30/B20 -> 1 | C31: =+C30/C20 -> 1 | D31: =+D30/D20 -> 1 | E31: =+E30/E20 -> 1 | F31: =+F30/F20 -> 1 | G31: =+G30/G20 -> 0.99995562 | H31: =+H30/H20 -> 0.99989306 | I31: =+I30/I20 -> 0.99996716 | ... V31: =+V30/V20 -> 0.95490105
A32: FIXED EXPENSES
A33: JEEP HIRE EXPENSES | D33: =+C33-B33 -> 0 | F33: =+E33-D33 -> 0 | G33: =VLOOKUP(A33,'July-B'!$B$9:$C$51,2,0) -> 30100 | H33: =+G33-F33 -> 30100 | I33: =VLOOKUP(A33,'TB-B-Aug'!$B$1:$C$53,2,0) -> 43400 | J33: =+I33-H33 -> 13300 | K33: =VLOOKUP(A33,'TFB-Sept,25'!$B$9:$C$54,2,0) -> 43400 | L33: =+K33-I33 -> 0 | M33: =VLOOKUP(A33,'PL-TFB-Oct'!$B$9:$C$57,2,0) -> 46150 | N33: =+M33-K33 -> 2750 | O33: {=VLOOKUP(A33,+'TFB-Nov,25'!$B$9:$C$58,2,0)} -> 46150 | P33: =+O33-M33 -> 0 | Q33: =VLOOKUP(A33,'TB -TFL-B-Dec,25'!$B$9:$C$62,2,0) -> 46150 | R33: =+Q33-O33 -> 0 | S33: =VLOOKUP(A33,'TB-TFL-B-Jan,26'!$B$9:$C$67,2,0) -> 46150 | T33: =+S33-Q33 -> 0 | U33: =VLOOKUP(A33,'TB-Feb,26-B'!$B$9:$C$67,2,0) -> 46150 | V33: =+U33-S33 -> 0
A34: PURCHASE STORES & SPARES | B34: =VLOOKUP(A34,'TFL- B-April,25'!$B$9:$C$64,2,0) -> 2730 | C34: =VLOOKUP(A34,'May-B'!$B$9:$C$39,2,0) -> 5340 | D34: =+C34-B34 -> 2610 | E34: =VLOOKUP(A34,'June,25-B'!$B$9:$C$46,2,0) -> 5340 | F34: =+E34-C34 -> 0 | G34: =VLOOKUP(A34,'July-B'!$B$9:$C$51,2,0) -> 6497 | H34: =+G34-E34 -> 1157 | I34: =VLOOKUP(A34,'TB-B-Aug'!$B$1:$C$53,2,0) -> 11917 | J34: =+I34-G34 -> 5420 | K34: =VLOOKUP(A34,'TFB-Sept,25'!$B$9:$C$54,2,0) -> 11917 | L34: =+K34-I34 -> 0 | M34: =VLOOKUP(A34,'PL-TFB-Oct'!$B$9:$C$57,2,0) -> 34338 | N34: =+M34-K34 -> 22421 | O34: {=VLOOKUP(A34,+'TFB-Nov,25'!$B$9:$C$58,2,0)} -> 46563 | P34: =+O34-M34 -> 12225 | Q34: =VLOOKUP(A34,'TB -TFL-B-Dec,25'!$B$9:$C$62,2,0) -> 51152 | R34: =+Q34-O34 -> 4589 | S34: =VLOOKUP(A34,'TB-TFL-B-Jan,26'!$B$9:$C$67,2,0) -> 51152 | T34: =+S34-Q34 -> 0 | U34: =VLOOKUP(A34,'TB-Feb,26-B'!$B$9:$C$67,2,0) -> 51152 | V34: =+U34-S34 -> 0
A35: PURCHASE STORES & SPARES (GARMENT) | B35: =VLOOKUP(A35,'TFL- B-April,25'!$B$9:$C$64,2,0)+40975 -> 73178.92 | C35: =VLOOKUP(A35,'May-B'!$B$9:$C$39,2,0) -> 170665.58 | D35: =+C35-B35 -> 97486.66 | E35: =VLOOKUP(A35,'June,25-B'!$B$9:$C$46,2,0) -> 259554 | F35: =+E35-C35 -> 88888.42 | G35: =VLOOKUP(A35,'July-B'!$B$9:$C$51,2,0) -> 400539.68 | H35: =+G35-E35 -> 140985.68 | I35: =VLOOKUP(A35,'TB-B-Aug'!$B$1:$C$53,2,0) -> 452689.68 | J35: =+I35-G35 -> 52150 | K35: =VLOOKUP(A35,'TFB-Sept,25'!$B$9:$C$54,2,0)+7822 -> 478682.28 | L35: =+K35-I35 -> 25992.6 | M35: =VLOOKUP(A35,'PL-TFB-Oct'!$B$9:$C$57,2,0)+38480 -> 509340.28 | N35: =+M35-K35 -> 30658 | O35: {=VLOOKUP(A35,+'TFB-Nov,25'!$B$9:$C$58,2,0)} -> 631653.67 | P35: =+O35-M35 -> 122313.39 | Q35: =VLOOKUP(A35,'TB -TFL-B-Dec,25'!$B$9:$C$62,2,0) -> 882569.46 | R35: =+Q35-O35 -> 250915.79 | S35: =VLOOKUP(A35,'TB-TFL-B-Jan,26'!$B$9:$C$67,2,0)+9600-1670 -> 923959.56 | T35: =+S35-Q35 -> 41390.1 | U35: =VLOOKUP(A35,'TB-Feb,26-B'!$B$9:$C$67,2,0) -> 1103395.1 | V35: =+U35-S35 -> 179435.49
A36: POWER | B36: 146247 | C36: =VLOOKUP(A36,'May-B'!$B$9:$C$39,2,0)+154281 -> 300528 | D36: =+C36-B36 -> 154281 | E36: =VLOOKUP(A36,'June,25-B'!$B$9:$C$46,2,0)+150000 -> 450528 | F36: =+E36-C36 -> 150000 | G36: =VLOOKUP(A36,'July-B'!$B$9:$C$51,2,0)+185682 -> 668010 | H36: =+G36-E36 -> 217482 | I36: =VLOOKUP(A36,'TB-B-Aug'!$B$1:$C$53,2,0)+185000 -> 853010 | J36: =+I36-G36 -> 185000 | K36: =VLOOKUP(A36,'TFB-Sept,25'!$B$9:$C$54,2,0)+150000 -> 985942 | L36: =+K36-I36 -> 132932 | M36: =VLOOKUP(A36,'PL-TFB-Oct'!$B$9:$C$57,2,0) -> 1135660 | N36: =+M36-K36 -> 149718 | O36: {=VLOOKUP(A36,+'TFB-Nov,25'!$B$9:$C$58,2,0)+88091+88605+21001} -> 1333357 | P36: =+O36-M36 -> 197697 | Q36: =VLOOKUP(A36,'TB -TFL-B-Dec,25'!$B$9:$C$62,2,0) -> 1480619 | R36: =+Q36-O36 -> 147262 | S36: =VLOOKUP(A36,'TB-TFL-B-Jan,26'!$B$9:$C$67,2,0) -> 1672586 | T36: =+S36-Q36 -> 191967 | U36: =VLOOKUP(A36,'TB-Feb,26-B'!$B$9:$C$67,2,0)+179597 -> 1852183 | V36: =+U36-S36 -> 179597
A37: FUEL & OIL | C37: =VLOOKUP(A37,'May-B'!$B$9:$C$39,2,0) -> 6700 | D37: =+C37-B37 -> 6700 | E37: =VLOOKUP(A37,'June,25-B'!$B$9:$C$46,2,0) -> 6700 | F37: =+E37-C37 -> 0 | G37: =VLOOKUP(A37,'July-B'!$B$9:$C$51,2,0) -> 6700 | H37: =+G37-E37 -> 0 | I37: =VLOOKUP(A37,'TB-B-Aug'!$B$1:$C$53,2,0) -> 6700 | J37: =+I37-G37 -> 0 | K37: =VLOOKUP(A37,'TFB-Sept,25'!$B$9:$C$54,2,0) -> 6700 | L37: =+K37-I37 -> 0 | M37: =VLOOKUP(A37,'PL-TFB-Oct'!$B$9:$C$57,2,0) -> 6700 | N37: =+M37-K37 -> 0 | O37: {=VLOOKUP(A37,+'TFB-Nov,25'!$B$9:$C$58,2,0)} -> 6700 | P37: =+O37-M37 -> 0 | Q37: =VLOOKUP(A37,'TB -TFL-B-Dec,25'!$B$9:$C$62,2,0)+1670 -> 8370 | R37: =+Q37-O37 -> 1670 | S37: =VLOOKUP(A37,'TB-TFL-B-Jan,26'!$B$9:$C$67,2,0)+1670 -> 8370 | T37: =+S37-Q37 -> 0 | U37: =VLOOKUP(A37,'TB-Feb,26-B'!$B$9:$C$67,2,0) -> 13450 | V37: =+U37-S37 -> 5080
